{
  "type": "Feature",
  "properties": {
    "gn:admin1_code":"03",
    "gn:asciiname":"Kedey-Aryk",
    "gn:country_code":"KG",
    "gn:dem":902,
    "gn:feature_class":"P",
    "gn:feature_code":"PPL",
    "gn:name":"Kedey-Aryk",
    "gn:population":0,
    "gn:timezone":"Asia/Bishkek",
    "iso:country":"KG",
    "name:kir_x_preferred":[
        "\u041a\u0435\u0434\u0435\u0439-\u0410\u0440\u044b\u043a"
    ],
    "name:rus_x_preferred":[
        "\u041a\u0435\u0434\u0435\u0439-\u0410\u0440\u044b\u043a"
    ],
    "name:und_x_variant":[
        "Gaday-Aryk"
    ],
    "wof:name":"Kedey-Aryk",
    "wof:placetype":"locality"
},
  "geometry": {"coordinates":[73.06534000000001,41.00526],"type":"Point"}
}