{
  "type": "Feature",
  "properties": {
    "gn:admin1_code":"04",
    "gn:asciiname":"Ak-Kul'",
    "gn:country_code":"KG",
    "gn:dem":1783,
    "gn:feature_class":"P",
    "gn:feature_code":"PPL",
    "gn:name":"Ak-Kul\u2019",
    "gn:population":0,
    "gn:timezone":"Asia/Bishkek",
    "iso:country":"KG",
    "name:kir_x_preferred":[
        "\u0410\u043a-\u041a\u04e9\u043b"
    ],
    "name:rus_x_preferred":[
        "\u0410\u043a-\u041a\u0443\u043b\u044c"
    ],
    "name:und_x_variant":[
        "Ak-Kul\u2019"
    ],
    "wof:name":"Ak-Kul'",
    "wof:placetype":"locality"
},
  "geometry": {"coordinates":[74.28686999999999,41.6738],"type":"Point"}
}