{
  "type": "Feature",
  "properties": {
    "gn:admin1_code":"02",
    "gn:asciiname":"Dmitriyevka",
    "gn:country_code":"KG",
    "gn:dem":741,
    "gn:feature_class":"P",
    "gn:feature_code":"PPL",
    "gn:name":"Dmitriyevka",
    "gn:population":0,
    "gn:timezone":"Asia/Bishkek",
    "iso:country":"KG",
    "name:kir_x_preferred":[
        "\u0414\u043c\u0438\u0442\u0440\u0438\u0435\u0432\u043a\u0430"
    ],
    "name:rus_x_preferred":[
        "\u0414\u043c\u0438\u0442\u0440\u0438\u0435\u0432\u043a\u0430"
    ],
    "wof:name":"Dmitriyevka",
    "wof:placetype":"locality"
},
  "geometry": {"coordinates":[74.90163000000003,42.89434],"type":"Point"}
}