{
  "type": "Feature",
  "properties": {
    "gn:admin1_code":"03",
    "gn:asciiname":"Kyzylbiit",
    "gn:country_code":"KG",
    "gn:dem":1014,
    "gn:feature_class":"P",
    "gn:feature_code":"PPL",
    "gn:name":"Kyzylbiit",
    "gn:population":0,
    "gn:timezone":"Asia/Bishkek",
    "iso:country":"KG",
    "name:kir_x_preferred":[
        "\u041a\u044b\u0437\u044b\u043b-\u0411\u0438\u0438\u0442"
    ],
    "name:rus_x_preferred":[
        "\u041a\u044b\u0437\u044b\u043b\u0431\u0438\u0438\u0442"
    ],
    "name:und_x_variant":[
        "Kyzylbeyit",
        "Kyzylbiit"
    ],
    "wof:name":"Kyzylbiit",
    "wof:placetype":"locality"
},
  "geometry": {"coordinates":[72.40942,41.54448],"type":"Point"}
}