{
  "type": "Feature",
  "properties": {
    "gn:admin1_code":"08",
    "gn:asciiname":"Dashtepe",
    "gn:country_code":"KG",
    "gn:dem":2464,
    "gn:feature_class":"P",
    "gn:feature_code":"PPL",
    "gn:name":"Dashtepe",
    "gn:population":0,
    "gn:timezone":"Asia/Bishkek",
    "iso:country":"KG",
    "name:kir_x_preferred":[
        "\u0414\u0430\u0448\u0442\u0435\u043f\u0435"
    ],
    "name:rus_x_preferred":[
        "\u0414\u0430\u0448\u0442\u0435\u043f\u0435"
    ],
    "name:und_x_variant":[
        "Jash-Tilek"
    ],
    "wof:name":"Dashtepe",
    "wof:placetype":"locality"
},
  "geometry": {"coordinates":[72.08906999999998,39.54805],"type":"Point"}
}