{
  "type": "Feature",
  "properties": {
    "gn:admin1_code":"08",
    "gn:admin2_code":"7910405",
    "gn:asciiname":"Jany-Nookat",
    "gn:country_code":"KG",
    "gn:dem":1480,
    "gn:feature_class":"P",
    "gn:feature_code":"PPL",
    "gn:name":"Jany-Nookat",
    "gn:population":0,
    "gn:timezone":"Asia/Bishkek",
    "iso:country":"KG",
    "name:kir_x_preferred":[
        "\u0416\u0430\u04a3\u044b-\u041d\u043e\u043e\u043a\u0430\u0442"
    ],
    "name:rus_x_preferred":[
        "\u0414\u0436\u0430\u043d\u044b-\u041d\u043e\u043e\u043a\u0430\u0442"
    ],
    "name:und_x_variant":[
        "Dzhany-Nookat",
        "Yangi-Naukat"
    ],
    "wof:name":"Jany-Nookat",
    "wof:placetype":"locality"
},
  "geometry": {"coordinates":[72.55006,40.24833],"type":"Point"}
}