{
  "type": "Feature",
  "properties": {
    "gn:admin1_code":"09",
    "gn:asciiname":"Kaytpas",
    "gn:country_code":"KG",
    "gn:dem":512,
    "gn:feature_class":"P",
    "gn:feature_code":"PPL",
    "gn:name":"Kaytpas",
    "gn:population":0,
    "gn:timezone":"Asia/Bishkek",
    "iso:country":"KG",
    "name:kir_x_preferred":[
        "\u041a\u0430\u0439\u0442\u043f\u0430\u0441"
    ],
    "name:kir_x_variant":[
        "Kaitpas"
    ],
    "name:rus_x_preferred":[
        "\u041a\u0430\u0439\u0442\u043f\u0430\u0441"
    ],
    "name:und_x_variant":[
        "Murge-Dzhak"
    ],
    "name:uzb_x_preferred":[
        "Murgejak"
    ],
    "wof:name":"Kaytpas",
    "wof:placetype":"locality"
},
  "geometry": {"coordinates":[71.27294000000001,40.32782],"type":"Point"}
}