{
  "type": "Feature",
  "properties": {
    "gn:admin1_code":"02",
    "gn:asciiname":"Ak-Tyuz",
    "gn:country_code":"KG",
    "gn:dem":2206,
    "gn:feature_class":"P",
    "gn:feature_code":"PPL",
    "gn:name":"Ak-Tyuz",
    "gn:population":0,
    "gn:timezone":"Asia/Bishkek",
    "iso:country":"KG",
    "name:kir_x_preferred":[
        "Ak-T\u00fcz"
    ],
    "name:rus_x_preferred":[
        "\u0410\u043a-\u0422\u044e\u0437"
    ],
    "wof:name":"Ak-Tyuz",
    "wof:placetype":"locality"
},
  "geometry": {"coordinates":[76.13325999999998,42.87955],"type":"Point"}
}