{
  "type": "Feature",
  "properties": {
    "gn:admin1_code":"08",
    "gn:asciiname":"Seget",
    "gn:country_code":"KG",
    "gn:dem":1699,
    "gn:feature_class":"P",
    "gn:feature_code":"PPL",
    "gn:name":"Seget",
    "gn:population":0,
    "gn:timezone":"Asia/Bishkek",
    "iso:country":"KG",
    "name:kir_x_preferred":[
        "\u0421\u0435\u0433\u0435\u0442"
    ],
    "name:rus_x_preferred":[
        "\u0421\u0435\u0433\u0435\u0442"
    ],
    "wof:name":"Seget",
    "wof:placetype":"locality"
},
  "geometry": {"coordinates":[72.51357,40.18189],"type":"Point"}
}