{
  "type": "Feature",
  "properties": {
    "gn:admin1_code":"02",
    "gn:asciiname":"Krasnyy Vostok",
    "gn:country_code":"KG",
    "gn:dem":840,
    "gn:feature_class":"P",
    "gn:feature_code":"PPL",
    "gn:name":"Krasnyy Vostok",
    "gn:population":0,
    "gn:timezone":"Asia/Bishkek",
    "iso:country":"KG",
    "name:kir_x_preferred":[
        "\u041a\u0440\u0430\u0441\u043d\u044b\u0439 \u0412\u043e\u0441\u0442\u043e\u043a"
    ],
    "name:rus_x_preferred":[
        "\u041a\u0440\u0430\u0441\u043d\u044b\u0439 \u0412\u043e\u0441\u0442\u043e\u043a"
    ],
    "wof:name":"Krasnyy Vostok",
    "wof:placetype":"locality"
},
  "geometry": {"coordinates":[74.97787,42.80139000000001],"type":"Point"}
}