{
  "type": "Feature",
  "properties": {
    "gn:admin1_code":"03",
    "gn:asciiname":"Dzheti-Koshkon",
    "gn:country_code":"KG",
    "gn:dem":683,
    "gn:feature_class":"P",
    "gn:feature_code":"PPL",
    "gn:name":"Dzheti-Koshkon",
    "gn:population":0,
    "gn:timezone":"Asia/Bishkek",
    "iso:country":"KG",
    "name:kir_x_preferred":[
        "\u0416\u0435\u0442\u0438-\u041a\u043e\u0448\u043a\u043e\u043d"
    ],
    "name:rus_x_preferred":[
        "\u0414\u0436\u0435\u0442\u0438-\u041a\u043e\u0448\u043a\u043e\u043d"
    ],
    "name:und_x_variant":[
        "Chakan"
    ],
    "wof:name":"Dzheti-Koshkon",
    "wof:placetype":"locality"
},
  "geometry": {"coordinates":[72.73174,40.98999],"type":"Point"}
}