{
  "type": "Feature",
  "properties": {
    "gn:admin1_code":"09",
    "gn:asciiname":"Say",
    "gn:country_code":"KG",
    "gn:dem":1509,
    "gn:feature_class":"P",
    "gn:feature_code":"PPL",
    "gn:name":"Say",
    "gn:population":0,
    "gn:timezone":"Asia/Bishkek",
    "iso:country":"KG",
    "name:kir_x_preferred":[
        "\u0421\u0430\u0439"
    ],
    "name:kir_x_variant":[
        "Sai"
    ],
    "name:rus_x_preferred":[
        "\u0421\u0430\u0439"
    ],
    "name:uzb_x_preferred":[
        "Soy"
    ],
    "wof:name":"Say",
    "wof:placetype":"locality"
},
  "geometry": {"coordinates":[71.20549,39.90779000000001],"type":"Point"}
}