{
  "type": "Feature",
  "properties": {
    "gn:admin1_code":"09",
    "gn:asciiname":"Say",
    "gn:country_code":"KG",
    "gn:dem":1509,
    "gn:feature_class":"P",
    "gn:feature_code":"PPL",
    "gn:name":"Say",
    "gn:population":0,
    "gn:timezone":"Asia/Bishkek",
    "iso:country":"KG",
    "name:cat_x_preferred":[
        "Say"
    ],
    "name:ceb_x_preferred":[
        "Say"
    ],
    "name:deu_x_preferred":[
        "Say"
    ],
    "name:fin_x_preferred":[
        "Say"
    ],
    "name:fra_x_preferred":[
        "Say"
    ],
    "name:kir_x_preferred":[
        "\u0421\u0430\u0439"
    ],
    "name:kir_x_variant":[
        "Sai"
    ],
    "name:lat_x_preferred":[
        "Say"
    ],
    "name:nld_x_preferred":[
        "Say"
    ],
    "name:pol_x_preferred":[
        "Say"
    ],
    "name:rus_x_preferred":[
        "\u0421\u0430\u0439"
    ],
    "name:rus_x_variant":[
        "\u0421\u044d\u0439"
    ],
    "name:spa_x_preferred":[
        "Say"
    ],
    "name:swe_x_preferred":[
        "Say"
    ],
    "name:tur_x_preferred":[
        "Say"
    ],
    "name:uzb_x_preferred":[
        "Soy"
    ],
    "name:vie_x_preferred":[
        "S\u1eady"
    ],
    "wof:name":"Say",
    "wof:placetype":"locality"
},
  "geometry": {"coordinates":[71.20549,39.90779000000001],"type":"Point"}
}