{
  "type": "Feature",
  "properties": {
    "gn:admin1_code":"03",
    "gn:asciiname":"Karagandy",
    "gn:country_code":"KG",
    "gn:dem":868,
    "gn:feature_class":"P",
    "gn:feature_code":"PPL",
    "gn:name":"Karagandy",
    "gn:population":0,
    "gn:timezone":"Asia/Bishkek",
    "iso:country":"KG",
    "name:kir_x_preferred":[
        "\u041a\u0430\u0440\u0430\u0433\u0430\u043d\u0434\u044b"
    ],
    "name:rus_x_preferred":[
        "\u041a\u0430\u0440\u0430\u0433\u0430\u043d\u0434\u044b"
    ],
    "wof:name":"Karagandy",
    "wof:placetype":"locality"
},
  "geometry": {"coordinates":[72.14735999999998,41.38988],"type":"Point"}
}