{
  "type": "Feature",
  "properties": {
    "gn:admin1_code":"02",
    "gn:asciiname":"Birikken",
    "gn:country_code":"KG",
    "gn:dem":1169,
    "gn:feature_class":"P",
    "gn:feature_code":"PPL",
    "gn:name":"Birikken",
    "gn:population":0,
    "gn:timezone":"Asia/Bishkek",
    "iso:country":"KG",
    "name:kir_x_preferred":[
        "\u0411\u0438\u0440\u0438\u043a\u043a\u0435\u043d"
    ],
    "name:rus_x_preferred":[
        "\u0411\u0438\u0440\u0438\u043a\u043a\u0435\u043d"
    ],
    "wof:name":"Birikken",
    "wof:placetype":"locality"
},
  "geometry": {"coordinates":[75.14654,42.70134],"type":"Point"}
}