{
  "type": "Feature",
  "properties": {
    "gn:admin1_code":"03",
    "gn:asciiname":"Dzhildyz-Kel'",
    "gn:country_code":"KG",
    "gn:dem":1506,
    "gn:feature_class":"P",
    "gn:feature_code":"PPL",
    "gn:name":"Dzhildyz-K\u00ebl\u2019",
    "gn:population":0,
    "gn:timezone":"Asia/Bishkek",
    "iso:country":"KG",
    "name:kir_x_preferred":[
        "\u0416\u044b\u043b\u0434\u044b\u0437-\u041a\u04e9\u043b"
    ],
    "name:rus_x_preferred":[
        "Dzhildyz-K\u00ebl\u2019"
    ],
    "name:rus_x_variant":[
        "\u0414\u0436\u0438\u043b\u0434\u044b\u0437-\u041a\u0451\u043b\u044c"
    ],
    "wof:name":"Dzhildyz-Kel'",
    "wof:placetype":"locality"
},
  "geometry": {"coordinates":[73.19598000000001,41.33079],"type":"Point"}
}