{
  "type": "Feature",
  "properties": {
    "gn:admin1_code":"07",
    "gn:asciiname":"Zelenyy Gay",
    "gn:country_code":"KG",
    "gn:dem":1622,
    "gn:feature_class":"P",
    "gn:feature_code":"PPL",
    "gn:name":"Zelenyy Gay",
    "gn:population":0,
    "gn:timezone":"Asia/Bishkek",
    "iso:country":"KG",
    "name:kir_x_preferred":[
        "\u0417\u0435\u043b\u0435\u043d\u044b\u0439 \u0413\u0430\u0439"
    ],
    "name:rus_x_preferred":[
        "\u0417\u0435\u043b\u0435\u043d\u044b\u0439 \u0413\u0430\u0439"
    ],
    "name:und_x_variant":[
        "Koysara",
        "Kurort Koy-Sara",
        "Kurort Koysary",
        "Koysary",
        "Zelenyy Gay"
    ],
    "wof:name":"Zelenyy Gay",
    "wof:placetype":"locality"
},
  "geometry": {"coordinates":[78.16789,42.55038],"type":"Point"}
}