{
  "type": "Feature",
  "properties": {
    "iso:country":"KG",
    "name:ceb_x_preferred":[
        "Sary-Tash"
    ],
    "name:deu_x_preferred":[
        "Sarytasch"
    ],
    "name:eng_x_preferred":[
        "Sary-Tash"
    ],
    "name:ita_x_preferred":[
        "Sary Ta\u0161"
    ],
    "name:jpn_x_preferred":[
        "\u30b5\u30eb\uff1d\u30bf\u30b7\u30e5"
    ],
    "name:kir_x_preferred":[
        "\u0421\u0430\u0440\u044b\u0442\u0430\u0448 \u0448\u0430\u0430\u0440\u0447\u0430\u0441\u044b"
    ],
    "name:kir_x_variant":[
        "Sary-Tash"
    ],
    "name:lit_x_preferred":[
        "Sary Ta\u0161as"
    ],
    "name:nds_x_preferred":[
        "Sary-Tasch"
    ],
    "name:nld_x_preferred":[
        "Sary-Tash"
    ],
    "name:rup_x_preferred":[
        "Sary-Tash"
    ],
    "name:rus_x_preferred":[
        "\u0421\u0430\u0440\u044b-\u0422\u0430\u0448"
    ],
    "name:swe_x_preferred":[
        "Sary-Tash"
    ],
    "name:tur_x_preferred":[
        "Sar\u0131ta\u015f"
    ],
    "name:unk_x_variant":[
        "Saritash"
    ],
    "name:uzb_x_preferred":[
        "Sariq-Tosh"
    ],
    "name:zho_x_preferred":[
        "\u6492\u5229-\u5854\u4ec0"
    ],
    "qs:gn_country":"KG",
    "qs:gn_fcode":"PPL",
    "qs:gn_pop":0,
    "qs:name":"Sary-Tash",
    "qs:name_adm0":"Kyrgyzstan",
    "qs:name_adm1":"Osh",
    "qs:photos":147,
    "qs:photos_1k":30,
    "qs:photos_9k":1,
    "qs:photos_9r":3,
    "qs:photos_all":147,
    "qs:photos_sr":3,
    "qs:placetype":"Town",
    "qs:pop_sr":"4",
    "qs:woe_adm0":23424864,
    "wd:wordcount":221,
    "wof:name":"Sary-Tash",
    "wof:placetype":"locality"
},
  "geometry": {"coordinates":[73.24836000000001,39.72883],"type":"Point"}
}