{
  "type": "Feature",
  "properties": {
    "gn:admin1_code":"08",
    "gn:asciiname":"Imeni Karla Marksa",
    "gn:country_code":"KG",
    "gn:dem":965,
    "gn:feature_class":"P",
    "gn:feature_code":"PPL",
    "gn:name":"Imeni Karla Marksa",
    "gn:population":0,
    "gn:timezone":"Asia/Bishkek",
    "iso:country":"KG",
    "name:kir_x_preferred":[
        "\u041a\u0430\u0440\u043b \u041c\u0430\u0440\u043a\u0441 \u0410\u0442\u044b\u043d\u0434\u0430\u0433\u044b"
    ],
    "name:rus_x_preferred":[
        "\u0418\u043c\u0435\u043d\u0438 \u041a\u0430\u0440\u043b\u0430 \u041c\u0430\u0440\u043a\u0441\u0430"
    ],
    "wof:name":"Imeni Karla Marksa",
    "wof:placetype":"locality"
},
  "geometry": {"coordinates":[72.70394,40.55065],"type":"Point"}
}