{
  "type": "Feature",
  "properties": {
    "gn:admin1_code":"03",
    "gn:asciiname":"Kurulush",
    "gn:country_code":"KG",
    "gn:dem":602,
    "gn:feature_class":"P",
    "gn:feature_code":"PPL",
    "gn:name":"Kurulush",
    "gn:population":0,
    "gn:timezone":"Asia/Bishkek",
    "iso:country":"KG",
    "name:kir_x_preferred":[
        "\u041a\u0443\u0440\u0443\u043b\u0443\u0448"
    ],
    "name:rus_x_preferred":[
        "\u041a\u0443\u0440\u0443\u043b\u0443\u0448"
    ],
    "name:uzb_x_preferred":[
        "Qurulush"
    ],
    "wof:name":"Kurulush",
    "wof:placetype":"locality"
},
  "geometry": {"coordinates":[72.47005,41.03392],"type":"Point"}
}