{
  "type": "Feature",
  "properties": {
    "gn:admin1_code":"08",
    "gn:asciiname":"Kyungey",
    "gn:country_code":"KG",
    "gn:dem":1749,
    "gn:feature_class":"P",
    "gn:feature_code":"PPL",
    "gn:name":"Kyungey",
    "gn:population":0,
    "gn:timezone":"Asia/Bishkek",
    "iso:country":"KG",
    "name:kir_x_preferred":[
        "\u041a\u044e\u043d\u0433\u0435\u0439"
    ],
    "name:rus_x_preferred":[
        "\u041a\u044e\u043d\u0433\u0435\u0439"
    ],
    "wof:name":"Kyungey",
    "wof:placetype":"locality"
},
  "geometry": {"coordinates":[73.29885999999998,40.3618],"type":"Point"}
}