{
  "type": "Feature",
  "properties": {
    "gn:admin1_code":"07",
    "gn:asciiname":"Oryuktyu-Khutor",
    "gn:country_code":"KG",
    "gn:dem":1638,
    "gn:feature_class":"P",
    "gn:feature_code":"PPL",
    "gn:name":"Oryuktyu-Khutor",
    "gn:population":0,
    "gn:timezone":"Asia/Bishkek",
    "iso:country":"KG",
    "name:kir_x_preferred":[
        "\u041e\u0440\u044e\u043a\u0442\u044e-\u0425\u0443\u0442\u043e\u0440"
    ],
    "name:rus_x_preferred":[
        "\u041e\u0440\u044e\u043a\u0442\u044e-\u0425\u0443\u0442\u043e\u0440"
    ],
    "name:rus_x_variant":[
        "Otdeleniye Chetv\u00ebrtoye Sovkhoza Yryukty"
    ],
    "name:und_x_variant":[
        "Otdeleniye Chetv\u00ebrtoye Sovkhoza Yryukty"
    ],
    "wof:name":"Oryuktyu-Khutor",
    "wof:placetype":"locality"
},
  "geometry": {"coordinates":[77.81909,42.7397],"type":"Point"}
}