{
  "type": "Feature",
  "properties": {
    "gn:admin1_code":"02",
    "gn:asciiname":"Severnoye",
    "gn:country_code":"KG",
    "gn:dem":577,
    "gn:feature_class":"P",
    "gn:feature_code":"PPL",
    "gn:name":"Severnoye",
    "gn:population":0,
    "gn:timezone":"Asia/Bishkek",
    "iso:country":"KG",
    "name:rus_x_preferred":[
        "\u0421\u0435\u0432\u0435\u0440\u043d\u043e\u0435"
    ],
    "wof:name":"Severnoye",
    "wof:placetype":"locality"
},
  "geometry": {"coordinates":[74.34321,43.15932],"type":"Point"}
}