{
  "type": "Feature",
  "properties": {
    "gn:admin1_code":"00",
    "gn:asciiname":"kyzyl-Toqoy",
    "gn:country_code":"KG",
    "gn:dem":1357,
    "gn:feature_class":"P",
    "gn:feature_code":"PPL",
    "gn:name":"kyzyl-Toqoy",
    "gn:population":0,
    "gn:timezone":"Asia/Bishkek",
    "iso:country":"KG",
    "name:eng_x_preferred":[
        "Qizil-Toqoy"
    ],
    "name:kir_x_preferred":[
        "\u041a\u044b\u0437\u044b\u043b-\u0422\u043e\u043a\u043e\u0439"
    ],
    "wof:name":"kyzyl-Toqoy",
    "wof:placetype":"locality"
},
  "geometry": {"coordinates":[71.3261,41.40702],"type":"Point"}
}