{
  "type": "Feature",
  "properties": {
    "gn:admin1_code":"02",
    "gn:asciiname":"Natsional'noye",
    "gn:country_code":"KG",
    "gn:dem":669,
    "gn:feature_class":"P",
    "gn:feature_code":"PPL",
    "gn:name":"Natsional\u2019noye",
    "gn:population":0,
    "gn:timezone":"Asia/Bishkek",
    "iso:country":"KG",
    "name:kir_x_preferred":[
        "\u041d\u0430\u0446\u0438\u043e\u043d\u0430\u043b\u044c\u043d\u043e\u0435"
    ],
    "name:rus_x_preferred":[
        "Natsional\u2019noye"
    ],
    "name:rus_x_variant":[
        "\u041d\u0430\u0446\u0438\u043e\u043d\u0430\u043b\u044c\u043d\u043e\u0435"
    ],
    "wof:name":"Natsional'noye",
    "wof:placetype":"locality"
},
  "geometry": {"coordinates":[74.28327,42.94074000000001],"type":"Point"}
}