{
  "type": "Feature",
  "properties": {
    "gn:admin1_code":"02",
    "gn:asciiname":"Malovodnoye",
    "gn:country_code":"KG",
    "gn:dem":757,
    "gn:feature_class":"P",
    "gn:feature_code":"PPL",
    "gn:name":"Malovodnoye",
    "gn:population":0,
    "gn:timezone":"Asia/Bishkek",
    "iso:country":"KG",
    "name:kir_x_preferred":[
        "\u041c\u0430\u043b\u043e\u0432\u043e\u0434\u043d\u043e\u0435"
    ],
    "name:kir_x_variant":[
        "\u041c\u0430\u043b\u043e\u0432\u043e\u0434\u043d\u044b\u0439"
    ],
    "name:rus_x_preferred":[
        "\u041c\u0430\u043b\u043e\u0432\u043e\u0434\u043d\u043e\u0435"
    ],
    "name:uzb_x_preferred":[
        "Malovodniy"
    ],
    "wof:name":"Malovodnoye",
    "wof:placetype":"locality"
},
  "geometry": {"coordinates":[74.38115000000001,42.84211],"type":"Point"}
}