{
  "type": "Feature",
  "properties": {
    "gn:admin1_code":"08",
    "gn:asciiname":"Yntymak",
    "gn:country_code":"KG",
    "gn:dem":804,
    "gn:feature_class":"P",
    "gn:feature_code":"PPL",
    "gn:name":"Yntymak",
    "gn:population":0,
    "gn:timezone":"Asia/Bishkek",
    "iso:country":"KG",
    "name:kir_x_preferred":[
        "\u042b\u043d\u0442\u044b\u043c\u0430\u043a"
    ],
    "name:rus_x_preferred":[
        "\u041f\u0440\u0438\u0441\u0430\u0432\u0430\u0439"
    ],
    "name:und_x_variant":[
        "Prisavay"
    ],
    "wof:name":"Yntymak",
    "wof:placetype":"locality"
},
  "geometry": {"coordinates":[73.00813000000002,40.758],"type":"Point"}
}