{
  "type": "Feature",
  "properties": {
    "gn:admin1_code":"03",
    "gn:asciiname":"Maili-Say",
    "gn:country_code":"KG",
    "gn:dem":1086,
    "gn:feature_class":"P",
    "gn:feature_code":"PPL",
    "gn:name":"Maili-Say",
    "gn:population":0,
    "gn:timezone":"Asia/Bishkek",
    "iso:country":"KG",
    "name:kir_x_preferred":[
        "\u041c\u0430\u0439\u043b\u044b-\u0421\u0430\u0439"
    ],
    "name:rus_x_preferred":[
        "\u041c\u0430\u0438\u043b\u0438-\u0421\u0430\u0439"
    ],
    "wof:name":"Maili-Say",
    "wof:placetype":"locality"
},
  "geometry": {"coordinates":[72.49155999999998,41.31755],"type":"Point"}
}