{
  "type": "Feature",
  "properties": {
    "gn:country":"KG",
    "gn:fcode":"PPL",
    "gn:pop":1100,
    "iso:country":"KG",
    "name:eng_x_preferred":[
        "Kerben"
    ],
    "name:eng_x_variant":[
        "Karavan"
    ],
    "name:kir_x_preferred":[
        "\u041a\u0430\u0440\u0430\u0432\u0430\u043d"
    ],
    "name:rus_x_preferred":[
        "\u041a\u0430\u0440\u0430\u0432\u0430\u043d"
    ],
    "qs:name":"Karavan",
    "qs:photos_9r":0,
    "qs:photos_sr":0,
    "qs:pop_sr":"3",
    "wd:wordcount":1618,
    "wof:name":"Karavan",
    "wof:placetype":"locality",
    "wof:population":1100
},
  "geometry": {"coordinates":[72.18626999999999,40.29513],"type":"Point"}
}