{
  "type": "Feature",
  "properties": {
    "gn:admin1_code":"00",
    "gn:asciiname":"Kyzylzhildyz",
    "gn:country_code":"KG",
    "gn:dem":1677,
    "gn:feature_class":"P",
    "gn:feature_code":"PPL",
    "gn:name":"Kyzylzhildyz",
    "gn:population":0,
    "gn:timezone":"Asia/Bishkek",
    "iso:country":"KG",
    "name:kir_x_preferred":[
        "\u041a\u044b\u0437\u044b\u043b-\u0416\u044b\u043b\u0434\u044b\u0437"
    ],
    "wof:name":"Kyzylzhildyz",
    "wof:placetype":"locality"
},
  "geometry": {"coordinates":[73.41667,41.66667],"type":"Point"}
}