{
  "type": "Feature",
  "properties": {
    "gn:admin1_code":"09",
    "gn:asciiname":"Suu-Bashy",
    "gn:country_code":"KG",
    "gn:dem":1069,
    "gn:feature_class":"P",
    "gn:feature_code":"PPL",
    "gn:name":"Suu-Bashy",
    "gn:population":0,
    "gn:timezone":"Asia/Bishkek",
    "iso:country":"KG",
    "name:kir_x_preferred":[
        "\u0421\u0443\u0443-\u0411\u0430\u0448\u0438"
    ],
    "name:rus_x_preferred":[
        "\u0421\u0443\u0443-\u0411\u0430\u0448\u044b"
    ],
    "name:und_x_variant":[
        "Suu-Bashi",
        "Suu-Bashy"
    ],
    "wof:name":"Suu-Bashy",
    "wof:placetype":"locality"
},
  "geometry": {"coordinates":[69.38582,39.865],"type":"Point"}
}