{
  "type": "Feature",
  "properties": {
    "gn:admin1_code":"03",
    "gn:asciiname":"Gulistan",
    "gn:country_code":"KG",
    "gn:dem":1240,
    "gn:feature_class":"P",
    "gn:feature_code":"PPL",
    "gn:name":"Gulistan",
    "gn:population":0,
    "gn:timezone":"Asia/Bishkek",
    "iso:country":"KG",
    "name:eng_x_preferred":[
        "Gyulstan"
    ],
    "name:kir_x_preferred":[
        "G\u00fclstan"
    ],
    "name:rus_x_preferred":[
        "\u0413\u0443\u043b\u0438\u0441\u0442\u0430\u043d"
    ],
    "name:und_x_variant":[
        "G\u00fclstan"
    ],
    "name:uzb_x_preferred":[
        "Gyulstan"
    ],
    "wof:name":"Gulistan",
    "wof:placetype":"locality"
},
  "geometry": {"coordinates":[71.65037,41.42957],"type":"Point"}
}