{
  "type": "Feature",
  "properties": {
    "gn:admin1_code":"08",
    "gn:asciiname":"Krasnyy Mayak",
    "gn:country_code":"KG",
    "gn:dem":995,
    "gn:feature_class":"P",
    "gn:feature_code":"PPL",
    "gn:name":"Krasnyy Mayak",
    "gn:population":0,
    "gn:timezone":"Asia/Bishkek",
    "iso:country":"KG",
    "name:kir_x_preferred":[
        "\u041a\u044b\u0437\u044b\u043b \u041c\u0430\u044f\u043a"
    ],
    "name:rus_x_preferred":[
        "\u041a\u0440\u0430\u0441\u043d\u044b\u0446 \u041c\u0430\u044f\u043a"
    ],
    "wof:name":"Krasnyy Mayak",
    "wof:placetype":"locality"
},
  "geometry": {"coordinates":[73.33519,40.81263],"type":"Point"}
}