{
  "type": "Feature",
  "properties": {
    "gn:admin1_code":"02",
    "gn:asciiname":"Djajylma",
    "gn:country_code":"KG",
    "gn:dem":817,
    "gn:feature_class":"P",
    "gn:feature_code":"PPL",
    "gn:name":"Djajylma",
    "gn:population":0,
    "gn:timezone":"Asia/Bishkek",
    "iso:country":"KG",
    "name:kir_x_preferred":[
        "\u0416\u0430\u0439\u044b\u043b\u043c\u0430"
    ],
    "name:rus_x_preferred":[
        "\u0414\u0436\u0435\u0434\u0438\u0433\u0435\u0440"
    ],
    "name:und_x_variant":[
        "Dzhediger"
    ],
    "wof:name":"Djajylma",
    "wof:placetype":"locality"
},
  "geometry": {"coordinates":[74.83409,42.8114],"type":"Point"}
}