{
  "type": "Feature",
  "properties": {
    "gn:admin1_code":"03",
    "gn:asciiname":"Ornok",
    "gn:country_code":"KG",
    "gn:dem":1499,
    "gn:feature_class":"P",
    "gn:feature_code":"PPL",
    "gn:name":"Ornok",
    "gn:population":0,
    "gn:timezone":"Asia/Bishkek",
    "iso:country":"KG",
    "name:kir_x_preferred":[
        "\u041e\u0440\u043d\u043e\u043a"
    ],
    "name:rus_x_preferred":[
        "\u041e\u0440\u043d\u043e\u043a"
    ],
    "wof:name":"Ornok",
    "wof:placetype":"locality"
},
  "geometry": {"coordinates":[72.77887,41.94786],"type":"Point"}
}