{
  "type": "Feature",
  "properties": {
    "gn:admin1_code":"02",
    "gn:asciiname":"Orto-Aryk",
    "gn:country_code":"KG",
    "gn:dem":908,
    "gn:feature_class":"P",
    "gn:feature_code":"PPL",
    "gn:name":"Orto-Aryk",
    "gn:population":0,
    "gn:timezone":"Asia/Bishkek",
    "iso:country":"KG",
    "name:kir_x_preferred":[
        "\u041e\u0440\u0442\u043e-\u0410\u0440\u044b\u043a"
    ],
    "name:rus_x_preferred":[
        "\u041e\u0440\u0442\u043e-\u0410\u0440\u044b\u043a"
    ],
    "wof:name":"Orto-Aryk",
    "wof:placetype":"locality"
},
  "geometry": {"coordinates":[73.66954,42.7475],"type":"Point"}
}