{
  "type": "Feature",
  "properties": {
    "gn:admin1_code":"07",
    "gn:asciiname":"Chelpek",
    "gn:country_code":"KG",
    "gn:dem":1793,
    "gn:feature_class":"P",
    "gn:feature_code":"PPL",
    "gn:name":"Chelpek",
    "gn:population":0,
    "gn:timezone":"Asia/Bishkek",
    "iso:country":"KG",
    "name:kir_x_preferred":[
        "\u0427\u0435\u043b\u043f\u0435\u043a"
    ],
    "name:rus_x_preferred":[
        "\u0427\u0435\u043b\u044c\u043f\u0435\u043a"
    ],
    "name:und_x_variant":[
        "Chel\u2019pek"
    ],
    "wof:name":"Chelpek",
    "wof:placetype":"locality"
},
  "geometry": {"coordinates":[78.36960000000001,42.46235],"type":"Point"}
}