{
  "type": "Feature",
  "properties": {
    "gn:admin1_code":"04",
    "gn:asciiname":"Uzgorysh",
    "gn:country_code":"KG",
    "gn:dem":2034,
    "gn:feature_class":"P",
    "gn:feature_code":"PPL",
    "gn:name":"Uzgorysh",
    "gn:population":0,
    "gn:timezone":"Asia/Bishkek",
    "iso:country":"KG",
    "name:kir_x_preferred":[
        "\u0423\u0437\u0433\u043e\u0440\u044b\u0448"
    ],
    "name:rus_x_preferred":[
        "\u0423\u0437\u0433\u043e\u0440\u044b\u0448"
    ],
    "name:und_x_variant":[
        "Kara-Burgen",
        "Kara-Burga"
    ],
    "wof:name":"Uzgorysh",
    "wof:placetype":"locality"
},
  "geometry": {"coordinates":[74.70430999999998,41.21809],"type":"Point"}
}