{
  "type": "Feature",
  "properties": {
    "gn:admin1_code":"08",
    "gn:asciiname":"Chegeden",
    "gn:country_code":"KG",
    "gn:dem":1306,
    "gn:feature_class":"P",
    "gn:feature_code":"PPL",
    "gn:name":"Chegeden",
    "gn:population":0,
    "gn:timezone":"Asia/Bishkek",
    "iso:country":"KG",
    "name:kir_x_preferred":[
        "\u0427\u0435\u0433\u0435\u0434\u0435\u043d"
    ],
    "name:rus_x_preferred":[
        "\u0427\u0435\u0433\u0435\u0434\u0435\u043d"
    ],
    "wof:name":"Chegeden",
    "wof:placetype":"locality"
},
  "geometry": {"coordinates":[72.7235,40.28451],"type":"Point"}
}