{
  "type": "Feature",
  "properties": {
    "gn:admin1_code":"06",
    "gn:asciiname":"Kek-Tebe",
    "gn:country_code":"KG",
    "gn:dem":725,
    "gn:feature_class":"P",
    "gn:feature_code":"PPL",
    "gn:name":"K\u00ebk-T\u00ebb\u00eb",
    "gn:population":0,
    "gn:timezone":"Asia/Bishkek",
    "iso:country":"KG",
    "name:kir_x_preferred":[
        "\u041a\u04e9\u043a-\u0414\u04e9\u0431\u04e9"
    ],
    "name:rus_x_preferred":[
        "K\u00ebk-T\u00ebb\u00eb"
    ],
    "name:rus_x_variant":[
        "\u041a\u0451\u043a-\u0422\u0451\u0431\u0451"
    ],
    "name:und_x_variant":[
        "K\u00ebk-T\u00ebb\u00eb"
    ],
    "wof:name":"Kek-Tebe",
    "wof:placetype":"locality"
},
  "geometry": {"coordinates":[71.44617,42.76421],"type":"Point"}
}