{
  "type": "Feature",
  "properties": {
    "gn:admin1_code":"07",
    "gn:asciiname":"Munduz",
    "gn:country_code":"KG",
    "gn:dem":1678,
    "gn:feature_class":"P",
    "gn:feature_code":"PPL",
    "gn:name":"Munduz",
    "gn:population":0,
    "gn:timezone":"Asia/Bishkek",
    "iso:country":"KG",
    "name:kir_x_preferred":[
        "\u041c\u0443\u043d\u0434\u0443\u0437"
    ],
    "name:rus_x_preferred":[
        "\u041c\u0443\u043d\u0434\u0443\u0437"
    ],
    "wof:name":"Munduz",
    "wof:placetype":"locality"
},
  "geometry": {"coordinates":[78.14043000000002,42.44406],"type":"Point"}
}