{
  "type": "Feature",
  "properties": {
    "gn:admin1_code":"04",
    "gn:asciiname":"Kolaryk",
    "gn:country_code":"KG",
    "gn:dem":1819,
    "gn:feature_class":"P",
    "gn:feature_code":"PPL",
    "gn:name":"Kolaryk",
    "gn:population":0,
    "gn:timezone":"Asia/Bishkek",
    "iso:country":"KG",
    "name:kir_x_preferred":[
        "\u041a\u043e\u043b-\u0410\u0440\u044b\u043a"
    ],
    "name:rus_x_preferred":[
        "\u041a\u043e\u043b\u0430\u0440\u044b\u043a"
    ],
    "wof:name":"Kolaryk",
    "wof:placetype":"locality"
},
  "geometry": {"coordinates":[74.66736,41.98135],"type":"Point"}
}