{
  "type": "Feature",
  "properties": {
    "gn:admin1_code":"02",
    "gn:asciiname":"Tel'man Atyndagy",
    "gn:country_code":"KG",
    "gn:dem":1078,
    "gn:feature_class":"P",
    "gn:feature_code":"PPL",
    "gn:name":"Tel\u2019man Atyndagy",
    "gn:population":0,
    "gn:timezone":"Asia/Bishkek",
    "iso:country":"KG",
    "name:kir_x_preferred":[
        "\u0422\u0435\u043b\u043c\u0430\u043d \u0430\u0442\u044b\u043d\u0434\u0430\u0433\u044b"
    ],
    "name:rus_x_preferred":[
        "Imeni Tel\u2019mana"
    ],
    "name:rus_x_variant":[
        "\u0418\u043c\u0435\u043d\u0438 \u0422\u0435\u043b\u044c\u043c\u0430\u043d\u0430"
    ],
    "name:und_x_variant":[
        "Tel\u2019man Atyndagy"
    ],
    "wof:name":"Tel'man Atyndagy",
    "wof:placetype":"locality"
},
  "geometry": {"coordinates":[75.06826,42.72635],"type":"Point"}
}