{
  "type": "Feature",
  "properties": {
    "gn:admin1_code":"02",
    "gn:asciiname":"Pervomayskoye",
    "gn:country_code":"KG",
    "gn:dem":855,
    "gn:feature_class":"P",
    "gn:feature_code":"PPL",
    "gn:name":"Pervomayskoye",
    "gn:population":0,
    "gn:timezone":"Asia/Bishkek",
    "iso:country":"KG",
    "name:kir_x_preferred":[
        "\u0411\u0438\u0440\u0438\u043d\u0447\u0438 \u041c\u0430\u0439"
    ],
    "name:kir_x_variant":[
        "\u041f\u0435\u0440\u0432\u043e\u043c\u0430\u0439\u0441\u043a\u043e\u0435"
    ],
    "name:rus_x_preferred":[
        "\u041f\u0435\u0440\u0432\u043e\u043c\u0430\u0439\u0441\u043a\u043e\u0435"
    ],
    "name:und_x_variant":[
        "Ebenfel\u2019d",
        "Pervomayskoye"
    ],
    "wof:name":"Pervomayskoye",
    "wof:placetype":"locality"
},
  "geometry": {"coordinates":[75.00190000000001,42.79742],"type":"Point"}
}