{
  "type": "Feature",
  "properties": {
    "gn:admin1_code":"03",
    "gn:asciiname":"Prigorodnyy",
    "gn:country_code":"KG",
    "gn:dem":786,
    "gn:feature_class":"P",
    "gn:feature_code":"PPL",
    "gn:name":"Prigorodnyy",
    "gn:population":0,
    "gn:timezone":"Asia/Bishkek",
    "iso:country":"KG",
    "name:kir_x_preferred":[
        "\u041f\u0440\u0438\u0433\u043e\u0440\u043e\u0434\u043d\u044b\u0439"
    ],
    "name:rus_x_preferred":[
        "\u041f\u0440\u0438\u0433\u043e\u0440\u043e\u0434\u043d\u044b\u0439"
    ],
    "wof:name":"Prigorodnyy",
    "wof:placetype":"locality"
},
  "geometry": {"coordinates":[73.01321999999998,40.90872],"type":"Point"}
}