{
  "type": "Feature",
  "properties": {
    "gn:admin1_code":"08",
    "gn:asciiname":"Kara-Shibak",
    "gn:country_code":"KG",
    "gn:dem":2550,
    "gn:feature_class":"P",
    "gn:feature_code":"PPL",
    "gn:name":"Kara-Shibak",
    "gn:population":0,
    "gn:timezone":"Asia/Bishkek",
    "iso:country":"KG",
    "name:kir_x_preferred":[
        "\u041a\u0430\u0440\u0430-\u0428\u044b\u0431\u0430\u043a"
    ],
    "name:rus_x_preferred":[
        "\u041a\u0430\u0440\u0430-\u0428\u044b\u0431\u0430\u043a"
    ],
    "name:und_x_variant":[
        "Kara-Shivak",
        "Kara-Shibak"
    ],
    "wof:name":"Kara-Shibak",
    "wof:placetype":"locality"
},
  "geometry": {"coordinates":[72.18718,39.51803],"type":"Point"}
}