{
  "type": "Feature",
  "properties": {
    "gn:admin1_code":"00",
    "gn:asciiname":"Baymam-Bet",
    "gn:cc2":"KG",
    "gn:country_code":"KG",
    "gn:dem":1667,
    "gn:feature_class":"P",
    "gn:feature_code":"PPL",
    "gn:name":"Baymam-Bet",
    "gn:population":0,
    "gn:timezone":"Asia/Bishkek",
    "iso:country":"KG",
    "name:und_x_variant":[
        "Bayman-Bet",
        "Baymam-Bet"
    ],
    "wof:name":"Baymam-Bet",
    "wof:placetype":"locality"
},
  "geometry": {"coordinates":[73.66667,40.88333],"type":"Point"}
}