{
  "type": "Feature",
  "properties": {
    "gn:admin1_code":"04",
    "gn:asciiname":"Kazybek",
    "gn:country_code":"KG",
    "gn:dem":2379,
    "gn:feature_class":"P",
    "gn:feature_code":"PPL",
    "gn:name":"Kazybek",
    "gn:population":0,
    "gn:timezone":"Asia/Bishkek",
    "iso:country":"KG",
    "name:kir_x_preferred":[
        "\u041a\u0430\u0437\u044b\u0431\u0435\u043a"
    ],
    "name:rus_x_historical":[
        "\u041f\u043e\u0433\u0440\u0430\u043d\u0438\u0447\u043d\u0438\u043a"
    ],
    "name:rus_x_preferred":[
        "\u041f\u043e\u0433\u0440\u0430\u043d\u0438\u0447\u043d\u0438\u043a"
    ],
    "wof:name":"Kazybek",
    "wof:placetype":"locality"
},
  "geometry": {"coordinates":[75.53268,41.03326],"type":"Point"}
}