{
  "type": "Feature",
  "properties": {
    "gn:admin1_code":"04",
    "gn:asciiname":"Ak-Kyya",
    "gn:country_code":"KG",
    "gn:dem":2472,
    "gn:feature_class":"P",
    "gn:feature_code":"PPL",
    "gn:name":"Ak-Kyya",
    "gn:population":0,
    "gn:timezone":"Asia/Bishkek",
    "iso:country":"KG",
    "name:kir_x_preferred":[
        "\u0410\u043a-\u041a\u044b\u044f"
    ],
    "wof:name":"Ak-Kyya",
    "wof:placetype":"locality"
},
  "geometry": {"coordinates":[75.9688,41.91909],"type":"Point"}
}