{
  "type": "Feature",
  "properties": {
    "gn:admin1_code":"04",
    "gn:asciiname":"Orobashi",
    "gn:country_code":"KG",
    "gn:dem":2048,
    "gn:feature_class":"P",
    "gn:feature_code":"PPL",
    "gn:name":"Orobashi",
    "gn:population":0,
    "gn:timezone":"Asia/Bishkek",
    "iso:country":"KG",
    "name:kir_x_preferred":[
        "\u041e\u0440\u043e\u0431\u0430\u0448\u0438"
    ],
    "name:rus_x_preferred":[
        "\u041e\u0440\u043e\u0431\u0430\u0448\u0438"
    ],
    "wof:name":"Orobashi",
    "wof:placetype":"locality"
},
  "geometry": {"coordinates":[75.44118,42.14139],"type":"Point"}
}