{
  "type": "Feature",
  "properties": {
    "gn:admin1_code":"07",
    "gn:asciiname":"Oybulak",
    "gn:country_code":"KG",
    "gn:dem":1650,
    "gn:feature_class":"P",
    "gn:feature_code":"PPL",
    "gn:name":"Oybulak",
    "gn:population":0,
    "gn:timezone":"Asia/Bishkek",
    "iso:country":"KG",
    "name:kir_x_preferred":[
        "\u041e\u0439-\u0411\u0443\u043b\u0430\u043a"
    ],
    "name:rus_x_preferred":[
        "\u041e\u0439\u0431\u0443\u043b\u0430\u043a"
    ],
    "wof:name":"Oybulak",
    "wof:placetype":"locality"
},
  "geometry": {"coordinates":[78.08674000000001,42.74831],"type":"Point"}
}