{
  "type": "Feature",
  "properties": {
    "gn:admin1_code":"03",
    "gn:asciiname":"Kara-Bulak",
    "gn:country_code":"KG",
    "gn:dem":984,
    "gn:feature_class":"P",
    "gn:feature_code":"PPL",
    "gn:name":"Kara-Bulak",
    "gn:population":0,
    "gn:timezone":"Asia/Bishkek",
    "iso:country":"KG",
    "name:ceb_x_preferred":[
        "Kara-Bulak"
    ],
    "name:kir_x_preferred":[
        "\u041a\u0430\u0440\u0430-\u0411\u0443\u043b\u0430\u043a"
    ],
    "name:rus_x_preferred":[
        "\u041a\u0430\u0440\u0430-\u0411\u0443\u043b\u0430\u043a"
    ],
    "name:swe_x_preferred":[
        "Kara-Bulak"
    ],
    "wof:name":"Kara-Bulak",
    "wof:placetype":"locality"
},
  "geometry": {"coordinates":[72.68377,41.15794],"type":"Point"}
}