{
  "type": "Feature",
  "properties": {
    "gn:admin1_code":"09",
    "gn:asciiname":"Zar-Tash",
    "gn:country_code":"KG",
    "gn:dem":764,
    "gn:feature_class":"P",
    "gn:feature_code":"PPL",
    "gn:name":"Zar-Tash",
    "gn:population":0,
    "gn:timezone":"Asia/Bishkek",
    "iso:country":"KG",
    "name:ceb_x_preferred":[
        "Zar-Tash"
    ],
    "name:kir_x_preferred":[
        "\u0417\u0430\u0440-\u0422\u0430\u0448"
    ],
    "name:rus_x_preferred":[
        "\u0417\u0430\u0440-\u0422\u0430\u0448"
    ],
    "name:swe_x_preferred":[
        "Zar-Tash"
    ],
    "name:uzb_x_preferred":[
        "Zar Tosh"
    ],
    "name:uzb_x_variant":[
        "Zar-Tosh"
    ],
    "wof:name":"Zar-Tash",
    "wof:placetype":"locality"
},
  "geometry": {"coordinates":[71.02687,40.25943],"type":"Point"}
}