{
  "type": "Feature",
  "properties": {
    "gn:admin1_code":"07",
    "gn:asciiname":"Temirkanat",
    "gn:country_code":"KG",
    "gn:dem":2088,
    "gn:feature_class":"P",
    "gn:feature_code":"PPL",
    "gn:name":"Temirkanat",
    "gn:population":0,
    "gn:timezone":"Asia/Bishkek",
    "iso:country":"KG",
    "name:ceb_x_preferred":[
        "Temirkanat"
    ],
    "name:kir_x_preferred":[
        "\u0422\u0435\u043c\u0438\u0440-\u041a\u0430\u043d\u0430\u0442"
    ],
    "name:rus_x_preferred":[
        "\u0422\u0435\u043c\u0438\u0440\u043a\u0430\u043d\u0430\u0442"
    ],
    "name:rus_x_variant":[
        "\u0422\u0435\u043c\u0438\u0440-\u041a\u0430\u043d\u0430\u0442"
    ],
    "name:swe_x_preferred":[
        "Temirkanat"
    ],
    "wof:name":"Temirkanat",
    "wof:placetype":"locality"
},
  "geometry": {"coordinates":[76.92,42.05686],"type":"Point"}
}