{
  "type": "Feature",
  "properties": {
    "gn:admin1_code":"09",
    "gn:asciiname":"Bulak-Bashi",
    "gn:country_code":"KG",
    "gn:dem":833,
    "gn:feature_class":"P",
    "gn:feature_code":"PPL",
    "gn:name":"Bulak-Bashi",
    "gn:population":0,
    "gn:timezone":"Asia/Bishkek",
    "iso:country":"KG",
    "name:kir_x_preferred":[
        "\u0411\u0443\u043b\u0430\u043a-\u0411\u0430\u0448\u044b"
    ],
    "name:rus_x_preferred":[
        "\u0411\u0443\u043b\u0430\u043a-\u0411\u0430\u0448\u0438"
    ],
    "wof:name":"Bulak-Bashi",
    "wof:placetype":"locality"
},
  "geometry": {"coordinates":[69.5671,40.00622],"type":"Point"}
}