{
  "type": "Feature",
  "properties": {
    "gn:admin1_code":"08",
    "gn:asciiname":"Gyul'stan",
    "gn:country_code":"KG",
    "gn:dem":1388,
    "gn:feature_class":"P",
    "gn:feature_code":"PPL",
    "gn:name":"Gyul\u2019stan",
    "gn:population":0,
    "gn:timezone":"Asia/Bishkek",
    "iso:country":"KG",
    "name:kir_x_preferred":[
        "G\u00fclstan"
    ],
    "name:rus_x_preferred":[
        "Gyul\u2019stan"
    ],
    "name:rus_x_variant":[
        "\u0413\u044e\u043b\u044c\u0441\u0442\u0430\u043d"
    ],
    "wof:name":"Gyul'stan",
    "wof:placetype":"locality"
},
  "geometry": {"coordinates":[72.57021,40.26357],"type":"Point"}
}