{
  "type": "Feature",
  "properties": {
    "gn:admin1_code":"02",
    "gn:asciiname":"Alga",
    "gn:country_code":"KG",
    "gn:dem":979,
    "gn:feature_class":"P",
    "gn:feature_code":"PPL",
    "gn:name":"Alga",
    "gn:population":0,
    "gn:timezone":"Asia/Bishkek",
    "iso:country":"KG",
    "name:kir_x_preferred":[
        "\u0410\u043b\u0433\u0430"
    ],
    "name:rus_x_preferred":[
        "\u0410\u043b\u0433\u0430"
    ],
    "wof:name":"Alga",
    "wof:placetype":"locality"
},
  "geometry": {"coordinates":[75.31548000000002,42.76363],"type":"Point"}
}