{
  "type": "Feature",
  "properties": {
    "gn:admin1_code":"07",
    "gn:asciiname":"Peschanyy",
    "gn:country_code":"KG",
    "gn:dem":1646,
    "gn:feature_class":"P",
    "gn:feature_code":"PPL",
    "gn:name":"Peschanyy",
    "gn:population":0,
    "gn:timezone":"Asia/Bishkek",
    "iso:country":"KG",
    "name:kir_x_preferred":[
        "\u0421\u0430\u0440\u044b-\u0411\u0443\u043b\u0443\u043d"
    ],
    "name:rus_x_preferred":[
        "\u041f\u0435\u0441\u0447\u0430\u043d\u044b\u0439"
    ],
    "wof:name":"Peschanyy",
    "wof:placetype":"locality"
},
  "geometry": {"coordinates":[78.18055,42.67028],"type":"Point"}
}