{
  "type": "Feature",
  "properties": {
    "gn:admin1_code":"07",
    "gn:asciiname":"Chetbaysaur",
    "gn:country_code":"KG",
    "gn:dem":1837,
    "gn:feature_class":"P",
    "gn:feature_code":"PPL",
    "gn:name":"Chetbaysaur",
    "gn:population":0,
    "gn:timezone":"Asia/Bishkek",
    "iso:country":"KG",
    "name:kir_x_preferred":[
        "\u0427\u0435\u0442\u0431\u0430\u0439\u0441\u0430\u0443\u0440"
    ],
    "name:rus_x_preferred":[
        "\u0427\u0435\u0442\u0431\u0430\u0439\u0441\u0430\u0443\u0440"
    ],
    "wof:name":"Chetbaysaur",
    "wof:placetype":"locality"
},
  "geometry": {"coordinates":[77.65846999999999,42.78334],"type":"Point"}
}