{
  "type": "Feature",
  "properties": {
    "gn:admin1_code":"08",
    "gn:asciiname":"Tel'manchaty",
    "gn:country_code":"KG",
    "gn:dem":1628,
    "gn:feature_class":"P",
    "gn:feature_code":"PPL",
    "gn:name":"Tel\u2019manchaty",
    "gn:population":0,
    "gn:timezone":"Asia/Bishkek",
    "iso:country":"KG",
    "name:kir_x_preferred":[
        "\u0422\u0435\u043b\u044c\u043c\u0430\u043d-\u0427\u0430\u0442\u044b"
    ],
    "name:rus_x_preferred":[
        "Tel\u2019manchaty"
    ],
    "name:rus_x_variant":[
        "\u0422\u0435\u043b\u044c\u043c\u0430\u043d\u0447\u0430\u0442\u044b"
    ],
    "name:und_x_variant":[
        "Tel\u2019man-Chaty"
    ],
    "wof:name":"Tel'manchaty",
    "wof:placetype":"locality"
},
  "geometry": {"coordinates":[73.42708,40.27219],"type":"Point"}
}