{
  "type": "Feature",
  "properties": {
    "gn:admin1_code":"09",
    "gn:asciiname":"Maydan",
    "gn:country_code":"KG",
    "gn:dem":1280,
    "gn:feature_class":"P",
    "gn:feature_code":"PPL",
    "gn:name":"Maydan",
    "gn:population":0,
    "gn:timezone":"Asia/Bishkek",
    "iso:country":"KG",
    "name:kir_x_preferred":[
        "\u041c\u0430\u0439\u0434\u0430\u043d"
    ],
    "name:kir_x_variant":[
        "Maidan"
    ],
    "name:rus_x_preferred":[
        "\u041c\u0430\u0439\u0434\u0430\u043d"
    ],
    "wof:name":"Maydan",
    "wof:placetype":"locality"
},
  "geometry": {"coordinates":[72.08745999999999,40.06195],"type":"Point"}
}