{
  "type": "Feature",
  "properties": {
    "gn:admin1_code":"08",
    "gn:asciiname":"Kysyk-Alma",
    "gn:country_code":"KG",
    "gn:dem":1396,
    "gn:feature_class":"P",
    "gn:feature_code":"PPL",
    "gn:name":"Kysyk-Alma",
    "gn:population":0,
    "gn:timezone":"Asia/Bishkek",
    "iso:country":"KG",
    "name:kir_x_preferred":[
        "\u041a\u044b\u0441\u044b\u043a-\u0410\u043b\u043c\u0430"
    ],
    "name:rus_x_preferred":[
        "\u041a\u044b\u0441\u044b\u043a-\u0410\u043b\u043c\u0430"
    ],
    "wof:name":"Kysyk-Alma",
    "wof:placetype":"locality"
},
  "geometry": {"coordinates":[73.27150999999998,40.64269],"type":"Point"}
}