{
  "type": "Feature",
  "properties": {
    "gn:admin1_code":"02",
    "gn:asciiname":"Tash-Bashat",
    "gn:country_code":"KG",
    "gn:dem":1665,
    "gn:feature_class":"P",
    "gn:feature_code":"PPL",
    "gn:name":"Tash-Bashat",
    "gn:population":0,
    "gn:timezone":"Asia/Bishkek",
    "iso:country":"KG",
    "name:kir_x_preferred":[
        "\u0422\u0430\u0448-\u0411\u0430\u0448\u0430\u0442"
    ],
    "name:rus_x_preferred":[
        "\u0422\u0430\u0448-\u0411\u0430\u0448\u0430\u0442"
    ],
    "wof:name":"Tash-Bashat",
    "wof:placetype":"locality"
},
  "geometry": {"coordinates":[74.75022,42.67583],"type":"Point"}
}