{
  "type": "Feature",
  "properties": {
    "gn:admin1_code":"03",
    "gn:asciiname":"Jany-Abad",
    "gn:country_code":"KG",
    "gn:dem":566,
    "gn:feature_class":"P",
    "gn:feature_code":"PPL",
    "gn:name":"Jany-Abad",
    "gn:population":0,
    "gn:timezone":"Asia/Bishkek",
    "iso:country":"KG",
    "name:kir_x_preferred":[
        "\u0416\u0430\u04a3\u044b-\u0410\u0431\u0430\u0434"
    ],
    "name:rus_x_preferred":[
        "\u0414\u0436\u0430\u043d\u044b-\u0410\u0431\u0430\u0434"
    ],
    "name:und_x_variant":[
        "Dzhany-Abad"
    ],
    "wof:name":"Jany-Abad",
    "wof:placetype":"locality"
},
  "geometry": {"coordinates":[72.59506,40.9431],"type":"Point"}
}