{
  "type": "Feature",
  "properties": {
    "gn:admin1_code":"09",
    "gn:asciiname":"Korgon-Tash",
    "gn:country_code":"KG",
    "gn:dem":1580,
    "gn:feature_class":"P",
    "gn:feature_code":"PPL",
    "gn:name":"Korgon-Tash",
    "gn:population":0,
    "gn:timezone":"Asia/Bishkek",
    "iso:country":"KG",
    "name:kir_x_preferred":[
        "Tashty-Kalan"
    ],
    "name:rus_x_preferred":[
        "\u0422\u0430\u0448\u0442\u044b-\u041a\u0430\u043b\u0430\u043d"
    ],
    "name:rus_x_variant":[
        "\u041a\u043e\u0440\u0433\u043e\u043d-\u0422\u0430\u0448"
    ],
    "wof:name":"Korgon-Tash",
    "wof:placetype":"locality"
},
  "geometry": {"coordinates":[70.95401,39.7316],"type":"Point"}
}