{
  "type": "Feature",
  "properties": {
    "gn:admin1_code":"08",
    "gn:asciiname":"Alcha-Bashat",
    "gn:country_code":"KG",
    "gn:dem":1596,
    "gn:feature_class":"P",
    "gn:feature_code":"PPL",
    "gn:name":"Alcha-Bashat",
    "gn:population":0,
    "gn:timezone":"Asia/Bishkek",
    "iso:country":"KG",
    "name:kir_x_preferred":[
        "\u0410\u043b\u0447\u0430-\u0411\u0430\u0448\u0430\u0442"
    ],
    "name:rus_x_preferred":[
        "\u0410\u043b\u0447\u0430-\u0411\u0430\u0448\u0430\u0442"
    ],
    "wof:name":"Alcha-Bashat",
    "wof:placetype":"locality"
},
  "geometry": {"coordinates":[73.29418000000003,40.65175],"type":"Point"}
}