{
  "type": "Feature",
  "properties": {
    "gn:admin1_code":"00",
    "gn:asciiname":"Kara-Oy",
    "gn:country_code":"KG",
    "gn:dem":990,
    "gn:feature_class":"P",
    "gn:feature_code":"PPL",
    "gn:name":"Kara-Oy",
    "gn:population":0,
    "gn:timezone":"Asia/Bishkek",
    "iso:country":"KG",
    "name:kir_x_preferred":[
        "\u041a\u0430\u0440\u0430-\u041e\u0439"
    ],
    "wof:name":"Kara-Oy",
    "wof:placetype":"locality"
},
  "geometry": {"coordinates":[72.94131999999998,41.21711],"type":"Point"}
}