{
  "type": "Feature",
  "properties": {
    "gn:admin1_code":"04",
    "gn:asciiname":"Chontuz",
    "gn:country_code":"KG",
    "gn:dem":1982,
    "gn:feature_class":"P",
    "gn:feature_code":"PPL",
    "gn:name":"Chontuz",
    "gn:population":0,
    "gn:timezone":"Asia/Bishkek",
    "iso:country":"KG",
    "name:kir_x_preferred":[
        "\u0427\u043e\u04a3-\u0422\u0443\u0437"
    ],
    "name:rus_x_preferred":[
        "\u0427\u043e\u043d\u0442\u0443\u0437"
    ],
    "wof:name":"Chontuz",
    "wof:placetype":"locality"
},
  "geometry": {"coordinates":[75.50004,42.15378],"type":"Point"}
}