{
  "type": "Feature",
  "properties": {
    "gn:admin1_code":"03",
    "gn:asciiname":"Dukur",
    "gn:country_code":"KG",
    "gn:dem":547,
    "gn:feature_class":"P",
    "gn:feature_code":"PPL",
    "gn:name":"Dukur",
    "gn:population":0,
    "gn:timezone":"Asia/Bishkek",
    "iso:country":"KG",
    "name:kir_x_preferred":[
        "\u0414\u0443\u043a\u0443\u0440"
    ],
    "name:rus_x_preferred":[
        "\u0414\u0443\u043a\u0443\u0440"
    ],
    "wof:name":"Dukur",
    "wof:placetype":"locality"
},
  "geometry": {"coordinates":[72.5658,40.94146],"type":"Point"}
}