{
  "type": "Feature",
  "properties": {
    "gn:admin1_code":"08",
    "gn:asciiname":"Charbak",
    "gn:country_code":"KG",
    "gn:dem":750,
    "gn:feature_class":"P",
    "gn:feature_code":"PPL",
    "gn:name":"Charbak",
    "gn:population":0,
    "gn:timezone":"Asia/Bishkek",
    "iso:country":"KG",
    "name:kir_x_preferred":[
        "\u0427\u0430\u0440\u0431\u0430\u043a"
    ],
    "name:rus_x_preferred":[
        "\u0427\u0430\u0440\u0431\u0430\u043a"
    ],
    "wof:name":"Charbak",
    "wof:placetype":"locality"
},
  "geometry": {"coordinates":[72.50748,40.53018],"type":"Point"}
}