{
  "type": "Feature",
  "properties": {
    "gn:admin1_code":"00",
    "gn:asciiname":"Klozin",
    "gn:country_code":"KG",
    "gn:dem":1798,
    "gn:feature_class":"P",
    "gn:feature_code":"PPL",
    "gn:name":"Klozin",
    "gn:population":0,
    "gn:timezone":"Asia/Bishkek",
    "iso:country":"KG",
    "name:kir_x_preferred":[
        "\u041a\u043e\u043b\u0437\u0438\u043d"
    ],
    "wof:name":"Klozin",
    "wof:placetype":"locality"
},
  "geometry": {"coordinates":[73.62973000000002,40.47343],"type":"Point"}
}