{
  "type": "Feature",
  "properties": {
    "iso:country":"KG",
    "name:bul_x_preferred":[
        "\u041a\u0430\u043d\u0442"
    ],
    "name:ceb_x_preferred":[
        "Kant"
    ],
    "name:ckb_x_preferred":[
        "\u0642\u0627\u0646\u062a\u060c \u0642\u0631\u063a\u06cc\u0632\u0633\u062a\u0627\u0646"
    ],
    "name:ckb_x_variant":[
        "\u0642\u0627\u0646\u062a"
    ],
    "name:deu_x_preferred":[
        "Kant"
    ],
    "name:eng_x_preferred":[
        "Kant"
    ],
    "name:est_x_preferred":[
        "Kant"
    ],
    "name:fas_x_preferred":[
        "\u0642\u0646\u062f\u060c \u0642\u0631\u0642\u06cc\u0632\u0633\u062a\u0627\u0646"
    ],
    "name:fas_x_variant":[
        "\u0642\u0627\u0646\u062a\u060c \u0642\u0631\u0642\u06cc\u0632\u0633\u062a\u0627\u0646",
        "\u0642\u0627\u0646\u062a"
    ],
    "name:fra_x_preferred":[
        "Kant"
    ],
    "name:heb_x_preferred":[
        "\u05e7\u05d0\u05e0\u05d8"
    ],
    "name:hsb_x_preferred":[
        "Kant"
    ],
    "name:ita_x_preferred":[
        "Kant"
    ],
    "name:jpn_x_preferred":[
        "\u30ab\u30f3\u30c8"
    ],
    "name:kir_x_preferred":[
        "\u041a\u0430\u043d\u0442"
    ],
    "name:kir_x_variant":[
        "Kant"
    ],
    "name:kor_x_preferred":[
        "\uce78\ud2b8"
    ],
    "name:lit_x_preferred":[
        "Kantas"
    ],
    "name:nld_x_preferred":[
        "Kant"
    ],
    "name:nob_x_preferred":[
        "Kant"
    ],
    "name:pol_x_preferred":[
        "Kant"
    ],
    "name:rus_x_preferred":[
        "\u041a\u0430\u043d\u0442"
    ],
    "name:sco_x_preferred":[
        "Kant"
    ],
    "name:swe_x_preferred":[
        "Kant"
    ],
    "name:tat_x_preferred":[
        "\u041a\u0430\u043d\u0442"
    ],
    "name:tur_x_preferred":[
        "Kant"
    ],
    "name:ukr_x_preferred":[
        "\u041a\u0430\u043d\u0442"
    ],
    "name:uzb_x_preferred":[
        "Qand"
    ],
    "name:zho_x_preferred":[
        "\u574e\u7279"
    ],
    "qs:gn_country":"KG",
    "qs:gn_fcode":"PPLA2",
    "qs:gn_pop":20181,
    "qs:name":"Kant",
    "qs:name_adm0":"Kyrgyzstan",
    "qs:name_adm1":"Chuy",
    "qs:photos":0,
    "qs:photos_1k":0,
    "qs:photos_9k":1,
    "qs:photos_9r":1,
    "qs:photos_all":10,
    "qs:photos_sr":0,
    "qs:placetype":"Town",
    "qs:pop_sr":"7",
    "qs:woe_adm0":23424864,
    "wd:wordcount":523,
    "wof:name":"Kant",
    "wof:placetype":"locality",
    "wof:population":20181
},
  "geometry": {"coordinates":[74.85077,42.89106],"type":"Point"}
}