{
  "type": "Feature",
  "properties": {
    "gn:admin1_code":"03",
    "gn:asciiname":"Yaryktash",
    "gn:country_code":"KG",
    "gn:dem":1122,
    "gn:feature_class":"P",
    "gn:feature_code":"PPL",
    "gn:name":"Yaryktash",
    "gn:population":0,
    "gn:timezone":"Asia/Bishkek",
    "iso:country":"KG",
    "name:kir_x_preferred":[
        "\u0416a\u0440\u044b\u043a\u0442\u0430\u0448"
    ],
    "name:rus_x_preferred":[
        "\u042f\u0440\u044b\u043a\u0442\u0430\u0448"
    ],
    "name:urd_x_preferred":[
        "\u06cc\u0627\u0631\u06cc\u06a9\u062a\u0627\u0634"
    ],
    "wof:name":"Yaryktash",
    "wof:placetype":"locality"
},
  "geometry": {"coordinates":[72.08752,41.76863],"type":"Point"}
}