{
  "type": "Feature",
  "properties": {
    "gn:admin1_code":"02",
    "gn:asciiname":"Rot-Front",
    "gn:country_code":"KG",
    "gn:dem":1069,
    "gn:feature_class":"P",
    "gn:feature_code":"PPL",
    "gn:name":"Rot-Front",
    "gn:population":0,
    "gn:timezone":"Asia/Bishkek",
    "iso:country":"KG",
    "name:kir_x_preferred":[
        "\u0420\u043e\u0442-\u0424\u0440\u043e\u043d\u0442"
    ],
    "name:rus_x_preferred":[
        "\u0420\u043e\u0442-\u0424\u0440\u043e\u043d\u0442"
    ],
    "name:und_x_variant":[
        "Bergtal",
        "Bergthal"
    ],
    "wof:name":"Rot-Front",
    "wof:placetype":"locality"
},
  "geometry": {"coordinates":[75.10354,42.72073],"type":"Point"}
}