{
  "type": "Feature",
  "properties": {
    "gn:admin1_code":"08",
    "gn:asciiname":"Zamaryk",
    "gn:country_code":"KG",
    "gn:dem":1135,
    "gn:feature_class":"P",
    "gn:feature_code":"PPL",
    "gn:name":"Zamaryk",
    "gn:population":0,
    "gn:timezone":"Asia/Bishkek",
    "iso:country":"KG",
    "name:kir_x_preferred":[
        "\u0417\u0430\u043c\u0430\u0440\u044b\u043a"
    ],
    "name:rus_x_preferred":[
        "\u0417\u0430\u043c\u0430\u0440\u044b\u043a"
    ],
    "wof:name":"Zamaryk",
    "wof:placetype":"locality"
},
  "geometry": {"coordinates":[72.84905999999999,40.44446],"type":"Point"}
}