{
  "type": "Feature",
  "properties": {
    "gn:admin1_code":"08",
    "gn:admin2_code":"8739771",
    "gn:asciiname":"Kyzyl-Eshme",
    "gn:country_code":"KG",
    "gn:dem":2596,
    "gn:feature_class":"P",
    "gn:feature_code":"PPL",
    "gn:name":"Kyzyl-Eshme",
    "gn:population":1100,
    "gn:timezone":"Asia/Bishkek",
    "iso:country":"KG",
    "name:kir_x_preferred":[
        "\u041a\u044b\u0437\u044b\u043b-\u042d\u0448\u043c\u0435"
    ],
    "name:rus_x_preferred":[
        "\u041a\u044b\u0437\u044b\u043b-\u042d\u0448\u043c\u0435"
    ],
    "wof:name":"Kyzyl-Eshme",
    "wof:placetype":"locality",
    "wof:population":1100
},
  "geometry": {"coordinates":[72.27153,39.56559],"type":"Point"}
}