{
  "type": "Feature",
  "properties": {
    "gn:admin1_code":"04",
    "gn:asciiname":"Kara-Bulung",
    "gn:country_code":"KG",
    "gn:dem":2242,
    "gn:feature_class":"P",
    "gn:feature_code":"PPL",
    "gn:name":"Kara-Bulung",
    "gn:population":0,
    "gn:timezone":"Asia/Bishkek",
    "iso:country":"KG",
    "name:kir_x_preferred":[
        "Kara-Bulung"
    ],
    "name:rus_x_preferred":[
        "\u041a\u0430\u0440\u0430\u0431\u0443\u043b\u0443\u043d"
    ],
    "name:und_x_variant":[
        "Karabulun"
    ],
    "wof:name":"Kara-Bulung",
    "wof:placetype":"locality"
},
  "geometry": {"coordinates":[75.59036999999999,41.09406],"type":"Point"}
}