{
  "type": "Feature",
  "properties": {
    "gn:admin1_code":"03",
    "gn:asciiname":"Masadan",
    "gn:country_code":"KG",
    "gn:dem":733,
    "gn:feature_class":"P",
    "gn:feature_code":"PPL",
    "gn:name":"Masadan",
    "gn:population":0,
    "gn:timezone":"Asia/Bishkek",
    "iso:country":"KG",
    "name:che_x_preferred":[
        "\u041c\u0430\u0441\u0430\u0434\u0430\u043d"
    ],
    "name:fra_x_preferred":[
        "Masadan"
    ],
    "name:kir_x_preferred":[
        "\u041c\u0430\u0441\u0430\u0434\u0430\u043d"
    ],
    "name:rus_x_preferred":[
        "\u041c\u0430\u0441\u0430\u0434\u0430\u043d"
    ],
    "name:tur_x_preferred":[
        "Masadan"
    ],
    "name:uzb_x_preferred":[
        "Masadon"
    ],
    "wof:name":"Masadan",
    "wof:placetype":"locality"
},
  "geometry": {"coordinates":[72.96905,40.89846],"type":"Point"}
}