{
  "type": "Feature",
  "properties": {
    "gn:admin1_code":"03",
    "gn:asciiname":"Chon-Aryk",
    "gn:country_code":"KG",
    "gn:dem":966,
    "gn:feature_class":"P",
    "gn:feature_code":"PPL",
    "gn:name":"Chon-Aryk",
    "gn:population":0,
    "gn:timezone":"Asia/Bishkek",
    "iso:country":"KG",
    "name:kir_x_preferred":[
        "\u0427\u043e\u04a3-\u0410\u0440\u044b\u043a"
    ],
    "name:rus_x_preferred":[
        "\u0427\u043e\u043d\u0430\u0440\u044b\u043a"
    ],
    "name:und_x_variant":[
        "Chonaryk",
        "Chong-Aryk"
    ],
    "name:uzb_x_preferred":[
        "Cho\u02bbn-Ariq"
    ],
    "wof:name":"Chon-Aryk",
    "wof:placetype":"locality"
},
  "geometry": {"coordinates":[72.64415,41.89024000000001],"type":"Point"}
}