{
  "type": "Feature",
  "properties": {
    "gn:admin1_code":"08",
    "gn:asciiname":"Shoro-Bashat",
    "gn:country_code":"KG",
    "gn:dem":965,
    "gn:feature_class":"P",
    "gn:feature_code":"PPL",
    "gn:name":"Shoro-Bashat",
    "gn:population":0,
    "gn:timezone":"Asia/Bishkek",
    "iso:country":"KG",
    "name:kir_x_preferred":[
        "\u0428\u043e\u0440\u043e-\u0411\u0430\u0448\u0430\u0442"
    ],
    "name:rus_x_preferred":[
        "\u0428\u043e\u0440\u043e-\u0411\u0430\u0448\u0430\u0442"
    ],
    "wof:name":"Shoro-Bashat",
    "wof:placetype":"locality"
},
  "geometry": {"coordinates":[73.27214000000002,40.8396],"type":"Point"}
}