{
  "type": "Feature",
  "properties": {
    "gn:admin1_code":"04",
    "gn:asciiname":"Kichi-Borolbos",
    "gn:country_code":"KG",
    "gn:dem":1968,
    "gn:feature_class":"P",
    "gn:feature_code":"PPL",
    "gn:name":"Kichi-Borolbos",
    "gn:population":0,
    "gn:timezone":"Asia/Bishkek",
    "iso:country":"KG",
    "name:kir_x_preferred":[
        "\u041a\u0438\u0447\u0438-\u0411\u043e\u0440\u043e\u043b\u0431\u043e\u0441"
    ],
    "name:rus_x_preferred":[
        "\u041a\u0438\u0447\u0438-\u0411\u043e\u0440\u043e\u043b\u0431\u043e\u0441"
    ],
    "wof:name":"Kichi-Borolbos",
    "wof:placetype":"locality"
},
  "geometry": {"coordinates":[75.10694000000002,41.54811],"type":"Point"}
}