{
  "type": "Feature",
  "properties": {
    "gn:admin1_code":"04",
    "gn:asciiname":"Iryi-Suu",
    "gn:country_code":"KG",
    "gn:dem":2210,
    "gn:feature_class":"P",
    "gn:feature_code":"PPL",
    "gn:name":"Iryi-Suu",
    "gn:population":0,
    "gn:timezone":"Asia/Bishkek",
    "iso:country":"KG",
    "name:kir_x_preferred":[
        "Iryi-Suu"
    ],
    "name:rus_x_preferred":[
        "\u0418\u0440\u0438\u0441\u0443"
    ],
    "name:und_x_variant":[
        "Irisu"
    ],
    "wof:name":"Iryi-Suu",
    "wof:placetype":"locality"
},
  "geometry": {"coordinates":[76.31469,41.46382],"type":"Point"}
}