{
  "type": "Feature",
  "properties": {
    "gn:admin1_code":"03",
    "gn:asciiname":"Kara-Jygach",
    "gn:country_code":"KG",
    "gn:dem":976,
    "gn:feature_class":"P",
    "gn:feature_code":"PPL",
    "gn:name":"Kara-Jygach",
    "gn:population":0,
    "gn:timezone":"Asia/Bishkek",
    "iso:country":"KG",
    "name:kir_x_preferred":[
        "\u041a\u044b\u0437\u044b\u043b\u0436\u0430\u0437\u044b"
    ],
    "name:kir_x_variant":[
        "Kara-Jygach"
    ],
    "name:rus_x_preferred":[
        "\u041a\u0430\u0440\u0430-\u0414\u0436\u044b\u0433\u0430\u0447"
    ],
    "name:und_x_variant":[
        "Kyzyldzhazy",
        "Kara-Dzhygach",
        "Karadzhigach"
    ],
    "wof:name":"Kara-Jygach",
    "wof:placetype":"locality"
},
  "geometry": {"coordinates":[73.28203000000001,41.79064],"type":"Point"}
}