{
  "type": "Feature",
  "properties": {
    "gn:admin1_code":"02",
    "gn:asciiname":"Plokhotnikova",
    "gn:country_code":"KG",
    "gn:dem":1110,
    "gn:feature_class":"P",
    "gn:feature_code":"PPL",
    "gn:name":"Plokhotnikova",
    "gn:population":0,
    "gn:timezone":"Asia/Bishkek",
    "iso:country":"KG",
    "name:kir_x_preferred":[
        "\u041f\u043b\u043e\u0445\u043e\u0442\u043d\u0438\u043a\u043e\u0432\u0430"
    ],
    "name:rus_x_preferred":[
        "\u041f\u043b\u043e\u0445\u043e\u0442\u043d\u0438\u043a\u043e\u0432\u0430"
    ],
    "wof:name":"Plokhotnikova",
    "wof:placetype":"locality"
},
  "geometry": {"coordinates":[75.19233,42.71793],"type":"Point"}
}