{
  "type": "Feature",
  "properties": {
    "gn:admin1_code":"08",
    "gn:asciiname":"Babashuulu",
    "gn:country_code":"KG",
    "gn:dem":1054,
    "gn:feature_class":"P",
    "gn:feature_code":"PPL",
    "gn:name":"Babashuulu",
    "gn:population":0,
    "gn:timezone":"Asia/Bishkek",
    "iso:country":"KG",
    "name:kir_x_preferred":[
        "\u0411\u0430\u0431\u0430\u0448\u0443\u0443\u043b\u0443"
    ],
    "name:rus_x_preferred":[
        "\u0411\u0430\u0431\u0430\u0448\u0443\u0443\u043b\u0443"
    ],
    "wof:name":"Babashuulu",
    "wof:placetype":"locality"
},
  "geometry": {"coordinates":[73.40734999999999,40.75891],"type":"Point"}
}