{
  "type": "Feature",
  "properties": {
    "gn:admin1_code":"03",
    "gn:asciiname":"Gostutpitomnik",
    "gn:country_code":"KG",
    "gn:dem":758,
    "gn:feature_class":"P",
    "gn:feature_code":"PPL",
    "gn:name":"Gostutpitomnik",
    "gn:population":0,
    "gn:timezone":"Asia/Bishkek",
    "iso:country":"KG",
    "name:kir_x_preferred":[
        "\u0413\u043e\u0441\u0442\u0443\u0442\u043f\u0438\u0442\u043e\u043c\u043d\u0438\u043a"
    ],
    "name:rus_x_preferred":[
        "\u0413\u043e\u0441\u0442\u0443\u0442\u043f\u0438\u0442\u043e\u043c\u043d\u0438\u043a"
    ],
    "wof:name":"Gostutpitomnik",
    "wof:placetype":"locality"
},
  "geometry": {"coordinates":[72.72694,41.06899],"type":"Point"}
}