{
  "type": "Feature",
  "properties": {
    "gn:admin1_code":"02",
    "gn:asciiname":"Dzhany-Alysh",
    "gn:country_code":"KG",
    "gn:dem":1047,
    "gn:feature_class":"P",
    "gn:feature_code":"PPL",
    "gn:name":"Dzhany-Alysh",
    "gn:population":0,
    "gn:timezone":"Asia/Bishkek",
    "iso:country":"KG",
    "name:kir_x_preferred":[
        "\u0416\u0430\u04a3\u044b-\u0410\u043b\u044b\u0448"
    ],
    "name:rus_x_preferred":[
        "\u0414\u0436\u0430\u043d\u044b-\u0410\u043b\u044b\u0448"
    ],
    "name:und_x_variant":[
        "Belyy Piket",
        "Dzhany-Alysh"
    ],
    "wof:name":"Dzhany-Alysh",
    "wof:placetype":"locality"
},
  "geometry": {"coordinates":[75.6066,42.80889000000001],"type":"Point"}
}