{
  "type": "Feature",
  "properties": {
    "gn:admin1_code":"02",
    "gn:asciiname":"Vinogradnoe",
    "gn:country_code":"KG",
    "gn:dem":610,
    "gn:feature_class":"P",
    "gn:feature_code":"PPL",
    "gn:name":"Vinogradnoe",
    "gn:population":0,
    "gn:timezone":"Asia/Bishkek",
    "iso:country":"KG",
    "name:kir_x_preferred":[
        "Vinogradnoe"
    ],
    "name:rus_x_preferred":[
        "\u0412\u0438\u043d\u043e\u0433\u0440\u0430\u0434\u043d\u043e\u0435"
    ],
    "name:und_x_variant":[
        "Vinogradnoye"
    ],
    "wof:name":"Vinogradnoe",
    "wof:placetype":"locality"
},
  "geometry": {"coordinates":[74.54087,43.09875],"type":"Point"}
}