{
  "type": "Feature",
  "properties": {
    "gn:admin1_code":"09",
    "gn:asciiname":"Birksu",
    "gn:country_code":"KG",
    "gn:dem":1983,
    "gn:feature_class":"P",
    "gn:feature_code":"PPL",
    "gn:name":"Birksu",
    "gn:population":0,
    "gn:timezone":"Asia/Bishkek",
    "iso:country":"KG",
    "name:kir_x_preferred":[
        "\u0411\u0438\u0440\u043a\u0441\u0443"
    ],
    "name:rus_x_preferred":[
        "\u0411\u0438\u0440\u043a\u0441\u0443"
    ],
    "wof:name":"Birksu",
    "wof:placetype":"locality"
},
  "geometry": {"coordinates":[70.1519,39.78207],"type":"Point"}
}