{
  "type": "Feature",
  "properties": {
    "gn:admin1_code":"08",
    "gn:asciiname":"Karamyk",
    "gn:country_code":"KG",
    "gn:dem":2287,
    "gn:feature_class":"P",
    "gn:feature_code":"PPL",
    "gn:name":"Karamyk",
    "gn:population":0,
    "gn:timezone":"Asia/Bishkek",
    "iso:country":"KG",
    "name:kir_x_preferred":[
        "\u041a\u0430\u0440\u0430\u043c\u044b\u043a"
    ],
    "name:rus_x_preferred":[
        "\u041a\u0430\u0440\u0430\u043c\u044b\u043a"
    ],
    "wof:name":"Karamyk",
    "wof:placetype":"locality"
},
  "geometry": {"coordinates":[71.79254,39.48564],"type":"Point"}
}