{
  "type": "Feature",
  "properties": {
    "gn:admin1_code":"03",
    "gn:asciiname":"Chakmak-Suu",
    "gn:country_code":"KG",
    "gn:dem":2420,
    "gn:feature_class":"P",
    "gn:feature_code":"PPL",
    "gn:name":"Chakmak-Suu",
    "gn:population":0,
    "gn:timezone":"Asia/Bishkek",
    "iso:country":"KG",
    "name:kir_x_preferred":[
        "\u0427\u0430\u043a\u043c\u0430\u043a-\u0421\u0443\u0443"
    ],
    "name:rus_x_preferred":[
        "\u0427\u0430\u043a\u043c\u0430\u043a-\u0421\u0443\u0443"
    ],
    "name:uzb_x_preferred":[
        "Chaqmoq-Suv"
    ],
    "wof:name":"Chakmak-Suu",
    "wof:placetype":"locality"
},
  "geometry": {"coordinates":[71.42083000000002,42.02719],"type":"Point"}
}