{
  "type": "Feature",
  "properties": {
    "gn:admin1_code":"08",
    "gn:asciiname":"Bash-Bulak",
    "gn:country_code":"KG",
    "gn:dem":1211,
    "gn:feature_class":"P",
    "gn:feature_code":"PPL",
    "gn:name":"Bash-Bulak",
    "gn:population":0,
    "gn:timezone":"Asia/Bishkek",
    "iso:country":"KG",
    "name:kir_x_preferred":[
        "\u0411\u0430\u0448-\u0411\u0443\u043b\u0430\u043a"
    ],
    "name:rus_x_preferred":[
        "\u0411\u0430\u0448-\u0411\u0443\u043b\u0430\u043a"
    ],
    "name:uzb_x_preferred":[
        "Bosh-Buloq"
    ],
    "wof:name":"Bash-Bulak",
    "wof:placetype":"locality"
},
  "geometry": {"coordinates":[72.96708000000002,40.51251],"type":"Point"}
}