{
  "type": "Feature",
  "properties": {
    "gn:admin1_code":"08",
    "gn:asciiname":"Bura",
    "gn:country_code":"KG",
    "gn:dem":2334,
    "gn:feature_class":"P",
    "gn:feature_code":"PPL",
    "gn:name":"Bura",
    "gn:population":0,
    "gn:timezone":"Asia/Bishkek",
    "iso:country":"KG",
    "name:kir_x_preferred":[
        "\u0411\u0443\u0440\u0430"
    ],
    "name:rus_x_preferred":[
        "\u0411\u0443\u0440\u0430"
    ],
    "wof:name":"Bura",
    "wof:placetype":"locality"
},
  "geometry": {"coordinates":[74.22091,40.39747],"type":"Point"}
}