{
  "type": "Feature",
  "properties": {
    "gn:admin1_code":"06",
    "gn:asciiname":"Dzhangyaryk",
    "gn:country_code":"KG",
    "gn:dem":1497,
    "gn:feature_class":"P",
    "gn:feature_code":"PPL",
    "gn:name":"Dzhangyaryk",
    "gn:population":0,
    "gn:timezone":"Asia/Bishkek",
    "iso:country":"KG",
    "name:kir_x_preferred":[
        "\u0416\u0430\u04a3\u044b-\u0410\u0440\u044b\u043a"
    ],
    "name:kir_x_variant":[
        "\u0414\u0436\u0430\u043d\u0433\u044b\u0430\u0440\u044b\u043a"
    ],
    "name:rus_x_preferred":[
        "\u0414\u0436\u0430\u043d\u0433\u044b\u0430\u0440\u044b\u043a"
    ],
    "wof:name":"Dzhangyaryk",
    "wof:placetype":"locality"
},
  "geometry": {"coordinates":[72.55719999999999,42.48593],"type":"Point"}
}