{
  "type": "Feature",
  "properties": {
    "gn:admin1_code":"03",
    "gn:asciiname":"Blagoveshenka",
    "gn:country_code":"KG",
    "gn:dem":806,
    "gn:feature_class":"P",
    "gn:feature_code":"PPL",
    "gn:name":"Blagoveshenka",
    "gn:population":0,
    "gn:timezone":"Asia/Bishkek",
    "iso:country":"KG",
    "name:kir_x_preferred":[
        "\u0411\u043b\u0430\u0433\u043e\u0432\u0435\u0448\u0435\u043d\u043a\u0430"
    ],
    "name:rus_x_preferred":[
        "\u0411\u043b\u0430\u0433\u043e\u0432\u0435\u0448\u0435\u043d\u043a\u0430"
    ],
    "name:und_x_variant":[
        "Blagoveshchenskoye",
        "Blagoveshenka"
    ],
    "wof:name":"Blagoveshenka",
    "wof:placetype":"locality"
},
  "geometry": {"coordinates":[72.9678,40.97474],"type":"Point"}
}