{
  "type": "Feature",
  "properties": {
    "gn:admin1_code":"03",
    "gn:asciiname":"Beshmazar",
    "gn:country_code":"KG",
    "gn:dem":934,
    "gn:feature_class":"P",
    "gn:feature_code":"PPL",
    "gn:name":"Beshmazar",
    "gn:population":0,
    "gn:timezone":"Asia/Bishkek",
    "iso:country":"KG",
    "name:kir_x_preferred":[
        "\u0411\u0435\u0448\u043c\u0430\u0437\u0430\u0440"
    ],
    "name:rus_x_preferred":[
        "\u0411\u0435\u0448\u043c\u0430\u0437\u0430\u0440"
    ],
    "wof:name":"Beshmazar",
    "wof:placetype":"locality"
},
  "geometry": {"coordinates":[72.69595,41.63815],"type":"Point"}
}