{
  "type": "Feature",
  "properties": {
    "gn:admin1_code":"07",
    "gn:asciiname":"Kyzyl-Tuu",
    "gn:country_code":"KG",
    "gn:dem":1727,
    "gn:feature_class":"P",
    "gn:feature_code":"PPL",
    "gn:name":"Kyzyl-Tuu",
    "gn:population":0,
    "gn:timezone":"Asia/Bishkek",
    "iso:country":"KG",
    "name:kir_x_preferred":[
        "\u041a\u044b\u0437\u044b\u043b-\u0422\u0443\u0443"
    ],
    "name:rus_x_preferred":[
        "\u041a\u044b\u0437\u044b\u043b\u0442\u0443"
    ],
    "name:und_x_variant":[
        "Kyzyltu",
        "Kyzyl-Tuu"
    ],
    "wof:name":"Kyzyl-Tuu",
    "wof:placetype":"locality"
},
  "geometry": {"coordinates":[76.67421999999998,42.18527],"type":"Point"}
}