{
  "type": "Feature",
  "properties": {
    "gn:admin1_code":"08",
    "gn:asciiname":"Zimov'ye Taka",
    "gn:country_code":"KG",
    "gn:dem":2937,
    "gn:feature_class":"P",
    "gn:feature_code":"PPL",
    "gn:name":"Zimov\u2019ye Taka",
    "gn:population":0,
    "gn:timezone":"Asia/Bishkek",
    "iso:country":"KG",
    "name:kir_x_preferred":[
        "\u0417\u0438\u043c\u043e\u0432\u044c\u0435 \u0422\u0430\u043a\u0430"
    ],
    "name:rus_x_preferred":[
        "\u0417\u0438\u043c\u043e\u0432\u044c\u0435 \u0422\u0430\u043a\u0430"
    ],
    "name:rus_x_variant":[
        "Zimov\u2019ye Taka"
    ],
    "name:und_x_variant":[
        "Taka"
    ],
    "wof:name":"Zimov'ye Taka",
    "wof:placetype":"locality"
},
  "geometry": {"coordinates":[72.44184,39.46101],"type":"Point"}
}