{
  "type": "Feature",
  "properties": {
    "gn:admin1_code":"02",
    "gn:asciiname":"Zheleznodorozhnoye",
    "gn:country_code":"KG",
    "gn:dem":891,
    "gn:feature_class":"P",
    "gn:feature_code":"PPL",
    "gn:name":"Zheleznodorozhnoye",
    "gn:population":0,
    "gn:timezone":"Asia/Bishkek",
    "iso:country":"KG",
    "name:kir_x_preferred":[
        "\u0416\u0435\u043b\u0435\u0437\u043d\u043e\u0434\u043epo\u0436\u043d\u043e\u0435"
    ],
    "name:rus_x_preferred":[
        "\u0416\u0435\u043b\u0435\u0437\u043d\u043e\u0434\u043e\u0440\u043e\u0436\u043d\u043e\u0435"
    ],
    "wof:name":"Zheleznodorozhnoye",
    "wof:placetype":"locality"
},
  "geometry": {"coordinates":[75.40248000000003,42.81875],"type":"Point"}
}