{
  "type": "Feature",
  "properties": {
    "gn:admin1_code":"09",
    "gn:asciiname":"Boz-Adyr",
    "gn:country_code":"KG",
    "gn:dem":1185,
    "gn:feature_class":"P",
    "gn:feature_code":"PPLA3",
    "gn:name":"Boz-Adyr",
    "gn:population":0,
    "gn:timezone":"Asia/Bishkek",
    "iso:country":"KG",
    "name:kir_x_preferred":[
        "Boz-Adyr"
    ],
    "name:rus_x_preferred":[
        "\u0411\u043e\u0437-\u0410\u0434\u044b\u0440"
    ],
    "name:uzb_x_preferred":[
        "Bo\u2018z-Adir"
    ],
    "wof:name":"Boz-Adyr",
    "wof:placetype":"locality"
},
  "geometry": {"coordinates":[71.07338,39.9986],"type":"Point"}
}