{
  "type": "Feature",
  "properties": {
    "gn:admin1_code":"03",
    "gn:asciiname":"Borluu-Kyya",
    "gn:country_code":"KG",
    "gn:dem":1431,
    "gn:feature_class":"P",
    "gn:feature_code":"PPL",
    "gn:name":"Borluu-Kyya",
    "gn:population":0,
    "gn:timezone":"Asia/Bishkek",
    "iso:country":"KG",
    "name:kir_x_preferred":[
        "\u0411\u043e\u0440\u043b\u0443\u0443-\u041a\u044b\u044f"
    ],
    "name:rus_x_preferred":[
        "\u0411\u043e\u0440\u043b\u0443\u0443-\u041a\u044b\u044f"
    ],
    "name:und_x_variant":[
        "Burlykiya",
        "Borluu-Kyya"
    ],
    "wof:name":"Borluu-Kyya",
    "wof:placetype":"locality"
},
  "geometry": {"coordinates":[73.31698,41.92032],"type":"Point"}
}