{
  "type": "Feature",
  "properties": {
    "gn:admin1_code":"09",
    "gn:asciiname":"Kon",
    "gn:country_code":"KG",
    "gn:dem":940,
    "gn:feature_class":"P",
    "gn:feature_code":"PPL",
    "gn:name":"Kon",
    "gn:population":0,
    "gn:timezone":"Asia/Bishkek",
    "iso:country":"KG",
    "name:kir_x_preferred":[
        "\u041a\u043e\u043d"
    ],
    "name:rus_x_preferred":[
        "\u041a\u043e\u043d"
    ],
    "wof:name":"Kon",
    "wof:placetype":"locality"
},
  "geometry": {"coordinates":[72.01824999999999,40.2324],"type":"Point"}
}