{
  "type": "Feature",
  "properties": {
    "gn:admin1_code":"09",
    "gn:asciiname":"Kon",
    "gn:country_code":"KG",
    "gn:dem":940,
    "gn:feature_class":"P",
    "gn:feature_code":"PPL",
    "gn:name":"Kon",
    "gn:population":0,
    "gn:timezone":"Asia/Bishkek",
    "iso:country":"KG",
    "name:bpy_x_preferred":[
        "\u0995\u09cb\u09a8"
    ],
    "name:ceb_x_preferred":[
        "Kon"
    ],
    "name:deu_x_preferred":[
        "Kon"
    ],
    "name:epo_x_preferred":[
        "KON"
    ],
    "name:fra_x_preferred":[
        "Kon"
    ],
    "name:kir_x_preferred":[
        "\u041a\u043e\u043d"
    ],
    "name:nld_x_preferred":[
        "Ko\u0144"
    ],
    "name:rus_x_preferred":[
        "\u041a\u043e\u043d"
    ],
    "name:spa_x_preferred":[
        "Kon"
    ],
    "name:swe_x_preferred":[
        "Kon"
    ],
    "name:vie_x_preferred":[
        "Kon"
    ],
    "wof:name":"Kon",
    "wof:placetype":"locality"
},
  "geometry": {"coordinates":[72.01824999999999,40.2324],"type":"Point"}
}