{
  "type": "Feature",
  "properties": {
    "gn:admin1_code":"08",
    "gn:asciiname":"Kyymyl",
    "gn:country_code":"KG",
    "gn:dem":918,
    "gn:feature_class":"P",
    "gn:feature_code":"PPL",
    "gn:name":"Kyymyl",
    "gn:population":0,
    "gn:timezone":"Asia/Bishkek",
    "iso:country":"KG",
    "name:kir_x_preferred":[
        "\u041a\u044b\u0439\u043c\u044b\u043b"
    ],
    "name:rus_x_preferred":[
        "\u041a\u044b\u0439\u043c\u044b\u043b"
    ],
    "wof:name":"Kyymyl",
    "wof:placetype":"locality"
},
  "geometry": {"coordinates":[73.23971,40.81786],"type":"Point"}
}