{
  "type": "Feature",
  "properties": {
    "gn:admin1_code":"03",
    "gn:asciiname":"Kel'",
    "gn:country_code":"KG",
    "gn:dem":1720,
    "gn:feature_class":"P",
    "gn:feature_code":"PPL",
    "gn:name":"K\u00ebl\u2019",
    "gn:population":0,
    "gn:timezone":"Asia/Bishkek",
    "iso:country":"KG",
    "name:kir_x_preferred":[
        "\u041a\u04e9\u043b"
    ],
    "name:rus_x_preferred":[
        "K\u00ebl\u2019"
    ],
    "name:rus_x_variant":[
        "\u041a\u0451\u043b\u044c"
    ],
    "name:und_x_variant":[
        "K\u00ebl\u2019"
    ],
    "wof:name":"Kel'",
    "wof:placetype":"locality"
},
  "geometry": {"coordinates":[73.95024000000002,41.78105],"type":"Point"}
}