{
  "type": "Feature",
  "properties": {
    "gn:admin1_code":"08",
    "gn:asciiname":"Kyzyl-Suu",
    "gn:country_code":"KG",
    "gn:dem":1298,
    "gn:feature_class":"P",
    "gn:feature_code":"PPL",
    "gn:name":"Kyzyl-Suu",
    "gn:population":0,
    "gn:timezone":"Asia/Bishkek",
    "iso:country":"KG",
    "name:kir_x_preferred":[
        "\u041a\u044b\u0437\u044b\u043b-\u0421\u0443\u0443"
    ],
    "name:rus_x_preferred":[
        "\u041a\u044b\u0437\u044b\u043b-\u0421\u0443\u0443"
    ],
    "wof:name":"Kyzyl-Suu",
    "wof:placetype":"locality"
},
  "geometry": {"coordinates":[73.26083,40.43428],"type":"Point"}
}