{
  "type": "Feature",
  "properties": {
    "gn:admin1_code":"04",
    "gn:asciiname":"Karabuk",
    "gn:country_code":"KG",
    "gn:dem":2017,
    "gn:feature_class":"P",
    "gn:feature_code":"PPL",
    "gn:name":"Karabuk",
    "gn:population":0,
    "gn:timezone":"Asia/Bishkek",
    "iso:country":"KG",
    "name:kir_x_preferred":[
        "\u041a\u0430\u0440\u0430\u0431\u0443\u043a"
    ],
    "name:rus_x_preferred":[
        "\u041a\u0430\u0440\u0430\u0431\u0443\u043a"
    ],
    "wof:name":"Karabuk",
    "wof:placetype":"locality"
},
  "geometry": {"coordinates":[75.86084,41.46499],"type":"Point"}
}