{
  "type": "Feature",
  "properties": {
    "gn:admin1_code":"09",
    "gn:asciiname":"Kesken-Tash",
    "gn:country_code":"KG",
    "gn:dem":1265,
    "gn:feature_class":"P",
    "gn:feature_code":"PPL",
    "gn:name":"Kesken-Tash",
    "gn:population":0,
    "gn:timezone":"Asia/Bishkek",
    "iso:country":"KG",
    "name:kir_x_preferred":[
        "\u041a\u0435\u0441\u043a\u0435\u043d-\u0422\u0430\u0448"
    ],
    "name:rus_x_preferred":[
        "\u041a\u0435\u0441\u043a\u0435\u043d-\u0422\u0430\u0448"
    ],
    "name:und_x_variant":[
        "Kisyk",
        "Kesken-Tash",
        "Kysyk"
    ],
    "name:uzb_x_preferred":[
        "Kesken-Tosh"
    ],
    "wof:name":"Kesken-Tash",
    "wof:placetype":"locality"
},
  "geometry": {"coordinates":[71.75219,40.03525],"type":"Point"}
}