{
  "type": "Feature",
  "properties": {
    "gn:admin1_code":"08",
    "gn:asciiname":"Bortumshuk",
    "gn:country_code":"KG",
    "gn:dem":2827,
    "gn:feature_class":"P",
    "gn:feature_code":"PPL",
    "gn:name":"Bortumshuk",
    "gn:population":0,
    "gn:timezone":"Asia/Bishkek",
    "iso:country":"KG",
    "name:kir_x_preferred":[
        "\u0411\u043e\u0440\u0442\u0443\u043c\u0448\u0443\u043a"
    ],
    "name:rus_x_preferred":[
        "\u0411\u043e\u0440\u0442\u0443\u043c\u0448\u0443\u043a"
    ],
    "wof:name":"Bortumshuk",
    "wof:placetype":"locality"
},
  "geometry": {"coordinates":[72.67403,39.64949],"type":"Point"}
}