{
  "type": "Feature",
  "properties": {
    "gn:admin1_code":"02",
    "gn:asciiname":"Ak-Say",
    "gn:country_code":"KG",
    "gn:dem":1014,
    "gn:feature_class":"P",
    "gn:feature_code":"PPL",
    "gn:name":"Ak-Say",
    "gn:population":0,
    "gn:timezone":"Asia/Bishkek",
    "iso:country":"KG",
    "name:kir_x_preferred":[
        "\u0410\u043a-\u0421\u0430\u0439"
    ],
    "name:rus_x_preferred":[
        "\u0410\u043a-\u0421\u0430\u0439"
    ],
    "wof:name":"Ak-Say",
    "wof:placetype":"locality"
},
  "geometry": {"coordinates":[75.05856,42.7475],"type":"Point"}
}