{
  "type": "Feature",
  "properties": {
    "gn:admin1_code":"03",
    "gn:asciiname":"Alcha",
    "gn:country_code":"KG",
    "gn:dem":1084,
    "gn:feature_class":"P",
    "gn:feature_code":"PPL",
    "gn:name":"Alcha",
    "gn:population":0,
    "gn:timezone":"Asia/Bishkek",
    "iso:country":"KG",
    "name:che_x_preferred":[
        "\u0410\u043b\u0447\u0430"
    ],
    "name:kir_x_preferred":[
        "\u0410\u043b\u0447\u0430"
    ],
    "name:rus_x_preferred":[
        "\u0410\u043b\u0447\u0430"
    ],
    "name:tgk_x_preferred":[
        "\u0410\u043b\u0447\u0430"
    ],
    "wof:name":"Alcha",
    "wof:placetype":"locality"
},
  "geometry": {"coordinates":[72.23541999999998,41.51484],"type":"Point"}
}