{
  "type": "Feature",
  "properties": {
    "gn:admin1_code":"00",
    "gn:asciiname":"Dzhalpak-Sary",
    "gn:country_code":"KG",
    "gn:dem":1162,
    "gn:feature_class":"P",
    "gn:feature_code":"PPL",
    "gn:name":"Dzhalpak-Sary",
    "gn:population":0,
    "gn:timezone":"Asia/Bishkek",
    "iso:country":"KG",
    "name:kir_x_preferred":[
        "\u0416\u0430\u043b\u043f\u0430\u043a-\u0421\u0430\u0440\u044b"
    ],
    "wof:name":"Dzhalpak-Sary",
    "wof:placetype":"locality"
},
  "geometry": {"coordinates":[73.09148,41.15042],"type":"Point"}
}