{
  "type": "Feature",
  "properties": {
    "gn:admin1_code":"10",
    "gn:asciiname":"Yuqori Uvam",
    "gn:country_code":"KG",
    "gn:dem":996,
    "gn:feature_class":"P",
    "gn:feature_code":"PPL",
    "gn:name":"Yuqori Uvam",
    "gn:population":0,
    "gn:timezone":"Asia/Bishkek",
    "iso:country":"KG",
    "name:uzb_x_preferred":[
        "Yuqori Uvam"
    ],
    "wof:name":"Yuqori Uvam",
    "wof:placetype":"locality"
},
  "geometry": {"coordinates":[72.82298,40.54102],"type":"Point"}
}