{
  "type": "Feature",
  "properties": {
    "gn:admin1_code":"02",
    "gn:asciiname":"Rovnoye",
    "gn:country_code":"KG",
    "gn:dem":674,
    "gn:feature_class":"P",
    "gn:feature_code":"PPL",
    "gn:name":"Rovnoye",
    "gn:population":0,
    "gn:timezone":"Asia/Bishkek",
    "iso:country":"KG",
    "name:kir_x_preferred":[
        "\u0420\u043e\u0432\u043d\u043e\u0435"
    ],
    "name:rus_x_preferred":[
        "\u0420\u043e\u0432\u043d\u043e\u0435"
    ],
    "wof:name":"Rovnoye",
    "wof:placetype":"locality"
},
  "geometry": {"coordinates":[73.5307,42.89448],"type":"Point"}
}