{
  "type": "Feature",
  "properties": {
    "gn:admin1_code":"03",
    "gn:asciiname":"Mazar",
    "gn:country_code":"KG",
    "gn:dem":1086,
    "gn:feature_class":"P",
    "gn:feature_code":"PPL",
    "gn:name":"Mazar",
    "gn:population":0,
    "gn:timezone":"Asia/Bishkek",
    "iso:country":"KG",
    "name:ceb_x_preferred":[
        "Mazar"
    ],
    "name:deu_x_preferred":[
        "Mazar"
    ],
    "name:fas_x_preferred":[
        "\u0645\u0632\u0627\u0631"
    ],
    "name:fra_x_preferred":[
        "Mazar"
    ],
    "name:heb_x_preferred":[
        "\u05de\u05d6\u05e8"
    ],
    "name:kir_x_preferred":[
        "\u041c\u0430\u0437\u0430\u0440"
    ],
    "name:rus_x_preferred":[
        "\u041c\u0430\u0437\u0430\u0440"
    ],
    "name:swe_x_preferred":[
        "Mazar"
    ],
    "wof:name":"Mazar",
    "wof:placetype":"locality"
},
  "geometry": {"coordinates":[71.50596,41.34898],"type":"Point"}
}