{
  "type": "Feature",
  "properties": {
    "gn:admin1_code":"00",
    "gn:asciiname":"Katyrantash",
    "gn:country_code":"KG",
    "gn:dem":2496,
    "gn:feature_class":"P",
    "gn:feature_code":"PPL",
    "gn:name":"Katyrantash",
    "gn:population":0,
    "gn:timezone":"Asia/Bishkek",
    "iso:country":"KG",
    "wof:name":"Katyrantash",
    "wof:placetype":"locality"
},
  "geometry": {"coordinates":[73.59999999999999,40.26667],"type":"Point"}
}