{
  "type": "Feature",
  "properties": {
    "gn:admin1_code":"03",
    "gn:asciiname":"Syny",
    "gn:country_code":"KG",
    "gn:dem":1017,
    "gn:feature_class":"P",
    "gn:feature_code":"PPL",
    "gn:name":"Syny",
    "gn:population":0,
    "gn:timezone":"Asia/Bishkek",
    "iso:country":"KG",
    "name:kir_x_preferred":[
        "Syny"
    ],
    "name:rus_x_preferred":[
        "\u0421\u044b\u043d\u044b"
    ],
    "wof:name":"Syny",
    "wof:placetype":"locality"
},
  "geometry": {"coordinates":[72.05521,41.61635],"type":"Point"}
}