{
  "type": "Feature",
  "properties": {
    "gn:admin1_code":"02",
    "gn:asciiname":"Leninskoye",
    "gn:country_code":"KG",
    "gn:dem":650,
    "gn:feature_class":"P",
    "gn:feature_code":"PPL",
    "gn:name":"Leninskoye",
    "gn:population":0,
    "gn:timezone":"Asia/Bishkek",
    "iso:country":"KG",
    "name:kir_x_preferred":[
        "Leninskoe"
    ],
    "name:rus_x_preferred":[
        "\u041b\u0435\u043d\u0438\u043d\u0441\u043a\u043e\u0435"
    ],
    "wof:name":"Leninskoye",
    "wof:placetype":"locality"
},
  "geometry": {"coordinates":[74.66252,42.97057],"type":"Point"}
}