{
  "type": "Feature",
  "properties": {
    "gn:admin1_code":"03",
    "gn:asciiname":"Boz-Chychkan",
    "gn:country_code":"KG",
    "gn:dem":809,
    "gn:feature_class":"P",
    "gn:feature_code":"PPL",
    "gn:name":"Boz-Chychkan",
    "gn:population":0,
    "gn:timezone":"Asia/Bishkek",
    "iso:country":"KG",
    "name:kir_x_preferred":[
        "\u0411\u043e\u0437-\u0427\u044b\u0447\u043a\u0430\u043d"
    ],
    "name:rus_x_preferred":[
        "\u0411\u043e\u0437-\u0427\u044b\u0447\u043a\u0430\u043d"
    ],
    "wof:name":"Boz-Chychkan",
    "wof:placetype":"locality"
},
  "geometry": {"coordinates":[73.0805,40.87069],"type":"Point"}
}