{
  "type": "Feature",
  "properties": {
    "gn:admin1_code":"09",
    "gn:asciiname":"Mal'mut",
    "gn:country_code":"KG",
    "gn:dem":1362,
    "gn:feature_class":"P",
    "gn:feature_code":"PPL",
    "gn:name":"Mal\u2019mut",
    "gn:population":0,
    "gn:timezone":"Asia/Bishkek",
    "iso:country":"KG",
    "name:rus_x_preferred":[
        "Mal\u2019mut"
    ],
    "name:rus_x_variant":[
        "\u041c\u0430\u043b\u044c\u043c\u0443\u0442"
    ],
    "name:uzb_x_preferred":[
        "Malmut"
    ],
    "wof:name":"Mal'mut",
    "wof:placetype":"locality"
},
  "geometry": {"coordinates":[71.18092,40.00261],"type":"Point"}
}