{
  "type": "Feature",
  "properties": {
    "gn:admin1_code":"02",
    "gn:asciiname":"Kara-Tebe",
    "gn:country_code":"KG",
    "gn:dem":685,
    "gn:feature_class":"P",
    "gn:feature_code":"PPL",
    "gn:name":"Kara-T\u00ebb\u00eb",
    "gn:population":0,
    "gn:timezone":"Asia/Bishkek",
    "iso:country":"KG",
    "name:kir_x_preferred":[
        "\u041a\u0430\u0440\u0430-\u0414\u04e9\u0431\u04e9"
    ],
    "name:rus_x_preferred":[
        "Kara-T\u00ebb\u00eb"
    ],
    "name:rus_x_variant":[
        "\u041a\u0430\u0440\u0430-\u0422\u0451\u0431\u0451"
    ],
    "wof:name":"Kara-Tebe",
    "wof:placetype":"locality"
},
  "geometry": {"coordinates":[73.72237,42.90413],"type":"Point"}
}