{
  "type": "Feature",
  "properties": {
    "gn:admin1_code":"03",
    "gn:asciiname":"Shaydan",
    "gn:country_code":"KG",
    "gn:dem":1571,
    "gn:feature_class":"P",
    "gn:feature_code":"PPL",
    "gn:name":"Shaydan",
    "gn:population":0,
    "gn:timezone":"Asia/Bishkek",
    "iso:country":"KG",
    "name:kir_x_preferred":[
        "\u0428\u0430\u0439\u0434\u0430\u043d"
    ],
    "name:rus_x_preferred":[
        "\u0428\u0430\u0439\u0434\u0430\u043d"
    ],
    "name:und_x_variant":[
        "Kol\u2019me",
        "Shaydan"
    ],
    "wof:name":"Shaydan",
    "wof:placetype":"locality"
},
  "geometry": {"coordinates":[72.78915000000001,41.29685],"type":"Point"}
}