{
  "type": "Feature",
  "properties": {
    "gn:admin1_code":"07",
    "gn:asciiname":"Uchkaynar",
    "gn:country_code":"KG",
    "gn:dem":1691,
    "gn:feature_class":"P",
    "gn:feature_code":"PPL",
    "gn:name":"Uchkaynar",
    "gn:population":0,
    "gn:timezone":"Asia/Bishkek",
    "iso:country":"KG",
    "name:kir_x_preferred":[
        "\u0423\u0447-\u041a\u0430\u0439\u043d\u0430\u0440"
    ],
    "name:rus_x_preferred":[
        "\u0423\u0447\u043a\u0430\u0439\u043d\u0430\u0440"
    ],
    "wof:name":"Uchkaynar",
    "wof:placetype":"locality"
},
  "geometry": {"coordinates":[78.46425000000001,42.53809],"type":"Point"}
}