{
  "type": "Feature",
  "properties": {
    "gn:admin1_code":"08",
    "gn:asciiname":"Bel",
    "gn:country_code":"KG",
    "gn:dem":1439,
    "gn:feature_class":"P",
    "gn:feature_code":"PPL",
    "gn:name":"Bel",
    "gn:population":0,
    "gn:timezone":"Asia/Bishkek",
    "iso:country":"KG",
    "name:kir_x_preferred":[
        "Bel"
    ],
    "name:rus_x_preferred":[
        "Bel\u2019"
    ],
    "name:rus_x_variant":[
        "\u0411\u0435\u043b\u044c"
    ],
    "name:und_x_variant":[
        "Bel\u2019uryuk"
    ],
    "wof:name":"Bel",
    "wof:placetype":"locality"
},
  "geometry": {"coordinates":[72.47492,40.2718],"type":"Point"}
}