{
  "type": "Feature",
  "properties": {
    "gn:admin1_code":"03",
    "gn:asciiname":"Khadzhir-Abad",
    "gn:country_code":"KG",
    "gn:dem":586,
    "gn:feature_class":"P",
    "gn:feature_code":"PPL",
    "gn:name":"Khadzhir-Abad",
    "gn:population":0,
    "gn:timezone":"Asia/Bishkek",
    "iso:country":"KG",
    "name:kir_x_preferred":[
        "\u0425\u0430\u0434\u0436\u0438\u0440-\u0410\u0431\u0430\u0434"
    ],
    "name:rus_x_preferred":[
        "\u0425\u0430\u0434\u0436\u0438\u0440-\u0410\u0431\u0430\u0434"
    ],
    "name:und_x_variant":[
        "Khodzharabad"
    ],
    "name:uzb_x_preferred":[
        "Xajir-Obod"
    ],
    "wof:name":"Khadzhir-Abad",
    "wof:placetype":"locality"
},
  "geometry": {"coordinates":[72.62183,40.9461],"type":"Point"}
}