{
  "type": "Feature",
  "properties": {
    "gn:admin1_code":"07",
    "gn:asciiname":"Zholgolot",
    "gn:country_code":"KG",
    "gn:dem":1787,
    "gn:feature_class":"P",
    "gn:feature_code":"PPL",
    "gn:name":"Zholgolot",
    "gn:population":0,
    "gn:timezone":"Asia/Bishkek",
    "iso:country":"KG",
    "name:kir_x_preferred":[
        "\u0416\u043e\u043b\u0433\u043e\u043b\u043e\u0442"
    ],
    "name:rus_x_preferred":[
        "\u0416\u043e\u043b\u0433\u043e\u043b\u043e\u0442"
    ],
    "name:und_x_variant":[
        "Dzhol-Golot"
    ],
    "wof:name":"Zholgolot",
    "wof:placetype":"locality"
},
  "geometry": {"coordinates":[78.42338000000002,42.47689],"type":"Point"}
}