{
  "type": "Feature",
  "properties": {
    "gn:admin1_code":"03",
    "gn:asciiname":"Shyng-Say",
    "gn:country_code":"KG",
    "gn:dem":1045,
    "gn:feature_class":"P",
    "gn:feature_code":"PPL",
    "gn:name":"Shyng-Say",
    "gn:population":0,
    "gn:timezone":"Asia/Bishkek",
    "iso:country":"KG",
    "name:kir_x_preferred":[
        "\u0428\u044b\u043d\u0433-\u0421\u0430\u0439"
    ],
    "name:rus_x_preferred":[
        "\u0428\u044b\u043d\u0433-\u0421\u0430\u0439"
    ],
    "wof:name":"Shyng-Say",
    "wof:placetype":"locality"
},
  "geometry": {"coordinates":[72.31304,41.31906],"type":"Point"}
}