{
  "type": "Feature",
  "properties": {
    "gn:admin1_code":"08",
    "gn:asciiname":"Kyzyl-Too",
    "gn:country_code":"KG",
    "gn:dem":1185,
    "gn:feature_class":"P",
    "gn:feature_code":"PPL",
    "gn:name":"Kyzyl-Too",
    "gn:population":0,
    "gn:timezone":"Asia/Bishkek",
    "iso:country":"KG",
    "name:kir_x_preferred":[
        "\u041a\u044b\u0437\u044b\u043b-\u0422\u043e\u043e"
    ],
    "name:rus_x_preferred":[
        "\u041a\u044b\u0437\u044b\u043b-\u0422\u043e\u043e"
    ],
    "wof:name":"Kyzyl-Too",
    "wof:placetype":"locality"
},
  "geometry": {"coordinates":[73.52019,40.82632],"type":"Point"}
}