{
  "type": "Feature",
  "properties": {
    "gn:admin1_code":"08",
    "gn:asciiname":"Dzhaka",
    "gn:country_code":"KG",
    "gn:dem":1279,
    "gn:feature_class":"P",
    "gn:feature_code":"PPL",
    "gn:name":"Dzhaka",
    "gn:population":0,
    "gn:timezone":"Asia/Bishkek",
    "iso:country":"KG",
    "name:kir_x_preferred":[
        "\u0416\u0430\u043a\u0430"
    ],
    "name:rus_x_preferred":[
        "\u0414\u0436\u0430\u043a\u0430"
    ],
    "wof:name":"Dzhaka",
    "wof:placetype":"locality"
},
  "geometry": {"coordinates":[73.25395,40.44878],"type":"Point"}
}