{
  "type": "Feature",
  "properties": {
    "gn:admin1_code":"03",
    "gn:asciiname":"Karabulak",
    "gn:country_code":"KG",
    "gn:dem":1340,
    "gn:feature_class":"P",
    "gn:feature_code":"PPL",
    "gn:name":"Karabulak",
    "gn:population":0,
    "gn:timezone":"Asia/Bishkek",
    "iso:country":"KG",
    "name:kir_x_preferred":[
        "\u041a\u0430\u0440\u0430\u0431\u0443\u043b\u0430\u043a"
    ],
    "name:rus_x_preferred":[
        "\u041a\u0430\u0440\u0430\u0431\u0443\u043b\u0430\u043a"
    ],
    "wof:name":"Karabulak",
    "wof:placetype":"locality"
},
  "geometry": {"coordinates":[74.20398,41.39588],"type":"Point"}
}