{
  "type": "Feature",
  "properties": {
    "gn:admin1_code":"02",
    "gn:asciiname":"Chunkurchak",
    "gn:country_code":"KG",
    "gn:dem":1949,
    "gn:feature_class":"P",
    "gn:feature_code":"PPL",
    "gn:name":"Chunkurchak",
    "gn:population":0,
    "gn:timezone":"Asia/Bishkek",
    "iso:country":"KG",
    "name:kir_x_preferred":[
        "\u0427\u0443\u043d\u043a\u0443\u0440\u0447\u0430\u043a"
    ],
    "name:rus_x_preferred":[
        "\u0427\u0443\u043d\u043a\u0443\u0440\u0447\u0430\u043a"
    ],
    "name:und_x_variant":[
        "Molochno-Tovarnaya Ferma Sovkhoza Alamedin"
    ],
    "wof:name":"Chunkurchak",
    "wof:placetype":"locality"
},
  "geometry": {"coordinates":[74.61663,42.64219],"type":"Point"}
}