{
  "type": "Feature",
  "properties": {
    "gn:admin1_code":"02",
    "gn:asciiname":"Bol'shevik",
    "gn:country_code":"KG",
    "gn:dem":698,
    "gn:feature_class":"P",
    "gn:feature_code":"PPL",
    "gn:name":"Bol\u2019shevik",
    "gn:population":0,
    "gn:timezone":"Asia/Bishkek",
    "iso:country":"KG",
    "name:kir_x_preferred":[
        "\u0411\u043e\u043b\u044c\u0448\u0435\u0432\u0438\u043a"
    ],
    "name:rus_x_preferred":[
        "Bol\u2019shevik"
    ],
    "name:rus_x_variant":[
        "\u0411\u043e\u043b\u044c\u0448\u0435\u0432\u0438\u043a"
    ],
    "wof:name":"Bol'shevik",
    "wof:placetype":"locality"
},
  "geometry": {"coordinates":[74.11079000000002,42.86939],"type":"Point"}
}