{
  "type": "Feature",
  "properties": {
    "gn:admin1_code":"03",
    "gn:asciiname":"Kyzyl-Tokoy",
    "gn:country_code":"KG",
    "gn:dem":1215,
    "gn:feature_class":"P",
    "gn:feature_code":"PPL",
    "gn:name":"Kyzyl-Tokoy",
    "gn:population":0,
    "gn:timezone":"Asia/Bishkek",
    "iso:country":"KG",
    "name:kir_x_preferred":[
        "\u041a\u044b\u0437\u044b\u043b-\u0422\u043e\u043a\u043e\u0439"
    ],
    "name:rus_x_preferred":[
        "\u041a\u044b\u0437\u044b\u043b-\u0422\u043e\u043a\u043e\u0439"
    ],
    "name:und_x_variant":[
        "Kizyl-Tukay",
        "Kyzyl-Tokay",
        "Kyzyl-Tokoy"
    ],
    "name:uzb_x_preferred":[
        "Qizil-Toqoy"
    ],
    "wof:name":"Kyzyl-Tokoy",
    "wof:placetype":"locality"
},
  "geometry": {"coordinates":[71.32810000000001,41.38473],"type":"Point"}
}