{
  "type": "Feature",
  "properties": {
    "gn:admin1_code":"08",
    "gn:asciiname":"Laglan",
    "gn:country_code":"KG",
    "gn:dem":1523,
    "gn:feature_class":"P",
    "gn:feature_code":"PPL",
    "gn:name":"Laglan",
    "gn:population":0,
    "gn:timezone":"Asia/Bishkek",
    "iso:country":"KG",
    "name:kir_x_preferred":[
        "\u041b\u0430\u0433\u043b\u0430\u043d"
    ],
    "name:rus_x_preferred":[
        "\u041b\u0430\u0433\u043b\u0430\u043d"
    ],
    "name:und_x_variant":[
        "Lyaglyan",
        "Lyaglan",
        "Laglan"
    ],
    "wof:name":"Laglan",
    "wof:placetype":"locality"
},
  "geometry": {"coordinates":[73.09787,40.27866],"type":"Point"}
}