{
  "type": "Feature",
  "properties": {
    "gn:admin1_code":"08",
    "gn:asciiname":"Berdoba",
    "gn:country_code":"KG",
    "gn:dem":3470,
    "gn:feature_class":"P",
    "gn:feature_code":"PPL",
    "gn:name":"Berdoba",
    "gn:population":0,
    "gn:timezone":"Asia/Bishkek",
    "iso:country":"KG",
    "name:kir_x_preferred":[
        "Bor-D\u00f6b\u00f6"
    ],
    "name:rus_x_preferred":[
        "\u0411\u0435\u0440\u0434\u043e\u0431\u0430"
    ],
    "name:und_x_variant":[
        "Bor-Doba",
        "Bordaba",
        "Berdoba"
    ],
    "wof:name":"Berdoba",
    "wof:placetype":"locality"
},
  "geometry": {"coordinates":[73.26831,39.50779],"type":"Point"}
}