{
  "type": "Feature",
  "properties": {
    "gn:admin1_code":"08",
    "gn:asciiname":"Kurbu-Tash",
    "gn:country_code":"KG",
    "gn:dem":1654,
    "gn:feature_class":"P",
    "gn:feature_code":"PPL",
    "gn:name":"Kurbu-Tash",
    "gn:population":0,
    "gn:timezone":"Asia/Bishkek",
    "iso:country":"KG",
    "name:kir_x_preferred":[
        "\u041a\u0443\u0440\u0431\u0443-\u0422\u0430\u0448"
    ],
    "name:rus_x_preferred":[
        "\u041a\u0443\u0440\u0431\u0443-\u0422\u0430\u0448"
    ],
    "wof:name":"Kurbu-Tash",
    "wof:placetype":"locality"
},
  "geometry": {"coordinates":[73.29559999999999,40.61355],"type":"Point"}
}