{
  "type": "Feature",
  "properties": {
    "gn:admin1_code":"08",
    "gn:asciiname":"Chagyr",
    "gn:country_code":"KG",
    "gn:dem":1070,
    "gn:feature_class":"P",
    "gn:feature_code":"PPL",
    "gn:name":"Chagyr",
    "gn:population":0,
    "gn:timezone":"Asia/Bishkek",
    "iso:country":"KG",
    "name:kir_x_preferred":[
        "\u0427\u0430\u0433\u044b\u0440"
    ],
    "name:rus_x_preferred":[
        "\u0427\u0430\u0433\u044b\u0440"
    ],
    "name:uzb_x_preferred":[
        "Chag\u2018ir"
    ],
    "wof:name":"Chagyr",
    "wof:placetype":"locality"
},
  "geometry": {"coordinates":[72.92158000000001,40.54823],"type":"Point"}
}