{
  "type": "Feature",
  "properties": {
    "gn:admin1_code":"02",
    "gn:asciiname":"Dzhal",
    "gn:country_code":"KG",
    "gn:dem":965,
    "gn:feature_class":"P",
    "gn:feature_code":"PPL",
    "gn:name":"Dzhal",
    "gn:population":0,
    "gn:timezone":"Asia/Bishkek",
    "iso:country":"KG",
    "name:kir_x_preferred":[
        "\u0416\u0430\u043b"
    ],
    "name:rus_x_preferred":[
        "\u0414\u0436\u0430\u043b"
    ],
    "wof:name":"Dzhal",
    "wof:placetype":"locality"
},
  "geometry": {"coordinates":[74.50879,42.79247],"type":"Point"}
}