{
  "type": "Feature",
  "properties": {
    "gn:admin1_code":"08",
    "gn:asciiname":"Almurut",
    "gn:country_code":"KG",
    "gn:dem":1627,
    "gn:feature_class":"P",
    "gn:feature_code":"PPL",
    "gn:name":"Almurut",
    "gn:population":0,
    "gn:timezone":"Asia/Bishkek",
    "iso:country":"KG",
    "name:kir_x_preferred":[
        "\u0410\u043b\u043c\u0443\u0440\u0443\u0442"
    ],
    "name:rus_x_preferred":[
        "\u0410\u043b\u043c\u0443\u0440\u0443\u0442"
    ],
    "wof:name":"Almurut",
    "wof:placetype":"locality"
},
  "geometry": {"coordinates":[73.19981,40.51739],"type":"Point"}
}