{
  "type": "Feature",
  "properties": {
    "gn:admin1_code":"07",
    "gn:asciiname":"Sarytologoy",
    "gn:country_code":"KG",
    "gn:dem":1803,
    "gn:feature_class":"P",
    "gn:feature_code":"PPL",
    "gn:name":"Sarytologoy",
    "gn:population":0,
    "gn:timezone":"Asia/Bishkek",
    "iso:country":"KG",
    "name:kir_x_preferred":[
        "\u0421\u0430\u0440\u044b-\u0422\u043e\u043b\u043e\u0433\u043e\u0439"
    ],
    "name:rus_x_preferred":[
        "\u0421\u0430\u0440\u044b\u0442\u043e\u043b\u043e\u0433\u043e\u0439"
    ],
    "wof:name":"Sarytologoy",
    "wof:placetype":"locality"
},
  "geometry": {"coordinates":[78.77629,42.72411],"type":"Point"}
}