{
  "type": "Feature",
  "properties": {
    "gn:admin1_code":"03",
    "gn:asciiname":"Ak-Dzhar",
    "gn:country_code":"KG",
    "gn:dem":1873,
    "gn:feature_class":"P",
    "gn:feature_code":"PPL",
    "gn:name":"Ak-Dzhar",
    "gn:population":0,
    "gn:timezone":"Asia/Bishkek",
    "iso:country":"KG",
    "name:kir_x_preferred":[
        "\u0410\u043a-\u0416\u0430\u0440"
    ],
    "name:rus_x_preferred":[
        "\u0410\u043a-\u0414\u0436\u0430\u0440"
    ],
    "wof:name":"Ak-Dzhar",
    "wof:placetype":"locality"
},
  "geometry": {"coordinates":[73.37805999999998,41.62238],"type":"Point"}
}