{
  "type": "Feature",
  "properties": {
    "gn:admin1_code":"04",
    "gn:asciiname":"Jangy-Aryk",
    "gn:country_code":"KG",
    "gn:dem":2117,
    "gn:feature_class":"P",
    "gn:feature_code":"PPL",
    "gn:name":"Jangy-Aryk",
    "gn:population":0,
    "gn:timezone":"Asia/Bishkek",
    "iso:country":"KG",
    "name:kir_x_preferred":[
        "Jangy-Aryk"
    ],
    "name:kir_x_variant":[
        "\u0416\u0430\u04a3\u044b-\u0410\u0440\u044b\u043a"
    ],
    "name:rus_x_preferred":[
        "\u0414\u0436\u0430\u043d\u0430\u0440\u044b\u043a"
    ],
    "name:und_x_variant":[
        "Dzhangi-Aryk",
        "Dzhangyaryk",
        "Dzhanaryk"
    ],
    "name:uzb_x_preferred":[
        "Yangi-Ariq"
    ],
    "wof:name":"Jangy-Aryk",
    "wof:placetype":"locality"
},
  "geometry": {"coordinates":[74.95336999999998,41.98582],"type":"Point"}
}