{
  "type": "Feature",
  "properties": {
    "gn:admin1_code":"09",
    "gn:asciiname":"Tash-Bulak",
    "gn:country_code":"KG",
    "gn:dem":1838,
    "gn:feature_class":"P",
    "gn:feature_code":"PPL",
    "gn:name":"Tash-Bulak",
    "gn:population":0,
    "gn:timezone":"Asia/Bishkek",
    "iso:country":"KG",
    "name:kir_x_preferred":[
        "\u0422\u0430\u0448-\u0411\u0443\u043b\u0430\u043a"
    ],
    "name:rus_x_preferred":[
        "\u0422\u0430\u0448-\u0411\u0443\u043b\u0430\u043a"
    ],
    "wof:name":"Tash-Bulak",
    "wof:placetype":"locality"
},
  "geometry": {"coordinates":[69.38890000000001,39.72323],"type":"Point"}
}