{
  "type": "Feature",
  "properties": {
    "gn:admin1_code":"09",
    "gn:asciiname":"Chet-Kyzyl",
    "gn:country_code":"KG",
    "gn:dem":860,
    "gn:feature_class":"P",
    "gn:feature_code":"PPL",
    "gn:name":"Chet-Kyzyl",
    "gn:population":0,
    "gn:timezone":"Asia/Bishkek",
    "iso:country":"KG",
    "name:rus_x_preferred":[
        "\u0427\u0435\u0442-\u041a\u044b\u0437\u044b\u043b"
    ],
    "wof:name":"Chet-Kyzyl",
    "wof:placetype":"locality"
},
  "geometry": {"coordinates":[70.85691,40.1412],"type":"Point"}
}