{
  "type": "Feature",
  "properties": {
    "gn:admin1_code":"07",
    "gn:asciiname":"Kul'tor",
    "gn:country_code":"KG",
    "gn:dem":1940,
    "gn:feature_class":"P",
    "gn:feature_code":"PPL",
    "gn:name":"Kul\u2019tor",
    "gn:population":0,
    "gn:timezone":"Asia/Bishkek",
    "iso:country":"KG",
    "name:kir_x_preferred":[
        "\u041a\u04e9\u043b-\u0422\u04e9\u0440"
    ],
    "name:rus_x_preferred":[
        "Kul\u2019tor"
    ],
    "name:rus_x_variant":[
        "\u041a\u0443\u043b\u044c\u0442\u043e\u0440"
    ],
    "name:und_x_variant":[
        "Kul\u2019tor"
    ],
    "wof:name":"Kul'tor",
    "wof:placetype":"locality"
},
  "geometry": {"coordinates":[76.66458,42.09031],"type":"Point"}
}