{
  "type": "Feature",
  "properties": {
    "gn:admin1_code":"08",
    "gn:asciiname":"Sary-Kolot",
    "gn:country_code":"KG",
    "gn:dem":866,
    "gn:feature_class":"P",
    "gn:feature_code":"PPL",
    "gn:name":"Sary-Kolot",
    "gn:population":0,
    "gn:timezone":"Asia/Bishkek",
    "iso:country":"KG",
    "name:kir_x_preferred":[
        "\u0421\u0430\u0440\u044b-\u041a\u043e\u043b\u043e\u0442"
    ],
    "name:rus_x_preferred":[
        "\u0421\u0430\u0440\u044b-\u041a\u043e\u043b\u043e\u0442"
    ],
    "name:uzb_x_preferred":[
        "Sari-Kolot"
    ],
    "wof:name":"Sary-Kolot",
    "wof:placetype":"locality"
},
  "geometry": {"coordinates":[73.00921,40.68048],"type":"Point"}
}