{
  "type": "Feature",
  "properties": {
    "gn:admin1_code":"02",
    "gn:asciiname":"Kenesh",
    "gn:country_code":"KG",
    "gn:dem":736,
    "gn:feature_class":"P",
    "gn:feature_code":"PPL",
    "gn:name":"Kenesh",
    "gn:population":0,
    "gn:timezone":"Asia/Bishkek",
    "iso:country":"KG",
    "name:kir_x_preferred":[
        "\u041a\u0435\u043d\u0435\u0448"
    ],
    "name:rus_x_preferred":[
        "\u041a\u0435\u043d\u0435\u0448"
    ],
    "wof:name":"Kenesh",
    "wof:placetype":"locality"
},
  "geometry": {"coordinates":[74.95128000000003,42.89921],"type":"Point"}
}