{
  "type": "Feature",
  "properties": {
    "gn:admin1_code":"04",
    "gn:asciiname":"Kyzyl-Jyldyz",
    "gn:country_code":"KG",
    "gn:dem":1630,
    "gn:feature_class":"P",
    "gn:feature_code":"PPL",
    "gn:name":"Kyzyl-Jyldyz",
    "gn:population":0,
    "gn:timezone":"Asia/Bishkek",
    "iso:country":"KG",
    "name:kir_x_preferred":[
        "\u041a\u044b\u0437\u044b\u043b-\u0416\u0438\u043b\u0434\u044b\u0437"
    ],
    "name:rus_x_preferred":[
        "\u041a\u044b\u0437\u044b\u043b\u0434\u0436\u0438\u043b\u0434\u044b\u0437"
    ],
    "name:und_x_variant":[
        "Kyzyldzhildyz"
    ],
    "wof:name":"Kyzyl-Jyldyz",
    "wof:placetype":"locality"
},
  "geometry": {"coordinates":[74.49099,41.91391],"type":"Point"}
}