{
  "type": "Feature",
  "properties": {
    "gn:admin1_code":"03",
    "gn:asciiname":"Aksu",
    "gn:country_code":"KG",
    "gn:dem":704,
    "gn:feature_class":"P",
    "gn:feature_code":"PPL",
    "gn:name":"Aksu",
    "gn:population":0,
    "gn:timezone":"Asia/Bishkek",
    "iso:country":"KG",
    "name:kir_x_preferred":[
        "\u0410\u043a-\u0421\u0443\u0443"
    ],
    "name:rus_x_preferred":[
        "\u0410\u043a\u0441\u0443"
    ],
    "wof:name":"Aksu",
    "wof:placetype":"locality"
},
  "geometry": {"coordinates":[72.25369000000001,41.39914],"type":"Point"}
}