{
  "type": "Feature",
  "properties": {
    "gn:admin1_code":"08",
    "gn:asciiname":"Yatan",
    "gn:country_code":"KG",
    "gn:dem":1216,
    "gn:feature_class":"P",
    "gn:feature_code":"PPL",
    "gn:name":"Yatan",
    "gn:population":0,
    "gn:timezone":"Asia/Bishkek",
    "iso:country":"KG",
    "name:kir_x_preferred":[
        "\u0416\u0430\u0442\u0430\u043d"
    ],
    "name:rus_x_preferred":[
        "\u042f\u0442\u0430\u043d"
    ],
    "wof:name":"Yatan",
    "wof:placetype":"locality"
},
  "geometry": {"coordinates":[72.67608,40.31208],"type":"Point"}
}