{
  "type": "Feature",
  "properties": {
    "gn:admin1_code":"04",
    "gn:asciiname":"Sary-Bulak",
    "gn:country_code":"KG",
    "gn:dem":2272,
    "gn:feature_class":"P",
    "gn:feature_code":"PPL",
    "gn:name":"Sary-Bulak",
    "gn:population":0,
    "gn:timezone":"Asia/Bishkek",
    "iso:country":"KG",
    "name:ceb_x_preferred":[
        "Sary-Bulak"
    ],
    "name:kir_x_preferred":[
        "\u0421\u0430\u0440\u044b-\u0411\u0443\u043b\u0430\u043a"
    ],
    "name:rus_x_preferred":[
        "\u0421\u0430\u0440\u044b\u0431\u0443\u043b\u0430\u043a"
    ],
    "name:swe_x_preferred":[
        "Sary-Bulak"
    ],
    "name:und_x_variant":[
        "Sarybulak"
    ],
    "wof:name":"Sary-Bulak",
    "wof:placetype":"locality"
},
  "geometry": {"coordinates":[75.76179999999999,41.96492],"type":"Point"}
}