{
  "type": "Feature",
  "properties": {
    "gn:admin1_code":"07",
    "gn:asciiname":"Yrdyk",
    "gn:country_code":"KG",
    "gn:dem":1714,
    "gn:feature_class":"P",
    "gn:feature_code":"PPL",
    "gn:name":"Yrdyk",
    "gn:population":0,
    "gn:timezone":"Asia/Bishkek",
    "iso:country":"KG",
    "name:kir_x_preferred":[
        "\u042b\u0440\u0434\u044b\u043a"
    ],
    "name:rus_x_preferred":[
        "\u042b\u0440\u0434\u044b\u043a"
    ],
    "name:und_x_variant":[
        "Irdyk",
        "Dyyshin",
        "Mariinskoye"
    ],
    "wof:name":"Yrdyk",
    "wof:placetype":"locality"
},
  "geometry": {"coordinates":[78.30063,42.45926],"type":"Point"}
}