{
  "type": "Feature",
  "properties": {
    "gn:admin1_code":"07",
    "gn:asciiname":"Otuzul",
    "gn:country_code":"KG",
    "gn:dem":1698,
    "gn:feature_class":"P",
    "gn:feature_code":"PPL",
    "gn:name":"Otuzul",
    "gn:population":0,
    "gn:timezone":"Asia/Bishkek",
    "iso:country":"KG",
    "name:kir_x_preferred":[
        "\u041e\u0442\u0443\u0437-\u0423\u0443\u043b"
    ],
    "name:rus_x_preferred":[
        "\u041e\u0442\u0443\u0437\u0443\u043b"
    ],
    "wof:name":"Otuzul",
    "wof:placetype":"locality"
},
  "geometry": {"coordinates":[78.47544000000001,42.54344],"type":"Point"}
}