{
  "type": "Feature",
  "properties": {
    "gn:admin1_code":"09",
    "gn:asciiname":"Shuran",
    "gn:country_code":"KG",
    "gn:dem":1122,
    "gn:feature_class":"P",
    "gn:feature_code":"PPL",
    "gn:name":"Shuran",
    "gn:population":0,
    "gn:timezone":"Asia/Bishkek",
    "iso:country":"KG",
    "name:kir_x_preferred":[
        "\u0428\u0443\u0440\u0430\u043d"
    ],
    "name:rus_x_preferred":[
        "\u0428\u0443\u0440\u0430\u043d"
    ],
    "name:uzb_x_preferred":[
        "Sho\u2018ron"
    ],
    "wof:name":"Shuran",
    "wof:placetype":"locality"
},
  "geometry": {"coordinates":[71.45050999999999,40.15958],"type":"Point"}
}