{
  "type": "Feature",
  "properties": {
    "gn:admin1_code":"02",
    "gn:asciiname":"Iyri-Suu",
    "gn:country_code":"KG",
    "gn:dem":678,
    "gn:feature_class":"P",
    "gn:feature_code":"PPL",
    "gn:name":"Iyri-Suu",
    "gn:population":0,
    "gn:timezone":"Asia/Bishkek",
    "iso:country":"KG",
    "name:kir_x_preferred":[
        "\u0418\u0439\u0440\u0438-\u0421\u0443\u0443"
    ],
    "name:rus_x_preferred":[
        "\u0418\u0439\u0440\u0438-\u0421\u0443\u0443"
    ],
    "wof:name":"Iyri-Suu",
    "wof:placetype":"locality"
},
  "geometry": {"coordinates":[73.84633000000002,42.90828],"type":"Point"}
}