{
  "type": "Feature",
  "properties": {
    "gn:admin1_code":"08",
    "gn:asciiname":"Miyazdy",
    "gn:country_code":"KG",
    "gn:dem":1873,
    "gn:feature_class":"P",
    "gn:feature_code":"PPL",
    "gn:name":"Miyazdy",
    "gn:population":0,
    "gn:timezone":"Asia/Bishkek",
    "iso:country":"KG",
    "name:kir_x_preferred":[
        "\u041c\u0438\u044f\u0437\u0434\u044b"
    ],
    "name:rus_x_preferred":[
        "\u041c\u0438\u044f\u0437\u0434\u044b"
    ],
    "wof:name":"Miyazdy",
    "wof:placetype":"locality"
},
  "geometry": {"coordinates":[73.60396,40.32247],"type":"Point"}
}