{
  "type": "Feature",
  "properties": {
    "gn:admin1_code":"03",
    "gn:asciiname":"Koy-Tash",
    "gn:country_code":"KG",
    "gn:dem":944,
    "gn:feature_class":"P",
    "gn:feature_code":"PPL",
    "gn:name":"Koy-Tash",
    "gn:population":0,
    "gn:timezone":"Asia/Bishkek",
    "iso:country":"KG",
    "name:ceb_x_preferred":[
        "Koy-Tash"
    ],
    "name:kir_x_preferred":[
        "\u041a\u043e\u0439-\u0422\u0430\u0448"
    ],
    "name:rus_x_preferred":[
        "\u041a\u043e\u0439-\u0422\u0430\u0448"
    ],
    "name:swe_x_preferred":[
        "Koy-Tash"
    ],
    "name:und_x_variant":[
        "Uchkurt"
    ],
    "name:uzb_x_preferred":[
        "Qo\u02bby-Tosh"
    ],
    "wof:name":"Koy-Tash",
    "wof:placetype":"locality"
},
  "geometry": {"coordinates":[72.10831999999998,41.57678],"type":"Point"}
}