{
  "type": "Feature",
  "properties": {
    "gn:admin1_code":"08",
    "gn:asciiname":"El'chibek",
    "gn:country_code":"KG",
    "gn:dem":1554,
    "gn:feature_class":"P",
    "gn:feature_code":"PPL",
    "gn:name":"El\u2019chibek",
    "gn:population":0,
    "gn:timezone":"Asia/Bishkek",
    "iso:country":"KG",
    "name:kir_x_preferred":[
        "\u042d\u043b\u044c\u0447\u0438\u0431\u0435\u043a"
    ],
    "name:rus_x_preferred":[
        "El\u2019chibek"
    ],
    "name:rus_x_variant":[
        "\u042d\u043b\u044c\u0447\u0438\u0431\u0435\u043a"
    ],
    "wof:name":"El'chibek",
    "wof:placetype":"locality"
},
  "geometry": {"coordinates":[73.24628,40.49413],"type":"Point"}
}