{
  "type": "Feature",
  "properties": {
    "gn:admin1_code":"08",
    "gn:asciiname":"Teleyken",
    "gn:country_code":"KG",
    "gn:dem":1122,
    "gn:feature_class":"P",
    "gn:feature_code":"PPL",
    "gn:name":"T\u00ebl\u00ebyken",
    "gn:population":0,
    "gn:timezone":"Asia/Bishkek",
    "iso:country":"KG",
    "name:kir_x_preferred":[
        "\u0422\u0443\u043b\u0435\u0439\u043a\u0435\u043d"
    ],
    "name:rus_x_preferred":[
        "T\u00ebl\u00ebyken"
    ],
    "name:rus_x_variant":[
        "\u0422\u0451\u043b\u0451\u0439\u043a\u0435\u043d"
    ],
    "name:und_x_variant":[
        "T\u00ebl\u00ebyken",
        "Tuleyken",
        "T\u00f6l\u00f6yk\u00f6n"
    ],
    "wof:name":"Teleyken",
    "wof:placetype":"locality"
},
  "geometry": {"coordinates":[72.80875,40.48674000000001],"type":"Point"}
}