{
  "type": "Feature",
  "properties": {
    "gn:admin1_code":"03",
    "gn:asciiname":"Kashka-Terek",
    "gn:country_code":"KG",
    "gn:dem":1113,
    "gn:feature_class":"P",
    "gn:feature_code":"PPL",
    "gn:name":"Kashka-Terek",
    "gn:population":0,
    "gn:timezone":"Asia/Bishkek",
    "iso:country":"KG",
    "name:kir_x_preferred":[
        "\u041a\u0430\u0448\u043a\u0430-\u0422\u0435\u0440\u0435\u043a"
    ],
    "name:rus_x_preferred":[
        "\u041a\u0430\u0448\u043a\u0430-\u0422\u0435\u0440\u0435\u043a"
    ],
    "wof:name":"Kashka-Terek",
    "wof:placetype":"locality"
},
  "geometry": {"coordinates":[73.14183,41.14233],"type":"Point"}
}