{
  "type": "Feature",
  "properties": {
    "gn:admin1_code":"02",
    "gn:asciiname":"Dzhany-Chek",
    "gn:country_code":"KG",
    "gn:dem":863,
    "gn:feature_class":"P",
    "gn:feature_code":"PPL",
    "gn:name":"Dzhany-Chek",
    "gn:population":0,
    "gn:timezone":"Asia/Bishkek",
    "iso:country":"KG",
    "name:kir_x_preferred":[
        "\u0416\u0430\u04a3\u044b-\u0427\u0435\u043a"
    ],
    "name:rus_x_preferred":[
        "\u0414\u0436\u0430\u043d\u044b-\u0427\u0435\u043a"
    ],
    "name:und_x_variant":[
        "Dzhenychek",
        "Dzhany-Chek"
    ],
    "wof:name":"Dzhany-Chek",
    "wof:placetype":"locality"
},
  "geometry": {"coordinates":[75.35428,42.81247000000001],"type":"Point"}
}