{
  "type": "Feature",
  "properties": {
    "gn:admin1_code":"03",
    "gn:asciiname":"Chet-Bulak",
    "gn:country_code":"KG",
    "gn:dem":1706,
    "gn:feature_class":"P",
    "gn:feature_code":"PPL",
    "gn:name":"Chet-Bulak",
    "gn:population":0,
    "gn:timezone":"Asia/Bishkek",
    "iso:country":"KG",
    "name:kir_x_preferred":[
        "\u0427\u0435\u0442-\u0411\u0443\u043b\u0430\u043a"
    ],
    "name:rus_x_preferred":[
        "\u0427\u0435\u0442-\u0411\u0443\u043b\u0430\u043a"
    ],
    "wof:name":"Chet-Bulak",
    "wof:placetype":"locality"
},
  "geometry": {"coordinates":[73.96453000000002,41.28845],"type":"Point"}
}