{
  "type": "Feature",
  "properties": {
    "gn:admin1_code":"08",
    "gn:asciiname":"Shamal-Terek",
    "gn:country_code":"KG",
    "gn:dem":1285,
    "gn:feature_class":"P",
    "gn:feature_code":"PPL",
    "gn:name":"Shamal-Terek",
    "gn:population":0,
    "gn:timezone":"Asia/Bishkek",
    "iso:country":"KG",
    "name:kir_x_preferred":[
        "\u0428\u0430\u043c\u0430\u043b-\u0422\u0435\u0440\u0435\u043a"
    ],
    "name:rus_x_preferred":[
        "\u0428\u0430\u043c\u0430\u043b-\u0422\u0435\u0440\u0435\u043a"
    ],
    "wof:name":"Shamal-Terek",
    "wof:placetype":"locality"
},
  "geometry": {"coordinates":[73.57611999999997,40.79444],"type":"Point"}
}