{
  "type": "Feature",
  "properties": {
    "gn:admin1_code":"02",
    "gn:asciiname":"Kirovskoye",
    "gn:country_code":"KG",
    "gn:dem":692,
    "gn:feature_class":"P",
    "gn:feature_code":"PPL",
    "gn:name":"Kirovskoye",
    "gn:population":0,
    "gn:timezone":"Asia/Bishkek",
    "iso:country":"KG",
    "name:kir_x_preferred":[
        "\u041a\u0438\u0440\u043e\u0432\u0441\u043a\u043e\u0435"
    ],
    "name:rus_x_preferred":[
        "\u041a\u0438\u0440\u043e\u0432\u0441\u043a\u043e\u0435"
    ],
    "wof:name":"Kirovskoye",
    "wof:placetype":"locality"
},
  "geometry": {"coordinates":[74.85554999999999,42.9411],"type":"Point"}
}