{
  "type": "Feature",
  "properties": {
    "gn:admin1_code":"07",
    "gn:asciiname":"Kara-Talaa",
    "gn:country_code":"KG",
    "gn:dem":1667,
    "gn:feature_class":"P",
    "gn:feature_code":"PPL",
    "gn:name":"Kara-Talaa",
    "gn:population":0,
    "gn:timezone":"Asia/Bishkek",
    "iso:country":"KG",
    "name:kir_x_preferred":[
        "\u041a\u0430\u0440\u0430-\u0422\u0430\u043b\u0430\u0430"
    ],
    "name:rus_x_preferred":[
        "\u041a\u0430\u0440\u0430-\u0422\u0430\u043b\u0430\u0430"
    ],
    "name:und_x_variant":[
        "Sovkhoz Ulakhol"
    ],
    "wof:name":"Kara-Talaa",
    "wof:placetype":"locality"
},
  "geometry": {"coordinates":[76.40526,42.31748],"type":"Point"}
}