{
  "type": "Feature",
  "properties": {
    "gn:admin1_code":"09",
    "gn:asciiname":"Baymaala",
    "gn:country_code":"KG",
    "gn:dem":795,
    "gn:feature_class":"P",
    "gn:feature_code":"PPL",
    "gn:name":"Baymaala",
    "gn:population":0,
    "gn:timezone":"Asia/Bishkek",
    "iso:country":"KG",
    "name:kir_x_preferred":[
        "Baimaala"
    ],
    "name:rus_x_preferred":[
        "\u0411\u0430\u0439\u043c\u0430\u0430\u043b\u0430"
    ],
    "name:uzb_x_preferred":[
        "Boymaola"
    ],
    "wof:name":"Baymaala",
    "wof:placetype":"locality"
},
  "geometry": {"coordinates":[71.62613,40.20049],"type":"Point"}
}