{
  "type": "Feature",
  "properties": {
    "gn:admin1_code":"09",
    "gn:asciiname":"Beles",
    "gn:country_code":"KG",
    "gn:dem":1135,
    "gn:feature_class":"P",
    "gn:feature_code":"PPL",
    "gn:name":"Beles",
    "gn:population":0,
    "gn:timezone":"Asia/Bishkek",
    "iso:country":"KG",
    "name:kir_x_preferred":[
        "\u0411\u0435\u043b\u0435\u0441"
    ],
    "name:rus_x_preferred":[
        "\u0411\u0435\u043b\u0435\u0441"
    ],
    "wof:name":"Beles",
    "wof:placetype":"locality"
},
  "geometry": {"coordinates":[69.85380000000001,39.87377],"type":"Point"}
}