{
  "type": "Feature",
  "properties": {
    "gn:admin1_code":"07",
    "gn:asciiname":"Uch-Koshkon",
    "gn:country_code":"KG",
    "gn:dem":2943,
    "gn:feature_class":"P",
    "gn:feature_code":"PPL",
    "gn:name":"\u00dcch-Koshkon",
    "gn:population":0,
    "gn:timezone":"Asia/Bishkek",
    "iso:country":"KG",
    "name:kir_x_preferred":[
        "\u04ae\u0447-\u041a\u043e\u0448\u043a\u043e\u043d"
    ],
    "name:und_x_variant":[
        "\u00dcch-Koshkon"
    ],
    "wof:name":"Uch-Koshkon",
    "wof:placetype":"locality"
},
  "geometry": {"coordinates":[78.70480999999999,41.82473],"type":"Point"}
}