{
  "type": "Feature",
  "properties": {
    "gn:admin1_code":"07",
    "gn:asciiname":"Echkili-Tash",
    "gn:country_code":"KG",
    "gn:dem":2903,
    "gn:feature_class":"P",
    "gn:feature_code":"PPL",
    "gn:name":"Echkili-Tash",
    "gn:population":0,
    "gn:timezone":"Asia/Bishkek",
    "iso:country":"KG",
    "name:kir_x_preferred":[
        "\u042d\u0447\u043a\u0438\u043b\u0438-\u0422\u0430\u0448"
    ],
    "name:rus_x_preferred":[
        "Kul\u2019ttsentr Echkilitash"
    ],
    "name:rus_x_variant":[
        "\u041a\u0443\u043b\u044c\u0442\u0446\u0435\u043d\u0442\u0440 \u042d\u0447\u043a\u0438\u043b\u0438\u0442\u0430\u0448"
    ],
    "wof:name":"Echkili-Tash",
    "wof:placetype":"locality"
},
  "geometry": {"coordinates":[79.31604,42.33545],"type":"Point"}
}