{
  "type": "Feature",
  "properties": {
    "gn:admin1_code":"07",
    "gn:asciiname":"Ming Bulak",
    "gn:country_code":"KG",
    "gn:dem":1648,
    "gn:feature_class":"P",
    "gn:feature_code":"PPL",
    "gn:name":"Ming Bulak",
    "gn:population":0,
    "gn:timezone":"Asia/Bishkek",
    "iso:country":"KG",
    "name:kir_x_preferred":[
        "Ming Bulak"
    ],
    "name:rus_x_preferred":[
        "\u041c\u0438\u043d\u0431\u0443\u043b\u0430\u043a"
    ],
    "name:und_x_variant":[
        "Minbulak"
    ],
    "wof:name":"Ming Bulak",
    "wof:placetype":"locality"
},
  "geometry": {"coordinates":[78.51430000000001,42.72816],"type":"Point"}
}