{
  "type": "Feature",
  "properties": {
    "gn:admin1_code":"02",
    "gn:asciiname":"Kyz-Molo",
    "gn:country_code":"KG",
    "gn:dem":601,
    "gn:feature_class":"P",
    "gn:feature_code":"PPL",
    "gn:name":"Kyz-Molo",
    "gn:population":0,
    "gn:timezone":"Asia/Bishkek",
    "iso:country":"KG",
    "name:kir_x_preferred":[
        "Kyz-Molo"
    ],
    "name:rus_x_preferred":[
        "\u041a\u044b\u0437-\u041c\u043e\u043b\u043e"
    ],
    "wof:name":"Kyz-Molo",
    "wof:placetype":"locality"
},
  "geometry": {"coordinates":[74.07597,43.0372],"type":"Point"}
}