{
  "type": "Feature",
  "properties": {
    "gn:admin1_code":"08",
    "gn:asciiname":"Kara-Tebe",
    "gn:country_code":"KG",
    "gn:dem":1442,
    "gn:feature_class":"P",
    "gn:feature_code":"PPL",
    "gn:name":"Kara-Tebe",
    "gn:population":0,
    "gn:timezone":"Asia/Bishkek",
    "iso:country":"KG",
    "name:rus_x_preferred":[
        "\u041a\u0430\u0440\u0430-\u0422\u0435\u0431\u0435"
    ],
    "wof:name":"Kara-Tebe",
    "wof:placetype":"locality"
},
  "geometry": {"coordinates":[73.27923,40.4513],"type":"Point"}
}