{
  "type": "Feature",
  "properties": {
    "gn:admin1_code":"08",
    "gn:asciiname":"Nayman",
    "gn:country_code":"KG",
    "gn:dem":635,
    "gn:feature_class":"P",
    "gn:feature_code":"PPL",
    "gn:name":"Nayman",
    "gn:population":0,
    "gn:timezone":"Asia/Bishkek",
    "iso:country":"KG",
    "name:kir_x_preferred":[
        "\u041d\u0430\u0439\u043c\u0430\u043d"
    ],
    "name:rus_x_preferred":[
        "\u041d\u0430\u0439\u043c\u0430\u043d"
    ],
    "wof:name":"Nayman",
    "wof:placetype":"locality"
},
  "geometry": {"coordinates":[72.18089000000001,40.45881],"type":"Point"}
}