{
  "type": "Feature",
  "properties": {
    "iso:country":"KG",
    "name:ckb_x_preferred":[
        "\u0642\u0627\u0631\u0627-\u0633\u0648"
    ],
    "name:ckb_x_variant":[
        "\u0642\u0627\u0631\u0627\u0633\u0648"
    ],
    "name:deu_x_preferred":[
        "Karasuu"
    ],
    "name:eng_x_preferred":[
        "Kara-Suu"
    ],
    "name:est_x_preferred":[
        "Karasuu"
    ],
    "name:fas_x_preferred":[
        "\u0642\u0627\u0631\u0627\u0633\u0648\u060c \u0642\u0631\u0642\u06cc\u0632\u0633\u062a\u0627\u0646"
    ],
    "name:fas_x_variant":[
        "\u0642\u0627\u0631\u0627\u0633\u0648"
    ],
    "name:fra_x_preferred":[
        "Kara-Suu"
    ],
    "name:hsb_x_preferred":[
        "Kara-Suu"
    ],
    "name:ita_x_preferred":[
        "Kara-Suu"
    ],
    "name:jpn_x_preferred":[
        "\u30ab\u30e9\u30b9\u30a6"
    ],
    "name:kir_x_preferred":[
        "\u041a\u0430\u0440\u0430-\u0421\u0443\u0443 \u0448\u0430\u0430\u0440\u044b"
    ],
    "name:kir_x_variant":[
        "Kara-Suu"
    ],
    "name:lit_x_preferred":[
        "Kara Su"
    ],
    "name:nld_x_preferred":[
        "Kara-Suu"
    ],
    "name:pol_x_preferred":[
        "Karasuu"
    ],
    "name:rup_x_preferred":[
        "Kara-Suu"
    ],
    "name:rus_x_preferred":[
        "\u041a\u0430\u0440\u0430-\u0421\u0443\u0443"
    ],
    "name:rus_x_variant":[
        "\u041a\u0430\u0440\u0430 \u0421\u0443\u0443"
    ],
    "name:sco_x_preferred":[
        "Kara-Suu"
    ],
    "name:spa_x_preferred":[
        "Kara-Suu"
    ],
    "name:swe_x_preferred":[
        "Kara Suu"
    ],
    "name:tat_x_preferred":[
        "\u041a\u0430\u0440\u0430\u0441\u0443"
    ],
    "name:tur_x_preferred":[
        "Kara-Su"
    ],
    "name:unk_x_variant":[
        "Kara Suu"
    ],
    "name:uzb_x_preferred":[
        "Qorasuv"
    ],
    "name:uzb_x_variant":[
        "Qora-Suu"
    ],
    "name:zho_x_preferred":[
        "\u5361\u62c9\u8607"
    ],
    "qs:gn_country":"KG",
    "qs:gn_fcode":"PPL",
    "qs:gn_pop":17800,
    "qs:name":"Kara-Su",
    "qs:name_adm0":"Kyrgyzstan",
    "qs:name_adm1":"Osh",
    "qs:photos":0,
    "qs:photos_1k":0,
    "qs:photos_9k":1,
    "qs:photos_9r":1,
    "qs:photos_all":3,
    "qs:photos_sr":0,
    "qs:placetype":"Town",
    "qs:pop_sr":"6",
    "qs:woe_adm0":23424864,
    "wd:wordcount":281,
    "wof:name":"Kara-Su",
    "wof:placetype":"locality",
    "wof:population":17800
},
  "geometry": {"coordinates":[72.86666,40.7046],"type":"Point"}
}