{
  "type": "Feature",
  "properties": {
    "gn:admin1_code":"09",
    "gn:asciiname":"Kotur-Bulak",
    "gn:country_code":"KG",
    "gn:dem":1054,
    "gn:feature_class":"P",
    "gn:feature_code":"PPL",
    "gn:name":"Kotur-Bulak",
    "gn:population":0,
    "gn:timezone":"Asia/Bishkek",
    "iso:country":"KG",
    "name:rus_x_preferred":[
        "\u041a\u043e\u0442\u0443\u0440-\u0411\u0443\u043b\u0430\u043a"
    ],
    "name:uzb_x_preferred":[
        "Qo\u2018tur-Buloq"
    ],
    "wof:name":"Kotur-Bulak",
    "wof:placetype":"locality"
},
  "geometry": {"coordinates":[71.94110999999999,40.17539],"type":"Point"}
}