{
  "type": "Feature",
  "properties": {
    "gn:admin1_code":"04",
    "gn:asciiname":"Bas-Kiya",
    "gn:country_code":"KG",
    "gn:dem":2030,
    "gn:feature_class":"P",
    "gn:feature_code":"PPL",
    "gn:name":"Bas-Kiya",
    "gn:population":0,
    "gn:timezone":"Asia/Bishkek",
    "iso:country":"KG",
    "name:kir_x_preferred":[
        "\u0411\u0430\u0441-\u041a\u0438\u044f"
    ],
    "name:rus_x_preferred":[
        "\u0411\u0430\u0441-\u041a\u0438\u044f"
    ],
    "name:und_x_variant":[
        "Baskyya"
    ],
    "wof:name":"Bas-Kiya",
    "wof:placetype":"locality"
},
  "geometry": {"coordinates":[75.79708000000002,41.50894],"type":"Point"}
}