{
  "type": "Feature",
  "properties": {
    "gn:admin1_code":"08",
    "gn:asciiname":"Almaly",
    "gn:country_code":"KG",
    "gn:dem":2102,
    "gn:feature_class":"P",
    "gn:feature_code":"PPL",
    "gn:name":"Almaly",
    "gn:population":0,
    "gn:timezone":"Asia/Bishkek",
    "iso:country":"KG",
    "name:ceb_x_preferred":[
        "Almaly"
    ],
    "name:kir_x_preferred":[
        "\u0410\u043b\u043c\u0430\u043b\u044b"
    ],
    "name:rus_x_preferred":[
        "\u0410\u043b\u043c\u0430\u043b\u044b"
    ],
    "name:swe_x_preferred":[
        "Almaly"
    ],
    "wof:name":"Almaly",
    "wof:placetype":"locality"
},
  "geometry": {"coordinates":[73.59931,40.24331],"type":"Point"}
}