{
  "type": "Feature",
  "properties": {
    "gn:admin1_code":"02",
    "gn:asciiname":"Alamedin",
    "gn:country_code":"KG",
    "gn:dem":708,
    "gn:feature_class":"P",
    "gn:feature_code":"PPL",
    "gn:name":"Alamedin",
    "gn:population":0,
    "gn:timezone":"Asia/Bishkek",
    "iso:country":"KG",
    "name:rus_x_preferred":[
        "\u0410\u043b\u0430\u043c\u0435\u0434\u0438\u043d"
    ],
    "name:und_x_variant":[
        "Alam\u00fcd\u00fcn",
        "Voroshilovskoye"
    ],
    "wof:name":"Alamedin",
    "wof:placetype":"locality"
},
  "geometry": {"coordinates":[74.63651,42.90646],"type":"Point"}
}