{
  "type": "Feature",
  "properties": {
    "gn:admin1_code":"03",
    "gn:asciiname":"Zimov'ye Sary-Kamysh",
    "gn:country_code":"KG",
    "gn:dem":1860,
    "gn:feature_class":"P",
    "gn:feature_code":"PPL",
    "gn:name":"Zimov\u2019ye Sary-Kamysh",
    "gn:population":0,
    "gn:timezone":"Asia/Bishkek",
    "iso:country":"KG",
    "name:eng_x_preferred":[
        "Sar-Qamish Qishloq"
    ],
    "name:kir_x_preferred":[
        "\u0421\u0430\u0440\u044b-\u041a\u0430\u043c\u044b\u0448"
    ],
    "name:rus_x_preferred":[
        "Zimov\u2019ye Sary-Kamysh"
    ],
    "name:rus_x_variant":[
        "\u0417\u0438\u043c\u043e\u0432\u044c\u0435 \u0421\u0430\u0440\u044b-\u041a\u0430\u043c\u044b\u0448"
    ],
    "name:und_x_variant":[
        "Zimov\u2019ye Sary-Kamysh"
    ],
    "wof:name":"Zimov'ye Sary-Kamysh",
    "wof:placetype":"locality"
},
  "geometry": {"coordinates":[71.24253,41.48757],"type":"Point"}
}