{
  "type": "Feature",
  "properties": {
    "gn:admin1_code":"07",
    "gn:asciiname":"Ashkhabak",
    "gn:country_code":"KG",
    "gn:dem":1878,
    "gn:feature_class":"P",
    "gn:feature_code":"PPL",
    "gn:name":"Ashkhabak",
    "gn:population":0,
    "gn:timezone":"Asia/Bishkek",
    "iso:country":"KG",
    "name:kir_x_preferred":[
        "\u0410\u0448\u0445\u0430\u0431\u0430\u043a"
    ],
    "name:rus_x_preferred":[
        "\u0410\u0448\u0445\u0430\u0431\u0430\u043a"
    ],
    "wof:name":"Ashkhabak",
    "wof:placetype":"locality"
},
  "geometry": {"coordinates":[77.16938,42.6897],"type":"Point"}
}