{
  "type": "Feature",
  "properties": {
    "gn:admin1_code":"04",
    "gn:asciiname":"Bagysh",
    "gn:country_code":"KG",
    "gn:dem":1962,
    "gn:feature_class":"P",
    "gn:feature_code":"PPL",
    "gn:name":"Bagysh",
    "gn:population":0,
    "gn:timezone":"Asia/Bishkek",
    "iso:country":"KG",
    "name:kir_x_preferred":[
        "\u0411\u0430\u0433\u04e9\u0448"
    ],
    "name:rus_x_preferred":[
        "\u0411\u0430\u0433\u044b\u0448"
    ],
    "name:und_x_variant":[
        "Bag\u00f6sh",
        "Bagysh",
        "Kuyruchuk"
    ],
    "wof:name":"Bagysh",
    "wof:placetype":"locality"
},
  "geometry": {"coordinates":[74.82581999999999,41.98131],"type":"Point"}
}