{
  "type": "Feature",
  "properties": {
    "gn:admin1_code":"08",
    "gn:asciiname":"Kichi-Dzhaz",
    "gn:country_code":"KG",
    "gn:dem":1539,
    "gn:feature_class":"P",
    "gn:feature_code":"PPL",
    "gn:name":"Kichi-Dzhaz",
    "gn:population":0,
    "gn:timezone":"Asia/Bishkek",
    "iso:country":"KG",
    "name:kir_x_preferred":[
        "\u041a\u0438\u0447\u0438-\u0416\u0430\u0437"
    ],
    "name:rus_x_preferred":[
        "\u041a\u0438\u0447\u0438-\u0414\u0436\u0430\u0437"
    ],
    "name:und_x_variant":[
        "Dzhas"
    ],
    "wof:name":"Kichi-Dzhaz",
    "wof:placetype":"locality"
},
  "geometry": {"coordinates":[72.45509,40.25309],"type":"Point"}
}