{
  "type": "Feature",
  "properties": {
    "gn:admin1_code":"09",
    "gn:asciiname":"Churbek",
    "gn:country_code":"KG",
    "gn:dem":1159,
    "gn:feature_class":"P",
    "gn:feature_code":"PPL",
    "gn:name":"Churbek",
    "gn:population":0,
    "gn:timezone":"Asia/Bishkek",
    "iso:country":"KG",
    "name:kir_x_preferred":[
        "\u0427\u0443\u0440\u0431\u0435\u043a"
    ],
    "name:rus_x_preferred":[
        "\u0414\u0436\u0430\u043d\u044b-\u0414\u0436\u043e\u043b"
    ],
    "name:und_x_variant":[
        "Dzhany-Dzhol"
    ],
    "wof:name":"Churbek",
    "wof:placetype":"locality"
},
  "geometry": {"coordinates":[69.90666999999999,39.97811],"type":"Point"}
}