{
  "type": "Feature",
  "properties": {
    "gn:admin1_code":"02",
    "gn:asciiname":"Almaluu",
    "gn:country_code":"KG",
    "gn:dem":1503,
    "gn:feature_class":"P",
    "gn:feature_code":"PPL",
    "gn:name":"Almaluu",
    "gn:population":0,
    "gn:timezone":"Asia/Bishkek",
    "iso:country":"KG",
    "name:kir_x_preferred":[
        "\u0410\u043b\u043c\u0430\u043b\u0443\u0443"
    ],
    "name:rus_x_preferred":[
        "\u0410\u043b\u043c\u0430\u043b\u0443\u0443"
    ],
    "wof:name":"Almaluu",
    "wof:placetype":"locality"
},
  "geometry": {"coordinates":[74.84451999999997,42.68747000000001],"type":"Point"}
}