{
  "type": "Feature",
  "properties": {
    "gn:admin1_code":"08",
    "gn:asciiname":"Karanay",
    "gn:country_code":"KG",
    "gn:dem":1265,
    "gn:feature_class":"P",
    "gn:feature_code":"PPL",
    "gn:name":"Karanay",
    "gn:population":0,
    "gn:timezone":"Asia/Bishkek",
    "iso:country":"KG",
    "name:kir_x_preferred":[
        "\u041a\u0430\u0440\u0430\u043d\u0430\u0439"
    ],
    "name:rus_x_preferred":[
        "\u041a\u0430\u0440\u0430\u043d\u0430\u0439"
    ],
    "name:uzb_x_preferred":[
        "Qoranay"
    ],
    "wof:name":"Karanay",
    "wof:placetype":"locality"
},
  "geometry": {"coordinates":[72.38674,40.30442],"type":"Point"}
}