{
  "type": "Feature",
  "properties": {
    "gn:admin1_code":"10",
    "gn:asciiname":"Dyykan-Kyshtak",
    "gn:country_code":"KG",
    "gn:dem":1031,
    "gn:feature_class":"P",
    "gn:feature_code":"PPL",
    "gn:name":"Dyykan-Kyshtak",
    "gn:population":0,
    "gn:timezone":"Asia/Bishkek",
    "iso:country":"KG",
    "name:kir_x_preferred":[
        "\u0414\u044b\u0439\u043a\u0430\u043d-\u041a\u044b\u0448\u0442\u0430\u043a"
    ],
    "name:rus_x_preferred":[
        "\u0414\u044b\u0439\u043a\u0430\u043d-\u041a\u044b\u0448\u0442\u0430\u043a"
    ],
    "name:uzb_x_preferred":[
        "Diykan-Qishtak"
    ],
    "wof:name":"Dyykan-Kyshtak",
    "wof:placetype":"locality"
},
  "geometry": {"coordinates":[72.78686999999999,40.51598],"type":"Point"}
}