{
  "type": "Feature",
  "properties": {
    "gn:admin1_code":"04",
    "gn:asciiname":"Dzhuanaryk",
    "gn:country_code":"KG",
    "gn:dem":1856,
    "gn:feature_class":"P",
    "gn:feature_code":"PPL",
    "gn:name":"Dzhuanaryk",
    "gn:population":0,
    "gn:timezone":"Asia/Bishkek",
    "iso:country":"KG",
    "name:kir_x_preferred":[
        "\u0416\u04af\u043d-\u0410\u0440\u044b\u043a"
    ],
    "name:rus_x_preferred":[
        "\u0414\u0436\u0443\u0430\u043d\u0430\u0440\u044b\u043a"
    ],
    "wof:name":"Dzhuanaryk",
    "wof:placetype":"locality"
},
  "geometry": {"coordinates":[75.66325000000001,42.18473],"type":"Point"}
}