{
  "type": "Feature",
  "properties": {
    "gn:admin1_code":"08",
    "gn:asciiname":"Chaty",
    "gn:country_code":"KG",
    "gn:dem":2259,
    "gn:feature_class":"P",
    "gn:feature_code":"PPL",
    "gn:name":"Chaty",
    "gn:population":0,
    "gn:timezone":"Asia/Bishkek",
    "iso:country":"KG",
    "name:rus_x_preferred":[
        "\u0427\u0430\u0442\u044b"
    ],
    "wof:name":"Chaty",
    "wof:placetype":"locality"
},
  "geometry": {"coordinates":[72.93959,39.93831],"type":"Point"}
}