{
  "type": "Feature",
  "properties": {
    "gn:admin1_code":"07",
    "gn:asciiname":"Kara-Koo",
    "gn:country_code":"KG",
    "gn:dem":1726,
    "gn:feature_class":"P",
    "gn:feature_code":"PPL",
    "gn:name":"Kara-Koo",
    "gn:population":0,
    "gn:timezone":"Asia/Bishkek",
    "iso:country":"KG",
    "name:kir_x_preferred":[
        "\u041a\u0430\u0440\u0430-\u041a\u043e\u043e"
    ],
    "name:rus_x_preferred":[
        "\u041a\u0430\u0440\u0430-\u0422\u043e\u043e"
    ],
    "name:und_x_variant":[
        "Karako",
        "Kara-Koo",
        "Kara-Too"
    ],
    "wof:name":"Kara-Koo",
    "wof:placetype":"locality"
},
  "geometry": {"coordinates":[76.6296,42.21353],"type":"Point"}
}