{
  "type": "Feature",
  "properties": {
    "gn:admin1_code":"02",
    "gn:asciiname":"Birdik",
    "gn:country_code":"KG",
    "gn:dem":686,
    "gn:feature_class":"P",
    "gn:feature_code":"PPL",
    "gn:name":"Birdik",
    "gn:population":0,
    "gn:timezone":"Asia/Bishkek",
    "iso:country":"KG",
    "name:kir_x_preferred":[
        "\u0411\u0438\u0440\u0434\u0438\u043a"
    ],
    "name:rus_x_preferred":[
        "\u0411\u0438\u0440\u0434\u0438\u043a"
    ],
    "wof:name":"Birdik",
    "wof:placetype":"locality"
},
  "geometry": {"coordinates":[74.90289,42.95739],"type":"Point"}
}