{
  "type": "Feature",
  "properties": {
    "gn:admin1_code":"08",
    "gn:asciiname":"Kommunizm",
    "gn:country_code":"KG",
    "gn:dem":1252,
    "gn:feature_class":"P",
    "gn:feature_code":"PPL",
    "gn:name":"Kommunizm",
    "gn:population":0,
    "gn:timezone":"Asia/Bishkek",
    "iso:country":"KG",
    "name:kir_x_preferred":[
        "\u041a\u043e\u043c\u043c\u0443\u043d\u0438\u0437\u043c"
    ],
    "name:rus_x_preferred":[
        "\u041a\u043e\u043c\u043c\u0443\u043d\u0438\u0437\u043c"
    ],
    "wof:name":"Kommunizm",
    "wof:placetype":"locality"
},
  "geometry": {"coordinates":[72.68216,40.30007],"type":"Point"}
}