{
  "type": "Feature",
  "properties": {
    "gn:admin1_code":"08",
    "gn:asciiname":"Kommunizm",
    "gn:country_code":"KG",
    "gn:dem":1252,
    "gn:feature_class":"P",
    "gn:feature_code":"PPL",
    "gn:name":"Kommunizm",
    "gn:population":0,
    "gn:timezone":"Asia/Bishkek",
    "iso:country":"KG",
    "name:fas_x_preferred":[
        "\u06a9\u0645\u0648\u0646\u06cc\u0632\u0645"
    ],
    "name:kir_x_preferred":[
        "\u041a\u043e\u043c\u043c\u0443\u043d\u0438\u0437\u043c"
    ],
    "name:msa_x_preferred":[
        "Kommunizm"
    ],
    "name:rus_x_preferred":[
        "\u041a\u043e\u043c\u043c\u0443\u043d\u0438\u0437\u043c"
    ],
    "name:tgk_x_preferred":[
        "\u0414\u0435\u04b3\u043e\u0442\u0438 \u0417\u0430\u0440\u04b3\u0430\u043b\u043e\u043b"
    ],
    "name:urd_x_preferred":[
        "\u06a9\u0645\u0648\u0646\u06cc\u0632\u0645"
    ],
    "wof:name":"Kommunizm",
    "wof:placetype":"locality"
},
  "geometry": {"coordinates":[72.68216,40.30007],"type":"Point"}
}