{
  "type": "Feature",
  "properties": {
    "gn:admin1_code":"03",
    "gn:asciiname":"Dzhargylchakty",
    "gn:country_code":"KG",
    "gn:dem":1368,
    "gn:feature_class":"P",
    "gn:feature_code":"PPL",
    "gn:name":"Dzhargylchakty",
    "gn:population":0,
    "gn:timezone":"Asia/Bishkek",
    "iso:country":"KG",
    "name:kir_x_preferred":[
        "\u0416\u0430\u0440\u0433\u044b\u043b\u0447\u0430\u043a\u0442\u044b"
    ],
    "name:rus_x_preferred":[
        "\u0414\u0436\u0430\u0440\u0433\u044b\u043b\u0447\u0430\u043a\u0442\u044b"
    ],
    "name:und_x_variant":[
        "Dzhargychak",
        "Beshtash",
        "Dzhargylchakty"
    ],
    "wof:name":"Dzhargylchakty",
    "wof:placetype":"locality"
},
  "geometry": {"coordinates":[72.52789,41.98546],"type":"Point"}
}