{
  "type": "Feature",
  "properties": {
    "gn:admin1_code":"09",
    "gn:asciiname":"Sovetskiy",
    "gn:country_code":"KG",
    "gn:dem":1136,
    "gn:feature_class":"P",
    "gn:feature_code":"PPL",
    "gn:name":"Sovetskiy",
    "gn:population":0,
    "gn:timezone":"Asia/Bishkek",
    "iso:country":"KG",
    "name:kir_x_preferred":[
        "\u0421\u043e\u0432\u0435\u0442\u0441\u043a\u0438\u0439"
    ],
    "name:kir_x_variant":[
        "Sovetskii"
    ],
    "name:rus_x_preferred":[
        "\u0421\u043e\u0432\u0435\u0442\u0441\u043a\u0438\u0439"
    ],
    "name:und_x_variant":[
        "Kan",
        "Sovetskiy",
        "Sovet"
    ],
    "wof:name":"Sovetskiy",
    "wof:placetype":"locality"
},
  "geometry": {"coordinates":[71.31187,40.16661],"type":"Point"}
}