{
  "type": "Feature",
  "properties": {
    "gn:admin1_code":"07",
    "gn:asciiname":"Shaty",
    "gn:country_code":"KG",
    "gn:dem":1761,
    "gn:feature_class":"P",
    "gn:feature_code":"PPL",
    "gn:name":"Shaty",
    "gn:population":0,
    "gn:timezone":"Asia/Bishkek",
    "iso:country":"KG",
    "name:kir_x_preferred":[
        "\u0428\u0430\u0442\u044b"
    ],
    "name:rus_x_preferred":[
        "\u0428\u0430\u0442\u044b"
    ],
    "wof:name":"Shaty",
    "wof:placetype":"locality"
},
  "geometry": {"coordinates":[78.38564000000002,42.786],"type":"Point"}
}