{
  "type": "Feature",
  "properties": {
    "gn:admin1_code":"09",
    "gn:asciiname":"Yangak",
    "gn:country_code":"KG",
    "gn:dem":1286,
    "gn:feature_class":"P",
    "gn:feature_code":"PPL",
    "gn:name":"Yangak",
    "gn:population":0,
    "gn:timezone":"Asia/Bishkek",
    "iso:country":"KG",
    "name:kir_x_preferred":[
        "\u0416\u0430\u04a3\u044b-\u0410\u043a"
    ],
    "name:rus_x_preferred":[
        "\u042f\u043d\u0433\u0430\u043a"
    ],
    "name:und_x_variant":[
        "Kal\u2019tak",
        "Yangak"
    ],
    "name:uzb_x_preferred":[
        "Yong\u2018oq"
    ],
    "wof:name":"Yangak",
    "wof:placetype":"locality"
},
  "geometry": {"coordinates":[71.45038000000002,40.13403],"type":"Point"}
}