{
  "type": "Feature",
  "properties": {
    "gn:admin1_code":"04",
    "gn:asciiname":"Aral",
    "gn:country_code":"KG",
    "gn:dem":2061,
    "gn:feature_class":"P",
    "gn:feature_code":"PPL",
    "gn:name":"Aral",
    "gn:population":0,
    "gn:timezone":"Asia/Bishkek",
    "iso:country":"KG",
    "name:cat_x_preferred":[
        "Aral"
    ],
    "name:ceb_x_preferred":[
        "Aral"
    ],
    "name:ces_x_preferred":[
        "Aral"
    ],
    "name:deu_x_preferred":[
        "Aral"
    ],
    "name:fas_x_preferred":[
        "\u0622\u0631\u0627\u0644"
    ],
    "name:fra_x_preferred":[
        "Aral"
    ],
    "name:glg_x_preferred":[
        "Aral"
    ],
    "name:ita_x_preferred":[
        "Aral"
    ],
    "name:kat_x_preferred":[
        "\u10d0\u10e0\u10d0\u10da\u10d8"
    ],
    "name:kaz_x_preferred":[
        "\u0410\u0440\u0430\u043b"
    ],
    "name:kir_x_preferred":[
        "\u0410\u0440\u0430\u043b"
    ],
    "name:mlg_x_preferred":[
        "Aral"
    ],
    "name:mon_x_preferred":[
        "\u0410\u0440\u0430\u043b"
    ],
    "name:nld_x_preferred":[
        "Aral"
    ],
    "name:nor_x_preferred":[
        "Aral"
    ],
    "name:pol_x_preferred":[
        "Aral"
    ],
    "name:por_x_preferred":[
        "Aral"
    ],
    "name:ron_x_preferred":[
        "Aral"
    ],
    "name:rus_x_preferred":[
        "\u0410\u0440\u0430\u043b"
    ],
    "name:spa_x_preferred":[
        "Aral"
    ],
    "name:swe_x_preferred":[
        "Aral"
    ],
    "name:tur_x_preferred":[
        "Aral"
    ],
    "name:vie_x_preferred":[
        "Aral"
    ],
    "wof:name":"Aral",
    "wof:placetype":"locality"
},
  "geometry": {"coordinates":[74.75621,42.0543],"type":"Point"}
}