{
  "type": "Feature",
  "properties": {
    "gn:admin1_code":"04",
    "gn:asciiname":"Aral",
    "gn:country_code":"KG",
    "gn:dem":2061,
    "gn:feature_class":"P",
    "gn:feature_code":"PPL",
    "gn:name":"Aral",
    "gn:population":0,
    "gn:timezone":"Asia/Bishkek",
    "iso:country":"KG",
    "name:kir_x_preferred":[
        "\u0410\u0440\u0430\u043b"
    ],
    "name:rus_x_preferred":[
        "\u0410\u0440\u0430\u043b"
    ],
    "wof:name":"Aral",
    "wof:placetype":"locality"
},
  "geometry": {"coordinates":[74.75621,42.0543],"type":"Point"}
}