{
  "type": "Feature",
  "properties": {
    "gn:admin1_code":"04",
    "gn:asciiname":"Kosh-Doeboe",
    "gn:country_code":"KG",
    "gn:dem":2175,
    "gn:feature_class":"P",
    "gn:feature_code":"PPL",
    "gn:name":"Kosh-D\u00f6b\u00f6",
    "gn:population":0,
    "gn:timezone":"Asia/Bishkek",
    "iso:country":"KG",
    "name:kir_x_preferred":[
        "\u041a\u043e\u0448-\u0414\u04e9\u0431\u04e9"
    ],
    "name:rus_x_preferred":[
        "\u041a\u043e\u0448-\u0414\u044e\u0431\u0435"
    ],
    "name:und_x_variant":[
        "Kosht\u00ebb\u00eb",
        "Kosh-Dyube"
    ],
    "wof:name":"Kosh-Doeboe",
    "wof:placetype":"locality"
},
  "geometry": {"coordinates":[74.25834,41.08349000000001],"type":"Point"}
}