{
  "type": "Feature",
  "properties": {
    "gn:admin1_code":"08",
    "gn:asciiname":"Kyzyl-Oktyabr'",
    "gn:country_code":"KG",
    "gn:dem":923,
    "gn:feature_class":"P",
    "gn:feature_code":"PPL",
    "gn:name":"Kyzyl-Oktyabr\u2019",
    "gn:population":0,
    "gn:timezone":"Asia/Bishkek",
    "iso:country":"KG",
    "name:kir_x_preferred":[
        "\u041a\u044b\u0437\u044b\u043b-\u041e\u043a\u0442\u044f\u0431\u0440\u044c"
    ],
    "name:rus_x_preferred":[
        "Kyzyl-Oktyabr\u2019"
    ],
    "name:rus_x_variant":[
        "\u041a\u044b\u0437\u044b\u043b-\u041e\u043a\u0442\u044f\u0431\u0440\u044c"
    ],
    "name:und_x_variant":[
        "Kyzyl-Oktyabr\u2019"
    ],
    "name:uzb_x_preferred":[
        "Qizil-Oktyabr"
    ],
    "wof:name":"Kyzyl-Oktyabr'",
    "wof:placetype":"locality"
},
  "geometry": {"coordinates":[73.16240000000001,40.7107],"type":"Point"}
}