{
  "type": "Feature",
  "properties": {
    "gn:admin1_code":"02",
    "gn:asciiname":"Ak-Beket",
    "gn:country_code":"KG",
    "gn:dem":1067,
    "gn:feature_class":"P",
    "gn:feature_code":"PPL",
    "gn:name":"Ak-Beket",
    "gn:population":0,
    "gn:timezone":"Asia/Bishkek",
    "iso:country":"KG",
    "name:kir_x_preferred":[
        "\u0410\u043a-\u0411\u0435\u043a\u0435\u0442"
    ],
    "name:rus_x_preferred":[
        "\u0410\u043a-\u0411\u0435\u043a\u0435\u0442"
    ],
    "name:rus_x_variant":[
        "\u0411\u0435\u043b\u044b\u0439 \u041f\u0438\u043a\u0435\u0442"
    ],
    "name:uzb_x_preferred":[
        "Oqbeket"
    ],
    "wof:name":"Ak-Beket",
    "wof:placetype":"locality"
},
  "geometry": {"coordinates":[75.63273000000002,42.80633],"type":"Point"}
}