{
  "type": "Feature",
  "properties": {
    "gn:admin1_code":"09",
    "gn:asciiname":"Kol'tso",
    "gn:country_code":"KG",
    "gn:dem":999,
    "gn:feature_class":"P",
    "gn:feature_code":"PPL",
    "gn:name":"Kol\u2019tso",
    "gn:population":0,
    "gn:timezone":"Asia/Bishkek",
    "iso:country":"KG",
    "name:kir_x_preferred":[
        "\u041a\u043e\u043b\u044c\u0446\u043e"
    ],
    "name:kir_x_variant":[
        "Koltso"
    ],
    "name:rus_x_preferred":[
        "Kol\u2019tso"
    ],
    "name:rus_x_variant":[
        "\u041a\u043e\u043b\u044c\u0446\u043e"
    ],
    "wof:name":"Kol'tso",
    "wof:placetype":"locality"
},
  "geometry": {"coordinates":[69.55243,39.9783],"type":"Point"}
}