{
  "type": "Feature",
  "properties": {
    "gn:admin1_code":"09",
    "gn:asciiname":"Uch-Korgon",
    "gn:country_code":"KG",
    "gn:dem":971,
    "gn:feature_class":"P",
    "gn:feature_code":"PPLA3",
    "gn:name":"Uch-Korgon",
    "gn:population":0,
    "gn:timezone":"Asia/Bishkek",
    "iso:country":"KG",
    "name:ceb_x_preferred":[
        "Uch-Korgon"
    ],
    "name:fas_x_preferred":[
        "\u0627\u0648\u0686 \u06a9\u0631\u06af\u0646"
    ],
    "name:kir_x_preferred":[
        "\u04ae\u0447-\u041a\u043e\u0440\u0433\u043e\u043d"
    ],
    "name:rus_x_preferred":[
        "\u0423\u0447-\u041a\u043e\u0440\u0433\u043e\u043d"
    ],
    "name:swe_x_preferred":[
        "Uch-Korgon"
    ],
    "name:und_x_variant":[
        "Uch-Kurgan",
        "Molotovabad",
        "Uchkorgon"
    ],
    "name:uzb_x_preferred":[
        "Uch-Qo\u2018rg\u2018on"
    ],
    "name:uzb_x_variant":[
        "Uch-Qo\u02bbrg\u02bbon"
    ],
    "wof:name":"Uch-Korgon",
    "wof:placetype":"locality"
},
  "geometry": {"coordinates":[72.05924,40.22881],"type":"Point"}
}