{
  "type": "Feature",
  "properties": {
    "gn:admin1_code":"07",
    "gn:asciiname":"Alkym",
    "gn:country_code":"KG",
    "gn:dem":1712,
    "gn:feature_class":"P",
    "gn:feature_code":"PPL",
    "gn:name":"Alkym",
    "gn:population":0,
    "gn:timezone":"Asia/Bishkek",
    "iso:country":"KG",
    "name:kir_x_preferred":[
        "\u0410\u043b\u043a\u044b\u043c"
    ],
    "name:rus_x_preferred":[
        "\u0410\u043b\u043a\u044b\u043c"
    ],
    "name:und_x_variant":[
        "Kyzyl-Dyykan"
    ],
    "wof:name":"Alkym",
    "wof:placetype":"locality"
},
  "geometry": {"coordinates":[78.26635999999998,42.46296],"type":"Point"}
}