{
  "type": "Feature",
  "properties": {
    "gn:admin1_code":"07",
    "gn:asciiname":"Akkochkar",
    "gn:country_code":"KG",
    "gn:dem":1776,
    "gn:feature_class":"P",
    "gn:feature_code":"PPL",
    "gn:name":"Akkochkar",
    "gn:population":0,
    "gn:timezone":"Asia/Bishkek",
    "iso:country":"KG",
    "name:kir_x_preferred":[
        "\u0410\u043a-\u041a\u043e\u0447\u043a\u043e\u0440"
    ],
    "name:rus_x_preferred":[
        "\u0410\u043a\u043a\u043e\u0447\u043a\u0430\u0440"
    ],
    "name:und_x_variant":[
        "Ak-Kochkor"
    ],
    "wof:name":"Akkochkar",
    "wof:placetype":"locality"
},
  "geometry": {"coordinates":[78.20249,42.42384000000001],"type":"Point"}
}