{
  "type": "Feature",
  "properties": {
    "gn:admin1_code":"00",
    "gn:asciiname":"Yartash",
    "gn:country_code":"KG",
    "gn:dem":1475,
    "gn:feature_class":"P",
    "gn:feature_code":"PPL",
    "gn:name":"Yartash",
    "gn:population":0,
    "gn:timezone":"Asia/Bishkek",
    "iso:country":"KG",
    "name:kir_x_preferred":[
        "\u0416\u0430\u0440\u0442\u0430\u0448"
    ],
    "wof:name":"Yartash",
    "wof:placetype":"locality"
},
  "geometry": {"coordinates":[72.66667,40.33333],"type":"Point"}
}