{
  "type": "Feature",
  "properties": {
    "gn:admin1_code":"08",
    "gn:asciiname":"Kul'tientr Ak-Talas",
    "gn:country_code":"KG",
    "gn:dem":1806,
    "gn:feature_class":"P",
    "gn:feature_code":"PPL",
    "gn:name":"Kul\u2019tientr Ak-Talas",
    "gn:population":0,
    "gn:timezone":"Asia/Bishkek",
    "iso:country":"KG",
    "name:kir_x_preferred":[
        "\u041a\u0443\u043b\u044c\u0442\u0438\u0435\u043d\u0442\u0440 \u0410\u043a-\u0422\u0430\u043b\u0430\u0441"
    ],
    "name:rus_x_preferred":[
        "Kul\u2019tientr Ak-Talas"
    ],
    "name:rus_x_variant":[
        "\u041a\u0443\u043b\u044c\u0442\u0438\u0435\u043d\u0442\u0440 \u0410\u043a-\u0422\u0430\u043b\u0430\u0441"
    ],
    "name:und_x_variant":[
        "Kul\u2019tientr Ak-Talas"
    ],
    "wof:name":"Kul'tientr Ak-Talas",
    "wof:placetype":"locality"
},
  "geometry": {"coordinates":[72.9405,40.03492],"type":"Point"}
}