{
  "type": "Feature",
  "properties": {
    "gn:admin1_code":"08",
    "gn:asciiname":"Boz",
    "gn:country_code":"KG",
    "gn:dem":2143,
    "gn:feature_class":"P",
    "gn:feature_code":"PPL",
    "gn:name":"Boz",
    "gn:population":0,
    "gn:timezone":"Asia/Bishkek",
    "iso:country":"KG",
    "name:ceb_x_preferred":[
        "Boz"
    ],
    "name:deu_x_preferred":[
        "Boz"
    ],
    "name:hun_x_preferred":[
        "Boz"
    ],
    "name:hye_x_preferred":[
        "\u0532\u0578\u0566"
    ],
    "name:isl_x_preferred":[
        "Boz"
    ],
    "name:kaz_x_preferred":[
        "\u0411\u043e\u0437"
    ],
    "name:kir_x_preferred":[
        "\u0411\u043e\u0437"
    ],
    "name:nld_x_preferred":[
        "Boz"
    ],
    "name:pol_x_preferred":[
        "Boz"
    ],
    "name:por_x_preferred":[
        "Boz"
    ],
    "name:ron_x_preferred":[
        "Boz"
    ],
    "name:rus_x_preferred":[
        "\u0411\u043e\u0437"
    ],
    "name:spa_x_preferred":[
        "Boz"
    ],
    "name:srp_x_preferred":[
        "\u0411\u043e\u0437"
    ],
    "name:ukr_x_preferred":[
        "\u0411\u043e\u0437"
    ],
    "name:uzb_x_preferred":[
        "Bo\u02bbz"
    ],
    "wof:name":"Boz",
    "wof:placetype":"locality"
},
  "geometry": {"coordinates":[73.34959000000001,40.24112],"type":"Point"}
}