{
  "type": "Feature",
  "properties": {
    "gn:admin1_code":"07",
    "gn:asciiname":"Cholpon",
    "gn:country_code":"KG",
    "gn:dem":1683,
    "gn:feature_class":"P",
    "gn:feature_code":"PPL",
    "gn:name":"Cholpon",
    "gn:population":0,
    "gn:timezone":"Asia/Bishkek",
    "iso:country":"KG",
    "name:kir_x_preferred":[
        "\u0427\u043e\u043b\u043f\u043e\u043d"
    ],
    "name:rus_x_preferred":[
        "\u0427\u043e\u043b\u043f\u043e\u043d"
    ],
    "name:und_x_variant":[
        "Cholpan",
        "Cholpon"
    ],
    "wof:name":"Cholpon",
    "wof:placetype":"locality"
},
  "geometry": {"coordinates":[78.47769,42.63586],"type":"Point"}
}