{
  "type": "Feature",
  "properties": {
    "gn:admin1_code":"03",
    "gn:asciiname":"Kegere-Tash",
    "gn:country_code":"KG",
    "gn:dem":1523,
    "gn:feature_class":"P",
    "gn:feature_code":"PPL",
    "gn:name":"Kegere-Tash",
    "gn:population":0,
    "gn:timezone":"Asia/Bishkek",
    "iso:country":"KG",
    "name:kir_x_preferred":[
        "\u041a\u044d\u0433\u0435\u0440\u0435-\u0422\u0430\u0448"
    ],
    "name:rus_x_preferred":[
        "\u041a\u0435\u0440\u0435\u0433\u0435-\u0422\u0430\u0448"
    ],
    "name:und_x_variant":[
        "Alash"
    ],
    "wof:name":"Kegere-Tash",
    "wof:placetype":"locality"
},
  "geometry": {"coordinates":[72.66615,41.26147],"type":"Point"}
}