{
  "type": "Feature",
  "properties": {
    "gn:admin1_code":"03",
    "gn:asciiname":"Uzbek-Abad",
    "gn:country_code":"KG",
    "gn:dem":708,
    "gn:feature_class":"P",
    "gn:feature_code":"PPL",
    "gn:name":"Uzbek-Abad",
    "gn:population":0,
    "gn:timezone":"Asia/Bishkek",
    "iso:country":"KG",
    "name:kir_x_preferred":[
        "\u04e8\u0437\u0431\u0435\u043a-\u0410\u0431\u0430\u0434"
    ],
    "name:kir_x_variant":[
        "\u0423\u0437\u0431\u0435\u043a-\u0410\u0432\u0430\u0434"
    ],
    "name:rus_x_preferred":[
        "\u0423\u0437\u0431\u0435\u043a-\u0410\u0432\u0430\u0434"
    ],
    "wof:name":"Uzbek-Abad",
    "wof:placetype":"locality"
},
  "geometry": {"coordinates":[72.94561999999998,40.85847],"type":"Point"}
}