{
  "type": "Feature",
  "properties": {
    "gn:admin1_code":"02",
    "gn:asciiname":"Ozernoye",
    "gn:country_code":"KG",
    "gn:dem":685,
    "gn:feature_class":"P",
    "gn:feature_code":"PPL",
    "gn:name":"Oz\u00ebrnoye",
    "gn:population":0,
    "gn:timezone":"Asia/Bishkek",
    "iso:country":"KG",
    "name:kir_x_preferred":[
        "\u041e\u0437\u0451\u0440\u043d\u043e\u0435"
    ],
    "name:rus_x_preferred":[
        "Oz\u00ebrnoye"
    ],
    "name:rus_x_variant":[
        "\u041e\u0437\u0451\u0440\u043d\u043e\u0435"
    ],
    "name:und_x_variant":[
        "Oz\u00ebrnoye"
    ],
    "wof:name":"Ozernoye",
    "wof:placetype":"locality"
},
  "geometry": {"coordinates":[74.43375999999998,42.94153],"type":"Point"}
}