{
  "type": "Feature",
  "properties": {
    "gn:admin1_code":"02",
    "gn:asciiname":"Aral-Dal'niy",
    "gn:country_code":"KG",
    "gn:dem":681,
    "gn:feature_class":"P",
    "gn:feature_code":"PPL",
    "gn:name":"Aral-Dal\u2019niy",
    "gn:population":0,
    "gn:timezone":"Asia/Bishkek",
    "iso:country":"KG",
    "name:kir_x_preferred":[
        "\u0410\u0440\u0430\u043b-\u0414\u0430\u043b\u044c\u043d\u0438\u0439"
    ],
    "name:rus_x_preferred":[
        "Aral-Dal\u2019niy"
    ],
    "name:rus_x_variant":[
        "\u0410\u0440\u0430\u043b-\u0414\u0430\u043b\u044c\u043d\u0438\u0439"
    ],
    "name:und_x_variant":[
        "Kutarma"
    ],
    "wof:name":"Aral-Dal'niy",
    "wof:placetype":"locality"
},
  "geometry": {"coordinates":[74.25171999999998,42.90444],"type":"Point"}
}