{
  "type": "Feature",
  "properties": {
    "gn:admin1_code":"08",
    "gn:asciiname":"Sary-Mogol",
    "gn:country_code":"KG",
    "gn:dem":2974,
    "gn:feature_class":"P",
    "gn:feature_code":"PPL",
    "gn:name":"Sary-Mogol",
    "gn:population":0,
    "gn:timezone":"Asia/Bishkek",
    "iso:country":"KG",
    "name:kir_x_preferred":[
        "\u0421\u0430\u0440\u044b-\u041c\u043e\u0433\u043e\u043b"
    ],
    "name:rus_x_preferred":[
        "\u0421\u0430\u0440\u044b-\u041c\u043e\u0433\u043e\u043b"
    ],
    "wof:name":"Sary-Mogol",
    "wof:placetype":"locality"
},
  "geometry": {"coordinates":[72.88274,39.67371],"type":"Point"}
}