{
  "type": "Feature",
  "properties": {
    "gn:admin1_code":"09",
    "gn:asciiname":"Madaniyat",
    "gn:country_code":"KG",
    "gn:dem":560,
    "gn:feature_class":"P",
    "gn:feature_code":"PPL",
    "gn:name":"Madaniyat",
    "gn:population":0,
    "gn:timezone":"Asia/Bishkek",
    "iso:country":"KG",
    "name:kir_x_preferred":[
        "\u041c\u0430\u0434\u0430\u043d\u0438\u044f\u0442"
    ],
    "name:rus_x_preferred":[
        "\u041c\u0430\u0434\u0430\u043d\u0438\u044f\u0442"
    ],
    "name:urd_x_preferred":[
        "\u0645\u06cc\u062f\u0627\u0646\u06cc\u062a"
    ],
    "name:uzb_x_preferred":[
        "Madaniyat"
    ],
    "wof:name":"Madaniyat",
    "wof:placetype":"locality"
},
  "geometry": {"coordinates":[69.55124000000001,40.09901],"type":"Point"}
}