{
  "type": "Feature",
  "properties": {
    "gn:admin1_code":"06",
    "gn:asciiname":"Ortoaryk",
    "gn:country_code":"KG",
    "gn:dem":1314,
    "gn:feature_class":"P",
    "gn:feature_code":"PPL",
    "gn:name":"Ortoaryk",
    "gn:population":0,
    "gn:timezone":"Asia/Bishkek",
    "iso:country":"KG",
    "name:kir_x_preferred":[
        "\u041e\u0440\u0442\u043e-\u0410\u0440\u044b\u043a"
    ],
    "name:rus_x_preferred":[
        "\u041e\u0440\u0442\u043e\u0430\u0440\u044b\u043a"
    ],
    "wof:name":"Ortoaryk",
    "wof:placetype":"locality"
},
  "geometry": {"coordinates":[72.34222,42.51991],"type":"Point"}
}