{
  "type": "Feature",
  "properties": {
    "gn:admin1_code":"08",
    "gn:asciiname":"Denuz-Too",
    "gn:country_code":"KG",
    "gn:dem":1269,
    "gn:feature_class":"P",
    "gn:feature_code":"PPL",
    "gn:name":"Denuz-Too",
    "gn:population":0,
    "gn:timezone":"Asia/Bishkek",
    "iso:country":"KG",
    "name:kir_x_preferred":[
        "\u0414\u043e\u043d\u0443\u0437-\u0422\u043e\u043e"
    ],
    "name:rus_x_preferred":[
        "\u0414\u0435\u043d\u0443\u0437-\u0422\u043e\u043e"
    ],
    "name:und_x_variant":[
        "Donguztou",
        "Donguztau",
        "Denuz-Too"
    ],
    "wof:name":"Denuz-Too",
    "wof:placetype":"locality"
},
  "geometry": {"coordinates":[73.55886,40.86268],"type":"Point"}
}