{
  "type": "Feature",
  "properties": {
    "gn:admin1_code":"04",
    "gn:asciiname":"Lama",
    "gn:country_code":"KG",
    "gn:dem":2179,
    "gn:feature_class":"P",
    "gn:feature_code":"PPL",
    "gn:name":"Lama",
    "gn:population":0,
    "gn:timezone":"Asia/Bishkek",
    "iso:country":"KG",
    "name:afr_x_preferred":[
        "Lama"
    ],
    "name:ara_x_preferred":[
        "\u0644\u0627\u0645\u0627"
    ],
    "name:aze_x_preferred":[
        "Lama"
    ],
    "name:bel_x_preferred":[
        "\u041b\u0430\u043c\u0430"
    ],
    "name:bod_x_preferred":[
        "\u0f56\u0fb3\u0f0b\u0f58\u0f0d"
    ],
    "name:bul_x_preferred":[
        "\u041b\u0430\u043c\u0430"
    ],
    "name:cat_x_preferred":[
        "Lama"
    ],
    "name:ces_x_preferred":[
        "L\u00e1ma"
    ],
    "name:dan_x_preferred":[
        "Lama"
    ],
    "name:deu_x_preferred":[
        "Lama"
    ],
    "name:ell_x_preferred":[
        "\u039b\u03ac\u03bc\u03b1"
    ],
    "name:epo_x_preferred":[
        "Lamao"
    ],
    "name:est_x_preferred":[
        "Laama"
    ],
    "name:fas_x_preferred":[
        "\u0644\u0627\u0645\u0627"
    ],
    "name:fin_x_preferred":[
        "Lama"
    ],
    "name:fra_x_preferred":[
        "Lama"
    ],
    "name:hin_x_preferred":[
        "\u0932\u093e\u092e\u093e"
    ],
    "name:hun_x_preferred":[
        "L\u00e1ma"
    ],
    "name:hye_x_preferred":[
        "\u053c\u0561\u0574\u0561"
    ],
    "name:ind_x_preferred":[
        "Lama"
    ],
    "name:isl_x_preferred":[
        "Lama"
    ],
    "name:ita_x_preferred":[
        "Lama"
    ],
    "name:jpn_x_preferred":[
        "\u30e9\u30de"
    ],
    "name:kat_x_preferred":[
        "\u10da\u10d0\u10db\u10d0"
    ],
    "name:kir_x_preferred":[
        "Lama"
    ],
    "name:kir_x_variant":[
        "\u042b\u043b\u0430\u043c\u0430"
    ],
    "name:kor_x_preferred":[
        "\ub77c\ub9c8"
    ],
    "name:lat_x_preferred":[
        "Lama"
    ],
    "name:mar_x_preferred":[
        "\u0932\u093e\u092e\u093e"
    ],
    "name:mdf_x_preferred":[
        "\u041b\u0430\u043c\u0430"
    ],
    "name:mon_x_preferred":[
        "\u041b\u0430\u043c"
    ],
    "name:mya_x_preferred":[
        "\u101c\u102c\u1019\u102c\u1018\u102f\u1014\u103a\u1038\u1000\u103c\u102e\u1038"
    ],
    "name:nld_x_preferred":[
        "Lama"
    ],
    "name:nno_x_preferred":[
        "Buddhistisk lama"
    ],
    "name:nor_x_preferred":[
        "Lama"
    ],
    "name:oci_x_preferred":[
        "Lama"
    ],
    "name:pan_x_preferred":[
        "\u0a32\u0a3e\u0a2e\u0a3e"
    ],
    "name:pol_x_preferred":[
        "Lama"
    ],
    "name:por_x_preferred":[
        "Lama"
    ],
    "name:ron_x_preferred":[
        "Lama"
    ],
    "name:rus_x_preferred":[
        "\u041b\u0430\u043c\u0430"
    ],
    "name:sco_x_preferred":[
        "Lama"
    ],
    "name:slk_x_preferred":[
        "L\u00e1ma"
    ],
    "name:slv_x_preferred":[
        "Lama"
    ],
    "name:spa_x_preferred":[
        "Lama"
    ],
    "name:srp_x_preferred":[
        "\u041b\u0430\u043c\u0430"
    ],
    "name:swa_x_preferred":[
        "Lama"
    ],
    "name:swe_x_preferred":[
        "Lama"
    ],
    "name:tha_x_preferred":[
        "\u0e25\u0e32\u0e21\u0e30"
    ],
    "name:tur_x_preferred":[
        "Lama"
    ],
    "name:tyv_x_preferred":[
        "\u041b\u0430\u043c\u0430"
    ],
    "name:ukr_x_preferred":[
        "\u041b\u0430\u043c\u0430"
    ],
    "name:uzb_x_preferred":[
        "Lama"
    ],
    "name:vie_x_preferred":[
        "L\u1ea1t-ma"
    ],
    "wof:name":"Lama",
    "wof:placetype":"locality"
},
  "geometry": {"coordinates":[74.91323,42.04006],"type":"Point"}
}