{
  "type": "Feature",
  "properties": {
    "gn:admin1_code":"04",
    "gn:asciiname":"Lama",
    "gn:country_code":"KG",
    "gn:dem":2179,
    "gn:feature_class":"P",
    "gn:feature_code":"PPL",
    "gn:name":"Lama",
    "gn:population":0,
    "gn:timezone":"Asia/Bishkek",
    "iso:country":"KG",
    "name:kir_x_preferred":[
        "Lama"
    ],
    "name:rus_x_preferred":[
        "\u041b\u0430\u043c\u0430"
    ],
    "wof:name":"Lama",
    "wof:placetype":"locality"
},
  "geometry": {"coordinates":[74.91323,42.04006],"type":"Point"}
}