{
  "type": "Feature",
  "properties": {
    "gn:admin1_code":"03",
    "gn:asciiname":"Askaly",
    "gn:country_code":"KG",
    "gn:dem":1356,
    "gn:feature_class":"P",
    "gn:feature_code":"PPL",
    "gn:name":"Askaly",
    "gn:population":0,
    "gn:timezone":"Asia/Bishkek",
    "iso:country":"KG",
    "name:kir_x_preferred":[
        "\u0410\u0441\u043a\u0430\u043b\u044b"
    ],
    "name:rus_x_preferred":[
        "\u0410\u0441\u043a\u0430\u043b\u044b"
    ],
    "name:und_x_variant":[
        "Aslam"
    ],
    "wof:name":"Askaly",
    "wof:placetype":"locality"
},
  "geometry": {"coordinates":[74.15533000000001,41.4198],"type":"Point"}
}