{
  "type": "Feature",
  "properties": {
    "iso:country":"KG",
    "name:ceb_x_preferred":[
        "Cholpon-Ata Airport"
    ],
    "name:eng_x_preferred":[
        "Cholpon-Ata Airport"
    ],
    "name:eng_x_variant":[
        "UAFG"
    ],
    "name:fas_x_preferred":[
        "\u0641\u0631\u0648\u062f\u06af\u0627\u0647 \u0686\u0627\u0644\u067e\u0627\u0646\u200c\u0622\u062a\u0627"
    ],
    "name:hun_x_preferred":[
        "Csolpon-Ata rep\u00fcl\u0151t\u00e9r"
    ],
    "name:jpn_x_preferred":[
        "\u30c1\u30e7\u30eb\u30dd\u30f3\uff1d\u30a2\u30bf\u7a7a\u6e2f"
    ],
    "name:pol_x_preferred":[
        "Port lotniczy Czo\u0142ponata"
    ],
    "name:swe_x_preferred":[
        "Tjolpon-Atinskij aeroport"
    ],
    "oa:elevation_ft":"5420",
    "oa:type":"small_airport",
    "woe:hierarchy":{
        "country_id":23424864,
        "planet_id":1,
        "state_id":20070190
    },
    "wof:name":"Cholponata Airport",
    "wof:placetype":"campus"
},
  "geometry": {"coordinates":[77.056667,42.653611],"type":"Point"}
}