{
  "type": "Feature",
  "properties": {
    "iso:country":"KG",
    "name:ceb_x_preferred":[
        "Cholpon-Ata Airport"
    ],
    "name:eng_x_preferred":[
        "Cholpon-Ata Airport"
    ],
    "name:jpn_x_preferred":[
        "\u30c1\u30e7\u30eb\u30dd\u30f3\uff1d\u30a2\u30bf\u7a7a\u6e2f"
    ],
    "name:pol_x_preferred":[
        "Port lotniczy Czo\u0142ponata"
    ],
    "name:swe_x_preferred":[
        "Tjolpon-Atinskij aeroport"
    ],
    "oa:elevation_ft":"5420",
    "oa:type":"small_airport",
    "woe:hierarchy":{
        "country_id":23424864,
        "planet_id":1,
        "state_id":20070190
    },
    "wof:name":"Cholponata Airport",
    "wof:placetype":"campus"
},
  "geometry": {"coordinates":[77.05666667,42.65361111],"type":"Point"}
}