{
  "type": "Feature",
  "properties": {
    "gn:admin1_code":"03",
    "gn:asciiname":"Ornok",
    "gn:country_code":"KG",
    "gn:dem":1395,
    "gn:feature_class":"P",
    "gn:feature_code":"PPL",
    "gn:name":"\u00d6rn\u00f6k",
    "gn:population":0,
    "gn:timezone":"Asia/Bishkek",
    "iso:country":"KG",
    "name:kir_x_preferred":[
        "\u04e8\u0440\u043d\u04e9\u043a"
    ],
    "name:und_x_variant":[
        "\u00d6rn\u00f6k"
    ],
    "wof:name":"Ornok",
    "wof:placetype":"locality"
},
  "geometry": {"coordinates":[74.15704000000002,41.41194],"type":"Point"}
}