{
  "type": "Feature",
  "properties": {
    "gn:country":"KG",
    "gn:fcode":"PPLA2",
    "gn:population":27704,
    "iso:country":"KG",
    "name:aze_x_preferred":[
        "Bazar-Korqon"
    ],
    "name:ceb_x_preferred":[
        "Bazar-Korgon"
    ],
    "name:che_x_preferred":[
        "\u0411\u0430\u0437\u0430\u0440-\u041a\u043e\u0440\u0433\u043e\u043d"
    ],
    "name:ckb_x_preferred":[
        "\u0628\u0627\u0632\u0627\u0695-\u0642\u06c6\u0631\u063a\u06c6\u0646"
    ],
    "name:eng_x_preferred":[
        "Bazar-Korgon"
    ],
    "name:est_x_preferred":[
        "Bazarkorgon"
    ],
    "name:fas_x_preferred":[
        "\u0628\u0627\u0632\u0627\u0631-\u0642\u0648\u0631\u063a\u0648\u0646"
    ],
    "name:fra_x_preferred":[
        "Bazar-Korgon"
    ],
    "name:hun_x_preferred":[
        "Bazarkorgon"
    ],
    "name:ita_x_preferred":[
        "Bazar-Korgon"
    ],
    "name:kir_x_preferred":[
        "Bazar-Korgon"
    ],
    "name:kir_x_variant":[
        "\u0411\u0430\u0437\u0430\u0440-\u041a\u043e\u0440\u0433\u043e\u043d"
    ],
    "name:nld_x_preferred":[
        "Bazar-Korgon"
    ],
    "name:pol_x_preferred":[
        "Bazarkorgon"
    ],
    "name:rus_x_preferred":[
        "\u0411\u0430\u0437\u0430\u0440-\u041a\u043e\u0440\u0433\u043e\u043d"
    ],
    "name:swe_x_preferred":[
        "Bazar-Korgon"
    ],
    "name:tgk_x_preferred":[
        "\u0411\u043e\u0437\u043e\u0440-\u049a\u04ef\u0440\u0493\u043e\u043d"
    ],
    "name:tur_x_preferred":[
        "Bazar-Korgon"
    ],
    "name:ukr_x_preferred":[
        "\u0411\u0430\u0437\u0430\u0440-\u041a\u043e\u0440\u0433\u043e\u043d"
    ],
    "name:ukr_x_variant":[
        "\u0421\u043e\u0441\u043d\u043e\u0432\u043a\u0430"
    ],
    "name:und_x_variant":[
        "Bazar"
    ],
    "name:uzb_x_preferred":[
        "Bozor-Qo\u2018rg\u2018on"
    ],
    "name:uzb_x_variant":[
        "Bozorqo\u02bbrg\u02bbon"
    ],
    "name:zho_x_preferred":[
        "\u5df4\u624e\u5c14\u5e93\u5c14\u5e72"
    ],
    "qs:name":"Bazar-Korgon",
    "qs:photos_9r":0,
    "qs:photos_sr":0,
    "qs:pop_sr":"7",
    "wd:wordcount":73,
    "wof:name":"Bazar-Korgon",
    "wof:placetype":"locality",
    "wof:population":27704
},
  "geometry": {"coordinates":[72.74585999999999,41.0376],"type":"Point"}
}