{
  "type": "Feature",
  "properties": {
    "gn:country":"KG",
    "gn:fcode":"PPLA2",
    "gn:pop":27704,
    "iso:country":"KG",
    "name:chi_x_preferred":[
        "\u5df4\u624e\u5c14\u5e93\u5c14\u5e72"
    ],
    "name:ckb_x_preferred":[
        "\u0628\u0627\u0632\u0627\u0695-\u0642\u06c6\u0631\u063a\u06c6\u0646"
    ],
    "name:dut_x_preferred":[
        "Bazar-Korgon"
    ],
    "name:eng_x_preferred":[
        "Bazar-Korgon"
    ],
    "name:est_x_preferred":[
        "Bazarkorgon"
    ],
    "name:fre_x_preferred":[
        "Bazar-Korgon"
    ],
    "name:ita_x_preferred":[
        "Bazar-Korgon"
    ],
    "name:kir_x_preferred":[
        "Bazar-Korgon"
    ],
    "name:per_x_preferred":[
        "\u0628\u0627\u0632\u0627\u0631-\u0642\u0648\u0631\u063a\u0648\u0646"
    ],
    "name:pol_x_preferred":[
        "Bazarkorgon"
    ],
    "name:rus_x_preferred":[
        "\u0411\u0430\u0437\u0430\u0440-\u041a\u043e\u0440\u0433\u043e\u043d"
    ],
    "name:swe_x_preferred":[
        "Bazar-Korgon"
    ],
    "name:tur_x_preferred":[
        "Bazar-Korgon"
    ],
    "name:ukr_x_preferred":[
        "\u0411\u0430\u0437\u0430\u0440-\u041a\u043e\u0440\u0433\u043e\u043d"
    ],
    "name:unk_x_variant":[
        "Bazar"
    ],
    "name:uzb_x_preferred":[
        "Bozor-Qo\u2018rg\u2018on"
    ],
    "qs:name":"Bazar-Korgon",
    "qs:photos_9r":0,
    "qs:photos_sr":0,
    "qs:pop_sr":"7",
    "wd:wordcount":73,
    "wof:name":"Bazar-Korgon",
    "wof:placetype":"locality",
    "wof:population":27704
},
  "geometry": {"coordinates":[72.74585999999999,41.0376],"type":"Point"}
}