{
  "type": "Feature",
  "properties": {
    "gn:admin1_code":"09",
    "gn:asciiname":"Kyrgyz-Kyshtak",
    "gn:country_code":"KG",
    "gn:dem":504,
    "gn:feature_class":"P",
    "gn:feature_code":"PPLA3",
    "gn:name":"Kyrgyz-Kyshtak",
    "gn:population":0,
    "gn:timezone":"Asia/Bishkek",
    "iso:country":"KG",
    "name:kir_x_preferred":[
        "\u041a\u0438\u0440\u0433\u0438\u0437-\u041a\u044b\u0448\u0442\u0430\u043a"
    ],
    "name:rus_x_preferred":[
        "\u041a\u0438\u0440\u0433\u0438\u0437-\u041a\u044b\u0448\u0442\u0430\u043a"
    ],
    "name:rus_x_variant":[
        "\u041a\u044b\u0440\u0433\u044b\u0437-\u041a\u044b\u0448\u0442\u0430\u043a"
    ],
    "name:und_x_variant":[
        "Kirgiz-Kyshtak"
    ],
    "name:uzb_x_preferred":[
        "Qirg\u2018iz-Qishtak"
    ],
    "wof:name":"Kyrgyz-Kyshtak",
    "wof:placetype":"locality"
},
  "geometry": {"coordinates":[71.34966,40.31055],"type":"Point"}
}