{
  "type": "Feature",
  "properties": {
    "gn:admin1_code":"09",
    "gn:asciiname":"Kozho Korum",
    "gn:country_code":"KG",
    "gn:dem":1499,
    "gn:feature_class":"P",
    "gn:feature_code":"PPL",
    "gn:name":"Kozho Korum",
    "gn:population":0,
    "gn:timezone":"Asia/Bishkek",
    "iso:country":"KG",
    "name:kir_x_preferred":[
        "\u041a\u043e\u0436\u043e \u041a\u043e\u0440\u0443\u043c"
    ],
    "name:rus_x_preferred":[
        "\u041a\u043e\u0436\u043e \u041a\u043e\u0440\u0443\u043c"
    ],
    "name:und_x_variant":[
        "Khodzhanorum",
        "Kozho Korum"
    ],
    "name:uzb_x_preferred":[
        "Kojo-Korum"
    ],
    "wof:name":"Kozho Korum",
    "wof:placetype":"locality"
},
  "geometry": {"coordinates":[71.32115999999998,40.09714],"type":"Point"}
}