{
  "type": "Feature",
  "properties": {
    "gn:admin1_code":"09",
    "gn:asciiname":"Tayan",
    "gn:country_code":"KG",
    "gn:dem":1279,
    "gn:feature_class":"P",
    "gn:feature_code":"PPLA3",
    "gn:name":"Tayan",
    "gn:population":0,
    "gn:timezone":"Asia/Bishkek",
    "iso:country":"KG",
    "name:ell_x_preferred":[
        "\u03a4\u03b1\u03b3\u03b9\u03ac\u03bd"
    ],
    "name:kir_x_preferred":[
        "\u0422\u0430\u044f\u043d"
    ],
    "name:rus_x_preferred":[
        "\u0422\u0430\u044f\u043d"
    ],
    "name:uzb_x_preferred":[
        "Taen"
    ],
    "name:uzb_x_variant":[
        "Tayan"
    ],
    "wof:name":"Tayan",
    "wof:placetype":"locality"
},
  "geometry": {"coordinates":[71.10826,39.9026],"type":"Point"}
}