{
  "type": "Feature",
  "properties": {
    "gn:admin1_code":"04",
    "gn:asciiname":"Alysh",
    "gn:country_code":"KG",
    "gn:dem":2154,
    "gn:feature_class":"P",
    "gn:feature_code":"PPL",
    "gn:name":"Alysh",
    "gn:population":0,
    "gn:timezone":"Asia/Bishkek",
    "iso:country":"KG",
    "name:kir_x_preferred":[
        "\u0410\u043b\u044b\u0448"
    ],
    "name:rus_x_preferred":[
        "\u0410\u043b\u044b\u0448"
    ],
    "wof:name":"Alysh",
    "wof:placetype":"locality"
},
  "geometry": {"coordinates":[76.19465,41.44479000000001],"type":"Point"}
}