{
  "type": "Feature",
  "properties": {
    "gn:admin1_code":"08",
    "gn:asciiname":"Nasirdin",
    "gn:country_code":"KG",
    "gn:dem":1383,
    "gn:feature_class":"P",
    "gn:feature_code":"PPL",
    "gn:name":"Nasirdin",
    "gn:population":0,
    "gn:timezone":"Asia/Bishkek",
    "iso:country":"KG",
    "name:kir_x_preferred":[
        "\u041d\u0430\u0441\u0438\u0440\u0434\u0438\u043d"
    ],
    "name:rus_x_preferred":[
        "\u041d\u0430\u0441\u0438\u0440\u0434\u0438\u043d"
    ],
    "wof:name":"Nasirdin",
    "wof:placetype":"locality"
},
  "geometry": {"coordinates":[73.49656999999998,40.58707],"type":"Point"}
}