{
  "type": "Feature",
  "properties": {
    "gn:admin1_code":"03",
    "gn:asciiname":"Gologon",
    "gn:country_code":"KG",
    "gn:dem":910,
    "gn:feature_class":"P",
    "gn:feature_code":"PPL",
    "gn:name":"Gologon",
    "gn:population":0,
    "gn:timezone":"Asia/Bishkek",
    "iso:country":"KG",
    "name:kir_x_preferred":[
        "\u0413\u04e9\u043b\u04e9\u0433\u04e9\u043d"
    ],
    "name:rus_x_preferred":[
        "G\u00ebl\u00ebg\u00ebn"
    ],
    "name:rus_x_variant":[
        "\u0413\u0451\u043b\u0451\u0433\u0451\u043d"
    ],
    "name:und_x_variant":[
        "Zimovka Kulyugen",
        "Kulyugen"
    ],
    "wof:name":"Gologon",
    "wof:placetype":"locality"
},
  "geometry": {"coordinates":[72.72336999999997,41.11707],"type":"Point"}
}