{
  "type": "Feature",
  "properties": {
    "gn:admin1_code":"04",
    "gn:asciiname":"Dungurme",
    "gn:country_code":"KG",
    "gn:dem":1733,
    "gn:feature_class":"P",
    "gn:feature_code":"PPL",
    "gn:name":"Dungurme",
    "gn:population":0,
    "gn:timezone":"Asia/Bishkek",
    "iso:country":"KG",
    "name:kir_x_preferred":[
        "\u0414\u044e\u043d\u0433\u044e\u0440\u0451\u043c\u0451"
    ],
    "name:rus_x_preferred":[
        "\u0414\u044e\u043d\u0433\u044e\u0440\u0451\u043c\u0451"
    ],
    "name:und_x_variant":[
        "Dyungyur\u00ebm\u00eb"
    ],
    "wof:name":"Dungurme",
    "wof:placetype":"locality"
},
  "geometry": {"coordinates":[74.32419,41.68444],"type":"Point"}
}