{
  "type": "Feature",
  "properties": {
    "gn:admin1_code":"04",
    "gn:asciiname":"Kichi-Dzhotash",
    "gn:country_code":"KG",
    "gn:dem":1760,
    "gn:feature_class":"P",
    "gn:feature_code":"PPL",
    "gn:name":"Kichi-Dzhotash",
    "gn:population":0,
    "gn:timezone":"Asia/Bishkek",
    "iso:country":"KG",
    "name:kir_x_preferred":[
        "\u041a\u0438\u0447\u0438-\u0416\u043e\u0442\u0430\u0448"
    ],
    "name:rus_x_preferred":[
        "\u041a\u0438\u0447\u0438-\u0414\u0436\u043e\u0442\u0430\u0448"
    ],
    "wof:name":"Kichi-Dzhotash",
    "wof:placetype":"locality"
},
  "geometry": {"coordinates":[74.16143000000002,41.7484],"type":"Point"}
}