{
  "type": "Feature",
  "properties": {
    "gn:admin1_code":"04",
    "gn:asciiname":"Terek",
    "gn:country_code":"KG",
    "gn:dem":2068,
    "gn:feature_class":"P",
    "gn:feature_code":"PPL",
    "gn:name":"Terek",
    "gn:population":0,
    "gn:timezone":"Asia/Bishkek",
    "iso:country":"KG",
    "name:bak_x_preferred":[
        "\u0422\u0438\u0440\u04d9\u043a"
    ],
    "name:bel_x_preferred":[
        "\u0426\u0435\u0440\u0430\u043a"
    ],
    "name:ceb_x_preferred":[
        "Terek"
    ],
    "name:dan_x_preferred":[
        "Terek"
    ],
    "name:epo_x_preferred":[
        "Terek"
    ],
    "name:fra_x_preferred":[
        "Terek"
    ],
    "name:hun_x_preferred":[
        "Tyerek"
    ],
    "name:ita_x_preferred":[
        "Terek"
    ],
    "name:kbd_x_preferred":[
        "\u0422\u044d\u0440\u0447"
    ],
    "name:kir_x_preferred":[
        "\u0422\u0435\u0440\u0435\u043a"
    ],
    "name:lez_x_preferred":[
        "\u0422\u0435\u0440\u0435\u043a"
    ],
    "name:nld_x_preferred":[
        "Terek"
    ],
    "name:nor_x_preferred":[
        "Terek"
    ],
    "name:pol_x_preferred":[
        "Tieriek"
    ],
    "name:rus_x_preferred":[
        "\u0422\u0435\u0440\u0435\u043a"
    ],
    "name:swe_x_preferred":[
        "Terek"
    ],
    "name:ukr_x_preferred":[
        "\u0422\u0435\u0440\u0435\u043a"
    ],
    "name:vep_x_preferred":[
        "Terek"
    ],
    "wof:name":"Terek",
    "wof:placetype":"locality"
},
  "geometry": {"coordinates":[74.99584,41.23148],"type":"Point"}
}