{
  "type": "Feature",
  "properties": {
    "gn:admin1_code":"08",
    "gn:asciiname":"Alashan",
    "gn:country_code":"KG",
    "gn:dem":1256,
    "gn:feature_class":"P",
    "gn:feature_code":"PPL",
    "gn:name":"Alashan",
    "gn:population":0,
    "gn:timezone":"Asia/Bishkek",
    "iso:country":"KG",
    "name:fas_x_preferred":[
        "\u0627\u0644\u0627\u0634\u0627\u0646"
    ],
    "name:kir_x_preferred":[
        "\u0410\u043b\u0430\u0448\u0430\u043d"
    ],
    "name:rus_x_preferred":[
        "\u0410\u043b\u0430\u0448\u0430\u043d"
    ],
    "name:und_x_variant":[
        "Alashay"
    ],
    "name:uzb_x_preferred":[
        "Alashan"
    ],
    "wof:name":"Alashan",
    "wof:placetype":"locality"
},
  "geometry": {"coordinates":[72.35551,40.30894],"type":"Point"}
}