{
  "type": "Feature",
  "properties": {
    "gn:admin1_code":"02",
    "gn:asciiname":"Meenetkech",
    "gn:country_code":"KG",
    "gn:dem":907,
    "gn:feature_class":"P",
    "gn:feature_code":"PPL",
    "gn:name":"Meenetkech",
    "gn:population":0,
    "gn:timezone":"Asia/Bishkek",
    "iso:country":"KG",
    "name:kir_x_preferred":[
        "\u041c\u044d\u044d\u043d\u0435\u0442\u043a\u0435\u0447"
    ],
    "name:rus_x_preferred":[
        "\u041c\u044d\u044d\u043d\u0435\u0442\u043a\u0435\u0447"
    ],
    "wof:name":"Meenetkech",
    "wof:placetype":"locality"
},
  "geometry": {"coordinates":[75.29885999999998,42.77945],"type":"Point"}
}