{
  "type": "Feature",
  "properties": {
    "gn:admin1_code":"02",
    "gn:asciiname":"Tar-Suu",
    "gn:country_code":"KG",
    "gn:dem":1508,
    "gn:feature_class":"P",
    "gn:feature_code":"PPL",
    "gn:name":"Tar-Suu",
    "gn:population":0,
    "gn:timezone":"Asia/Bishkek",
    "iso:country":"KG",
    "name:kir_x_preferred":[
        "\u0422\u0430\u0440-\u0421\u0443\u0443"
    ],
    "name:rus_x_preferred":[
        "\u0422\u0430\u0440-\u0421\u0443\u0443"
    ],
    "name:und_x_variant":[
        "Tarsu",
        "Tar-Suu"
    ],
    "wof:name":"Tar-Suu",
    "wof:placetype":"locality"
},
  "geometry": {"coordinates":[76.05903000000001,42.70651],"type":"Point"}
}