{
  "type": "Feature",
  "properties": {
    "gn:admin1_code":"04",
    "gn:asciiname":"Tash-Bulak",
    "gn:country_code":"KG",
    "gn:dem":2038,
    "gn:feature_class":"P",
    "gn:feature_code":"PPL",
    "gn:name":"Tash-Bulak",
    "gn:population":0,
    "gn:timezone":"Asia/Bishkek",
    "iso:country":"KG",
    "name:kir_x_preferred":[
        "\u0422\u0430\u0448-\u0411\u0443\u043b\u0430\u043a"
    ],
    "name:rus_x_preferred":[
        "\u0422\u0430\u0448\u0431\u0443\u043b\u0430\u043a"
    ],
    "name:und_x_variant":[
        "Tashbulak"
    ],
    "wof:name":"Tash-Bulak",
    "wof:placetype":"locality"
},
  "geometry": {"coordinates":[75.90725999999999,41.42872],"type":"Point"}
}