{
  "type": "Feature",
  "properties": {
    "gn:admin1_code":"08",
    "gn:asciiname":"Yetti-Ogayni",
    "gn:country_code":"KG",
    "gn:dem":832,
    "gn:feature_class":"P",
    "gn:feature_code":"PPL",
    "gn:name":"Yetti-Ogayni",
    "gn:population":0,
    "gn:timezone":"Asia/Bishkek",
    "iso:country":"KG",
    "name:rus_x_preferred":[
        "\u0415\u0442\u0442\u0438-\u041e\u0433\u0430\u0439\u043d\u0438"
    ],
    "wof:name":"Yetti-Ogayni",
    "wof:placetype":"locality"
},
  "geometry": {"coordinates":[72.54488000000001,40.50289],"type":"Point"}
}