{
  "type": "Feature",
  "properties": {
    "gn:admin1_code":"04",
    "gn:asciiname":"Kardydzharyk",
    "gn:country_code":"KG",
    "gn:dem":2061,
    "gn:feature_class":"P",
    "gn:feature_code":"PPL",
    "gn:name":"Kardydzharyk",
    "gn:population":0,
    "gn:timezone":"Asia/Bishkek",
    "iso:country":"KG",
    "name:kir_x_preferred":[
        "\u041a\u0430\u0440\u0434\u044b\u0434\u0436-\u0410\u0440\u044b\u043a"
    ],
    "name:rus_x_preferred":[
        "\u041a\u0430\u0440\u0434\u044b\u0434\u0436\u0430\u0440\u044b\u043a"
    ],
    "wof:name":"Kardydzharyk",
    "wof:placetype":"locality"
},
  "geometry": {"coordinates":[74.76478,42.0547],"type":"Point"}
}