{
  "type": "Feature",
  "properties": {
    "gn:admin1_code":"03",
    "gn:asciiname":"Altyn-Kyya",
    "gn:country_code":"KG",
    "gn:dem":1296,
    "gn:feature_class":"P",
    "gn:feature_code":"PPL",
    "gn:name":"Altyn-Kyya",
    "gn:population":0,
    "gn:timezone":"Asia/Bishkek",
    "iso:country":"KG",
    "name:kir_x_preferred":[
        "\u041a\u04e9\u0437\u04e9-\u0422\u0435\u0440\u0435\u0433"
    ],
    "name:rus_x_preferred":[
        "\u0410\u043b\u0442\u044b\u043d-\u041a\u044b\u044f"
    ],
    "name:und_x_variant":[
        "K\u00f6s\u00f6-Terek",
        "Altyn-Kyya"
    ],
    "wof:name":"Altyn-Kyya",
    "wof:placetype":"locality"
},
  "geometry": {"coordinates":[73.06381999999998,41.3947],"type":"Point"}
}