{
  "type": "Feature",
  "properties": {
    "gn:admin1_code":"06",
    "gn:asciiname":"Kektokoy",
    "gn:country_code":"KG",
    "gn:dem":1286,
    "gn:feature_class":"P",
    "gn:feature_code":"PPL",
    "gn:name":"K\u00ebktokoy",
    "gn:population":0,
    "gn:timezone":"Asia/Bishkek",
    "iso:country":"KG",
    "name:kir_x_preferred":[
        "\u041a\u04e9\u043a-\u0422\u043e\u043a\u043e\u0439"
    ],
    "name:rus_x_preferred":[
        "K\u00ebktokoy"
    ],
    "name:rus_x_variant":[
        "\u041a\u0451\u043a\u0442\u043e\u043a\u043e\u0439"
    ],
    "wof:name":"Kektokoy",
    "wof:placetype":"locality"
},
  "geometry": {"coordinates":[72.30996,42.51721],"type":"Point"}
}