{
  "type": "Feature",
  "properties": {
    "gn:admin1_code":"08",
    "gn:asciiname":"Karchabek",
    "gn:country_code":"KG",
    "gn:dem":1201,
    "gn:feature_class":"P",
    "gn:feature_code":"PPL",
    "gn:name":"Karchabek",
    "gn:population":0,
    "gn:timezone":"Asia/Bishkek",
    "iso:country":"KG",
    "name:kir_x_preferred":[
        "\u041a\u0430\u0440\u0447\u0430\u0431\u0435\u043a"
    ],
    "name:rus_x_preferred":[
        "\u041a\u0430\u0440\u0447\u0430\u0431\u0435\u043a"
    ],
    "wof:name":"Karchabek",
    "wof:placetype":"locality"
},
  "geometry": {"coordinates":[73.53832,40.8292],"type":"Point"}
}