{
  "type": "Feature",
  "properties": {
    "gn:admin1_code":"03",
    "gn:asciiname":"Balykty",
    "gn:country_code":"KG",
    "gn:dem":1397,
    "gn:feature_class":"P",
    "gn:feature_code":"PPL",
    "gn:name":"Balykty",
    "gn:population":0,
    "gn:timezone":"Asia/Bishkek",
    "iso:country":"KG",
    "name:kir_x_preferred":[
        "\u0411\u0430\u043b\u044b\u043a\u0442\u044b"
    ],
    "name:rus_x_preferred":[
        "\u0411\u0430\u043b\u044b\u043a\u0442\u044b"
    ],
    "name:uzb_x_preferred":[
        "Baliqti"
    ],
    "wof:name":"Balykty",
    "wof:placetype":"locality"
},
  "geometry": {"coordinates":[72.58105999999999,41.97247],"type":"Point"}
}