{
  "type": "Feature",
  "properties": {
    "gn:admin1_code":"06",
    "gn:asciiname":"Karakatash",
    "gn:country_code":"KG",
    "gn:dem":1506,
    "gn:feature_class":"P",
    "gn:feature_code":"PPL",
    "gn:name":"Karakatash",
    "gn:population":0,
    "gn:timezone":"Asia/Bishkek",
    "iso:country":"KG",
    "name:kir_x_preferred":[
        "\u041a\u0430\u0440\u0430-\u041a\u0430\u0442\u0430\u0448"
    ],
    "name:rus_x_preferred":[
        "\u041a\u0430\u0440\u0430\u043a\u0430\u0442\u0430\u0448"
    ],
    "wof:name":"Karakatash",
    "wof:placetype":"locality"
},
  "geometry": {"coordinates":[72.57731,42.48924],"type":"Point"}
}