{
  "type": "Feature",
  "properties": {
    "gn:admin1_code":"02",
    "gn:asciiname":"Tosh-Bulak",
    "gn:country_code":"KG",
    "gn:dem":1273,
    "gn:feature_class":"P",
    "gn:feature_code":"PPL",
    "gn:name":"Tosh-Bulak",
    "gn:population":0,
    "gn:timezone":"Asia/Bishkek",
    "iso:country":"KG",
    "name:kir_x_preferred":[
        "\u0422\u043e\u0448-\u0411\u0443\u043b\u0430\u043a"
    ],
    "name:rus_x_preferred":[
        "\u0411\u0435\u043b\u043e\u0433\u043e\u0440\u043a\u0430"
    ],
    "name:und_x_variant":[
        "Belogorskoye",
        "Belogorka"
    ],
    "wof:name":"Tosh-Bulak",
    "wof:placetype":"locality"
},
  "geometry": {"coordinates":[74.23902,42.68131],"type":"Point"}
}