{
  "type": "Feature",
  "properties": {
    "gn:admin1_code":"04",
    "gn:asciiname":"Ak-Say Madaniy Borbor",
    "gn:country_code":"KG",
    "gn:dem":3264,
    "gn:feature_class":"P",
    "gn:feature_code":"PPL",
    "gn:name":"Ak-Say Madaniy Borbor",
    "gn:population":0,
    "gn:timezone":"Asia/Bishkek",
    "iso:country":"KG",
    "name:kir_x_preferred":[
        "Ak-Say Madaniy Borbor"
    ],
    "wof:name":"Ak-Say Madaniy Borbor",
    "wof:placetype":"locality"
},
  "geometry": {"coordinates":[76.10251,40.80157],"type":"Point"}
}