{
  "type": "Feature",
  "properties": {
    "gn:admin1_code":"03",
    "gn:asciiname":"Kosh-Bolot",
    "gn:country_code":"KG",
    "gn:dem":1034,
    "gn:feature_class":"P",
    "gn:feature_code":"PPL",
    "gn:name":"Kosh-Bolot",
    "gn:population":0,
    "gn:timezone":"Asia/Bishkek",
    "iso:country":"KG",
    "name:eng_x_preferred":[
        "Qo\u2018sh-Bolot"
    ],
    "name:kir_x_preferred":[
        "\u041a\u043e\u0448-\u0411\u043e\u043b\u043e\u0442"
    ],
    "name:rus_x_preferred":[
        "\u041a\u043e\u0448-\u0411\u043e\u043b\u043e\u0442"
    ],
    "wof:name":"Kosh-Bolot",
    "wof:placetype":"locality"
},
  "geometry": {"coordinates":[71.27925999999999,41.18719],"type":"Point"}
}