{
  "type": "Feature",
  "properties": {
    "gn:admin1_code":"00",
    "gn:asciiname":"Nura",
    "gn:country_code":"KG",
    "gn:dem":908,
    "gn:feature_class":"P",
    "gn:feature_code":"PPL",
    "gn:name":"Nura",
    "gn:population":0,
    "gn:timezone":"Asia/Bishkek",
    "iso:country":"KG",
    "name:kir_x_preferred":[
        "\u041d\u0443\u0440\u0430"
    ],
    "wof:name":"Nura",
    "wof:placetype":"locality"
},
  "geometry": {"coordinates":[73.17435,40.89425],"type":"Point"}
}