{
  "type": "Feature",
  "properties": {
    "gn:admin1_code":"03",
    "gn:asciiname":"Nichke",
    "gn:country_code":"KG",
    "gn:dem":1640,
    "gn:feature_class":"P",
    "gn:feature_code":"PPL",
    "gn:name":"Nichke",
    "gn:population":0,
    "gn:timezone":"Asia/Bishkek",
    "iso:country":"KG",
    "name:kir_x_preferred":[
        "\u041d\u0438\u0447\u043a\u0435"
    ],
    "name:rus_x_preferred":[
        "\u041d\u0438\u0447\u043a\u0435"
    ],
    "wof:name":"Nichke",
    "wof:placetype":"locality"
},
  "geometry": {"coordinates":[73.46731,41.69287],"type":"Point"}
}