{
  "type": "Feature",
  "properties": {
    "gn:admin1_code":"08",
    "gn:asciiname":"Jar-Bashi",
    "gn:country_code":"KG",
    "gn:dem":2437,
    "gn:feature_class":"P",
    "gn:feature_code":"PPL",
    "gn:name":"Jar-Bashi",
    "gn:population":0,
    "gn:timezone":"Asia/Bishkek",
    "iso:country":"KG",
    "name:kir_x_preferred":[
        "\u0416\u0430\u0440-\u0411\u0430\u0448\u044b"
    ],
    "name:rus_x_preferred":[
        "\u0414\u0436\u0430\u0440-\u0411\u0430\u0448\u0438"
    ],
    "name:und_x_variant":[
        "Dzhar-Bashi"
    ],
    "wof:name":"Jar-Bashi",
    "wof:placetype":"locality"
},
  "geometry": {"coordinates":[72.11693000000002,39.51468],"type":"Point"}
}