{
  "type": "Feature",
  "properties": {
    "gn:admin1_code":"04",
    "gn:asciiname":"Akbashim",
    "gn:country_code":"KG",
    "gn:dem":1775,
    "gn:feature_class":"P",
    "gn:feature_code":"PPL",
    "gn:name":"Akbashim",
    "gn:population":0,
    "gn:timezone":"Asia/Bishkek",
    "iso:country":"KG",
    "name:fas_x_preferred":[
        "\u0627\u06a9\u0628\u0627\u0634\u06cc\u0645"
    ],
    "name:kir_x_preferred":[
        "\u0410\u043a-\u0411\u0430\u0448\u0438\u043c"
    ],
    "name:rus_x_preferred":[
        "\u0410\u043a\u0431\u0430\u0448\u0438\u043c"
    ],
    "wof:name":"Akbashim",
    "wof:placetype":"locality"
},
  "geometry": {"coordinates":[75.40352,41.3967],"type":"Point"}
}