{
  "type": "Feature",
  "properties": {
    "gn:admin1_code":"09",
    "gn:asciiname":"Koshbulak",
    "gn:country_code":"KG",
    "gn:dem":1534,
    "gn:elevation":"1909.0",
    "gn:feature_class":"P",
    "gn:feature_code":"PPL",
    "gn:name":"Koshbulak",
    "gn:population":0,
    "gn:timezone":"Asia/Bishkek",
    "iso:country":"KG",
    "name:ckb_x_preferred":[
        "\u06a4\u06c6\u0633\u062a\u06c6\u0686\u0646\u06cc"
    ],
    "name:fas_x_preferred":[
        "\u0648\u0648\u0633\u062a\u0648\u0686\u0646\u06cc\u06cc"
    ],
    "name:kir_x_preferred":[
        "\u041a\u043e\u0448-\u0411\u0443\u043b\u0430\u043a"
    ],
    "name:rus_x_preferred":[
        "\u0412\u043e\u0441\u0442\u043e\u0447\u043d\u044b\u0439"
    ],
    "name:und_x_variant":[
        "Vostochnyy"
    ],
    "name:uzb_x_preferred":[
        "Vostochniy"
    ],
    "wof:name":"Koshbulak",
    "wof:placetype":"locality"
},
  "geometry": {"coordinates":[69.64860999999999,39.92224],"type":"Point"}
}