{
  "type": "Feature",
  "properties": {
    "gn:admin1_code":"09",
    "gn:asciiname":"Mazar-Sarkent",
    "gn:country_code":"KG",
    "gn:dem":2579,
    "gn:feature_class":"P",
    "gn:feature_code":"PPL",
    "gn:name":"Mazar-Sarkent",
    "gn:population":0,
    "gn:timezone":"Asia/Bishkek",
    "iso:country":"KG",
    "name:kir_x_preferred":[
        "\u041c\u0430\u0437\u0430\u0440-\u0421\u0430\u0440\u043a\u0435\u043d\u0442"
    ],
    "name:rus_x_preferred":[
        "\u041c\u0430\u0437\u0430\u0440-\u0421\u0430\u0440\u043a\u0435\u043d\u0442"
    ],
    "wof:name":"Mazar-Sarkent",
    "wof:placetype":"locality"
},
  "geometry": {"coordinates":[69.586,39.66203],"type":"Point"}
}