{
  "type": "Feature",
  "properties": {
    "gn:admin1_code":"07",
    "gn:asciiname":"Dzhergalan",
    "gn:country_code":"KG",
    "gn:dem":2326,
    "gn:feature_class":"P",
    "gn:feature_code":"PPL",
    "gn:name":"Dzhergalan",
    "gn:population":0,
    "gn:timezone":"Asia/Bishkek",
    "iso:country":"KG",
    "name:kir_x_preferred":[
        "\u0416\u0435\u0440\u0433\u0430\u043b\u0430\u043d"
    ],
    "name:rus_x_preferred":[
        "\u0414\u0436\u0435\u0440\u0433\u0430\u043b\u0430\u043d"
    ],
    "name:und_x_variant":[
        "Dzhirgala",
        "Dzhargalan",
        "Dzhirgalan",
        "Dzhergalan",
        "Jyrgalang"
    ],
    "wof:name":"Dzhergalan",
    "wof:placetype":"locality"
},
  "geometry": {"coordinates":[79.02800000000001,42.60356],"type":"Point"}
}