{
  "type": "Feature",
  "properties": {
    "gn:admin1_code":"08",
    "gn:asciiname":"Kyz-Emchek",
    "gn:country_code":"KG",
    "gn:dem":1772,
    "gn:feature_class":"P",
    "gn:feature_code":"PPL",
    "gn:name":"Kyz-Emchek",
    "gn:population":0,
    "gn:timezone":"Asia/Bishkek",
    "iso:country":"KG",
    "name:kir_x_preferred":[
        "\u041a\u044b\u0437-\u042d\u043c\u0447\u0435\u043a"
    ],
    "name:rus_x_preferred":[
        "\u041a\u044b\u0437-\u042d\u043c\u0447\u0435\u043a"
    ],
    "wof:name":"Kyz-Emchek",
    "wof:placetype":"locality"
},
  "geometry": {"coordinates":[73.50095,40.34731],"type":"Point"}
}