{
  "type": "Feature",
  "properties": {
    "gn:admin1_code":"03",
    "gn:asciiname":"Kanjyga",
    "gn:country_code":"KG",
    "gn:dem":1743,
    "gn:feature_class":"P",
    "gn:feature_code":"PPL",
    "gn:name":"Kanjyga",
    "gn:population":0,
    "gn:timezone":"Asia/Bishkek",
    "iso:country":"KG",
    "name:kir_x_preferred":[
        "\u041a\u0430\u043d\u0436\u044b\u0433\u0430"
    ],
    "name:rus_x_preferred":[
        "\u041a\u0430\u043d\u0434\u0436\u044b\u0433\u0430"
    ],
    "name:und_x_variant":[
        "Kandzhyga"
    ],
    "wof:name":"Kanjyga",
    "wof:placetype":"locality"
},
  "geometry": {"coordinates":[73.53182,41.10952],"type":"Point"}
}