{
  "type": "Feature",
  "properties": {
    "gn:admin1_code":"07",
    "gn:asciiname":"Syuttubulak",
    "gn:country_code":"KG",
    "gn:dem":2064,
    "gn:feature_class":"P",
    "gn:feature_code":"PPL",
    "gn:name":"Syuttubulak",
    "gn:population":0,
    "gn:timezone":"Asia/Bishkek",
    "iso:country":"KG",
    "name:kir_x_preferred":[
        "\u0421\u04af\u0442\u04af\u04af-\u0411\u0443\u043b\u0430\u043a"
    ],
    "name:rus_x_preferred":[
        "\u0421\u044e\u0442\u0442\u0443\u0431\u0443\u043b\u0430\u043a"
    ],
    "wof:name":"Syuttubulak",
    "wof:placetype":"locality"
},
  "geometry": {"coordinates":[78.12886,42.32293],"type":"Point"}
}