{
  "type": "Feature",
  "properties": {
    "gn:admin1_code":"09",
    "gn:asciiname":"Kochoboyu",
    "gn:country_code":"KG",
    "gn:dem":1155,
    "gn:feature_class":"P",
    "gn:feature_code":"PPL",
    "gn:name":"Kochoboyu",
    "gn:population":0,
    "gn:timezone":"Asia/Bishkek",
    "iso:country":"KG",
    "name:kir_x_preferred":[
        "\u041a\u043e\u0447\u043e\u0431\u043e\u044e"
    ],
    "name:rus_x_preferred":[
        "\u041a\u043e\u0447\u043e\u0431\u043e\u044e"
    ],
    "wof:name":"Kochoboyu",
    "wof:placetype":"locality"
},
  "geometry": {"coordinates":[70.5158,39.94781],"type":"Point"}
}