{
  "type": "Feature",
  "properties": {
    "gn:admin1_code":"03",
    "gn:asciiname":"Aktash",
    "gn:country_code":"KG",
    "gn:dem":1640,
    "gn:feature_class":"P",
    "gn:feature_code":"PPL",
    "gn:name":"Aktash",
    "gn:population":0,
    "gn:timezone":"Asia/Bishkek",
    "iso:country":"KG",
    "name:kir_x_preferred":[
        "\u0410\u043a-\u0422\u0430\u0448"
    ],
    "name:rus_x_preferred":[
        "\u0410\u043a\u0442\u0430\u0448"
    ],
    "wof:name":"Aktash",
    "wof:placetype":"locality"
},
  "geometry": {"coordinates":[72.08332,41.69264],"type":"Point"}
}