{
  "type": "Feature",
  "properties": {
    "gn:admin1_code":"08",
    "gn:asciiname":"Konduk",
    "gn:country_code":"KG",
    "gn:dem":1965,
    "gn:feature_class":"P",
    "gn:feature_code":"PPL",
    "gn:name":"Konduk",
    "gn:population":0,
    "gn:timezone":"Asia/Bishkek",
    "iso:country":"KG",
    "name:kir_x_preferred":[
        "\u041a\u043e\u043d\u0434\u0443\u043a"
    ],
    "name:rus_x_preferred":[
        "\u041a\u043e\u043d\u0434\u0443\u043a"
    ],
    "name:und_x_variant":[
        "K\u00f6ngd\u00fck"
    ],
    "wof:name":"Konduk",
    "wof:placetype":"locality"
},
  "geometry": {"coordinates":[74.11622,40.46052],"type":"Point"}
}