{
  "type": "Feature",
  "properties": {
    "gn:admin1_code":"08",
    "gn:asciiname":"Soku-Tash",
    "gn:country_code":"KG",
    "gn:dem":1632,
    "gn:feature_class":"P",
    "gn:feature_code":"PPL",
    "gn:name":"Soku-Tash",
    "gn:population":0,
    "gn:timezone":"Asia/Bishkek",
    "iso:country":"KG",
    "name:kir_x_preferred":[
        "\u0421\u043e\u043a\u0443-\u0422\u0430\u0448"
    ],
    "name:rus_x_preferred":[
        "\u0421\u043e\u043a\u0443-\u0422\u0430\u0448"
    ],
    "wof:name":"Soku-Tash",
    "wof:placetype":"locality"
},
  "geometry": {"coordinates":[73.48696,40.25457],"type":"Point"}
}