{
  "type": "Feature",
  "properties": {
    "gn:admin1_code":"09",
    "gn:asciiname":"Sary-Kamysh",
    "gn:country_code":"KG",
    "gn:dem":1267,
    "gn:feature_class":"P",
    "gn:feature_code":"PPL",
    "gn:name":"Sary-Kamysh",
    "gn:population":0,
    "gn:timezone":"Asia/Bishkek",
    "iso:country":"KG",
    "name:kir_x_preferred":[
        "\u0421\u0430\u0440\u044b-\u041a\u0430\u043c\u044b\u0448"
    ],
    "name:rus_x_preferred":[
        "\u0421\u0430\u0440\u044b-\u041a\u0430\u043c\u044b\u0448"
    ],
    "name:uzb_x_preferred":[
        "Sariqamish"
    ],
    "wof:name":"Sary-Kamysh",
    "wof:placetype":"locality"
},
  "geometry": {"coordinates":[71.17896999999998,40.12069],"type":"Point"}
}