{
  "type": "Feature",
  "properties": {
    "gn:admin1_code":"03",
    "gn:asciiname":"Ketmen-Tobo",
    "gn:country_code":"KG",
    "gn:dem":1111,
    "gn:feature_class":"P",
    "gn:feature_code":"PPL",
    "gn:name":"Ketmen-T\u00f6b\u00f6",
    "gn:population":0,
    "gn:timezone":"Asia/Bishkek",
    "iso:country":"KG",
    "name:kir_x_preferred":[
        "\u041a\u0435\u0442\u043c\u0435\u043d-\u0422\u04e9\u0431\u04e9"
    ],
    "name:rus_x_preferred":[
        "Zimov\u2019ye Dzhiyde"
    ],
    "name:rus_x_variant":[
        "\u0417\u0438\u043c\u043e\u0432\u044c\u0435 \u0414\u0436\u0438\u0439\u0434\u0435"
    ],
    "name:und_x_variant":[
        "Ketmen-T\u00f6b\u00f6"
    ],
    "wof:name":"Ketmen-Tobo",
    "wof:placetype":"locality"
},
  "geometry": {"coordinates":[73.12872,41.73153],"type":"Point"}
}