{
  "type": "Feature",
  "properties": {
    "gn:admin1_code":"03",
    "gn:asciiname":"Kurpak-Korgon",
    "gn:country_code":"KG",
    "gn:dem":614,
    "gn:feature_class":"P",
    "gn:feature_code":"PPL",
    "gn:name":"Kurpak-Korgon",
    "gn:population":0,
    "gn:timezone":"Asia/Bishkek",
    "iso:country":"KG",
    "name:kir_x_preferred":[
        "\u041a\u0443\u0440\u043f\u0430\u043a-\u041a\u043e\u0440\u0433\u043e\u043d"
    ],
    "name:rus_x_preferred":[
        "\u041a\u0443\u0440\u043f\u0430\u043a-\u041a\u043e\u0440\u0433\u043e\u043d"
    ],
    "name:und_x_variant":[
        "Podachi",
        "Kurpak-Korgon"
    ],
    "name:uzb_x_preferred":[
        "Ko\u2018rpak-Qo\u2018rg\u2018on"
    ],
    "wof:name":"Kurpak-Korgon",
    "wof:placetype":"locality"
},
  "geometry": {"coordinates":[72.65009000000001,40.96552],"type":"Point"}
}