{
  "type": "Feature",
  "properties": {
    "gn:admin1_code":"07",
    "gn:asciiname":"Baetovka",
    "gn:country_code":"KG",
    "gn:dem":1645,
    "gn:feature_class":"P",
    "gn:feature_code":"PPL",
    "gn:name":"Baetovka",
    "gn:population":0,
    "gn:timezone":"Asia/Bishkek",
    "iso:country":"KG",
    "name:kir_x_preferred":[
        "Baetovka"
    ],
    "name:rus_x_preferred":[
        "\u0411\u0430\u0435\u0442\u043e\u0432\u043a\u0430"
    ],
    "name:und_x_variant":[
        "Bayetovka"
    ],
    "wof:name":"Baetovka",
    "wof:placetype":"locality"
},
  "geometry": {"coordinates":[76.97429,42.61889],"type":"Point"}
}