{
  "type": "Feature",
  "properties": {
    "gn:admin1_code":"02",
    "gn:asciiname":"Kayyrma",
    "gn:country_code":"KG",
    "gn:dem":1279,
    "gn:feature_class":"P",
    "gn:feature_code":"PPL",
    "gn:name":"Kayyrma",
    "gn:population":0,
    "gn:timezone":"Asia/Bishkek",
    "iso:country":"KG",
    "name:kir_x_preferred":[
        "\u041a\u0430\u0439\u044b\u0440\u043c\u0430"
    ],
    "name:rus_x_preferred":[
        "\u041a\u0430\u0439\u044b\u0440\u043c\u0430"
    ],
    "wof:name":"Kayyrma",
    "wof:placetype":"locality"
},
  "geometry": {"coordinates":[75.39631999999997,42.69316],"type":"Point"}
}