{
  "type": "Feature",
  "properties": {
    "gn:admin1_code":"08",
    "gn:asciiname":"Sary-Bulak",
    "gn:country_code":"KG",
    "gn:dem":2425,
    "gn:feature_class":"P",
    "gn:feature_code":"PPL",
    "gn:name":"Sary-Bulak",
    "gn:population":0,
    "gn:timezone":"Asia/Bishkek",
    "iso:country":"KG",
    "name:kir_x_preferred":[
        "\u0421\u0430\u0440\u044b-\u0411\u0443\u043b\u0430\u043a"
    ],
    "name:rus_x_preferred":[
        "\u0421\u0430\u0440\u044b-\u0411\u0443\u043b\u0430\u043a"
    ],
    "wof:name":"Sary-Bulak",
    "wof:placetype":"locality"
},
  "geometry": {"coordinates":[72.00881,39.50335],"type":"Point"}
}