{
  "type": "Feature",
  "properties": {
    "gn:admin1_code":"02",
    "gn:asciiname":"Sadovoye",
    "gn:country_code":"KG",
    "gn:dem":726,
    "gn:feature_class":"P",
    "gn:feature_code":"PPL",
    "gn:name":"Sadovoye",
    "gn:population":0,
    "gn:timezone":"Asia/Bishkek",
    "iso:country":"KG",
    "name:kir_x_preferred":[
        "\u0421\u0430\u0434\u043e\u0432\u043e\u0435"
    ],
    "name:rus_x_preferred":[
        "\u0421\u0430\u0434\u043e\u0432\u043e\u0435"
    ],
    "wof:name":"Sadovoye",
    "wof:placetype":"locality"
},
  "geometry": {"coordinates":[74.17255,42.85399],"type":"Point"}
}