{
  "type": "Feature",
  "properties": {
    "gn:admin1_code":"04",
    "gn:asciiname":"Talabulak",
    "gn:country_code":"KG",
    "gn:dem":2347,
    "gn:feature_class":"P",
    "gn:feature_code":"PPL",
    "gn:name":"Talabulak",
    "gn:population":0,
    "gn:timezone":"Asia/Bishkek",
    "iso:country":"KG",
    "name:kir_x_preferred":[
        "\u0422\u0430\u043b\u0430-\u0411\u0443\u043b\u0430\u043a"
    ],
    "name:rus_x_preferred":[
        "\u0422\u0430\u043b\u0430\u0431\u0443\u043b\u0430\u043a"
    ],
    "wof:name":"Talabulak",
    "wof:placetype":"locality"
},
  "geometry": {"coordinates":[75.24525,42.27658],"type":"Point"}
}