{
  "type": "Feature",
  "properties": {
    "iso:country":"KG",
    "name:ceb_x_preferred":[
        "Kemin"
    ],
    "name:ckb_x_preferred":[
        "\u06a9\u06ce\u0645\u06cc\u0646"
    ],
    "name:deu_x_preferred":[
        "Kemin"
    ],
    "name:eng_x_preferred":[
        "Kemin"
    ],
    "name:fas_x_preferred":[
        "\u06a9\u0645\u06cc\u0646\u060c \u0642\u0631\u0642\u06cc\u0632\u0633\u062a\u0627\u0646"
    ],
    "name:fas_x_variant":[
        "\u06a9\u0645\u06cc\u0646"
    ],
    "name:fra_x_preferred":[
        "Kemin"
    ],
    "name:hsb_x_preferred":[
        "Kemin"
    ],
    "name:ita_x_preferred":[
        "Kemin"
    ],
    "name:kaz_x_preferred":[
        "\u041a\u0435\u043c\u0438\u043d"
    ],
    "name:kir_x_preferred":[
        "\u041a\u0435\u043c\u0438\u043d"
    ],
    "name:nld_x_preferred":[
        "Kemin"
    ],
    "name:pol_x_preferred":[
        "Kemin"
    ],
    "name:rup_x_preferred":[
        "Kemin"
    ],
    "name:rus_x_preferred":[
        "\u0411\u044b\u0441\u0442\u0440\u043e\u0432\u043a\u0430"
    ],
    "name:rus_x_variant":[
        "\u041a\u0435\u043c\u0438\u043d"
    ],
    "name:sco_x_preferred":[
        "Kemin"
    ],
    "name:swe_x_preferred":[
        "Bystrovka"
    ],
    "name:tat_x_preferred":[
        "\u041a\u0438\u043c\u0438\u043d"
    ],
    "name:tur_x_preferred":[
        "Kemin"
    ],
    "name:und_x_variant":[
        "Bystrorechenskoye"
    ],
    "name:uzb_x_preferred":[
        "Kemin"
    ],
    "name:zho_x_preferred":[
        "\u51ef\u660e"
    ],
    "qs:gn_country":"KG",
    "qs:gn_fcode":"PPLA2",
    "qs:gn_pop":10295,
    "qs:name":"Bystrovka",
    "qs:name_adm0":"Kyrgyzstan",
    "qs:name_adm1":"Chuy",
    "qs:photos":0,
    "qs:photos_1k":0,
    "qs:photos_9k":1,
    "qs:photos_9r":1,
    "qs:photos_all":12,
    "qs:photos_sr":0,
    "qs:placetype":"Town",
    "qs:pop_sr":"6",
    "qs:woe_adm0":23424864,
    "wof:name":"Bystrovka",
    "wof:placetype":"locality",
    "wof:population":10295
},
  "geometry": {"coordinates":[75.68917,42.78458],"type":"Point"}
}