{
  "type": "Feature",
  "properties": {
    "gn:asciiname":"Alykulova",
    "gn:country_code":"KG",
    "gn:dem":754,
    "gn:feature_class":"P",
    "gn:feature_code":"PPL",
    "gn:name":"Alykulova",
    "gn:population":0,
    "gn:timezone":"Asia/Bishkek",
    "iso:country":"KG",
    "wof:name":"Alykulova",
    "wof:placetype":"locality"
},
  "geometry": {"coordinates":[72.7325,41.06278],"type":"Point"}
}