{
  "type": "Feature",
  "properties": {
    "gn:admin1_code":"08",
    "gn:asciiname":"Imeni Kalinina",
    "gn:country_code":"KG",
    "gn:dem":2534,
    "gn:feature_class":"P",
    "gn:feature_code":"PPL",
    "gn:name":"Imeni Kalinina",
    "gn:population":0,
    "gn:timezone":"Asia/Bishkek",
    "iso:country":"KG",
    "name:kir_x_preferred":[
        "\u041a\u0430\u043b\u0438\u043d\u0438\u043d\u0430"
    ],
    "name:rus_x_preferred":[
        "\u0418\u043c\u0435\u043d\u0438 \u041a\u0430\u043b\u0438\u043d\u0438\u043d\u0430"
    ],
    "name:und_x_variant":[
        "Kugart",
        "Kel\u2019techaty",
        "Imeni Kalinina"
    ],
    "wof:name":"Imeni Kalinina",
    "wof:placetype":"locality"
},
  "geometry": {"coordinates":[74.42891,40.32728],"type":"Point"}
}