{
  "type": "Feature",
  "properties": {
    "gn:admin1_code":"06",
    "gn:asciiname":"May",
    "gn:country_code":"KG",
    "gn:dem":714,
    "gn:feature_class":"P",
    "gn:feature_code":"PPL",
    "gn:name":"May",
    "gn:population":0,
    "gn:timezone":"Asia/Bishkek",
    "iso:country":"KG",
    "name:kir_x_preferred":[
        "\u041c\u0430\u0439"
    ],
    "name:rus_x_preferred":[
        "\u041c\u0430\u0439\u0441\u043a\u043e\u0435"
    ],
    "name:und_x_variant":[
        "Mayskoye"
    ],
    "wof:name":"May",
    "wof:placetype":"locality"
},
  "geometry": {"coordinates":[71.48205,42.7716],"type":"Point"}
}