{
  "type": "Feature",
  "properties": {
    "gn:admin1_code":"03",
    "gn:asciiname":"Arkalyk",
    "gn:country_code":"KG",
    "gn:dem":667,
    "gn:feature_class":"P",
    "gn:feature_code":"PPL",
    "gn:name":"Arkalyk",
    "gn:population":0,
    "gn:timezone":"Asia/Bishkek",
    "iso:country":"KG",
    "name:kir_x_preferred":[
        "\u0410\u0440\u043a\u0430\u043b\u044b\u043a"
    ],
    "name:rus_x_preferred":[
        "\u0410\u0440\u043a\u0430\u043b\u044b\u043a"
    ],
    "wof:name":"Arkalyk",
    "wof:placetype":"locality"
},
  "geometry": {"coordinates":[72.72403,40.97484],"type":"Point"}
}