{
  "type": "Feature",
  "properties": {
    "gn:admin1_code":"03",
    "gn:asciiname":"Arkalyk",
    "gn:country_code":"KG",
    "gn:dem":667,
    "gn:feature_class":"P",
    "gn:feature_code":"PPL",
    "gn:name":"Arkalyk",
    "gn:population":0,
    "gn:timezone":"Asia/Bishkek",
    "iso:country":"KG",
    "name:ara_x_preferred":[
        "\u0623\u0631\u0643\u0627\u0644\u064a\u0643"
    ],
    "name:bak_x_preferred":[
        "\u0410\u0440\u04a1\u0430\u043b\u044b\u04a1"
    ],
    "name:cat_x_preferred":[
        "Arkalik"
    ],
    "name:ceb_x_preferred":[
        "Arkalyk"
    ],
    "name:ces_x_preferred":[
        "Arkalyk"
    ],
    "name:ckb_x_preferred":[
        "\u0626\u0627\u0631\u0642\u0627\u0644\u0642"
    ],
    "name:deu_x_preferred":[
        "Arqalyq"
    ],
    "name:eus_x_preferred":[
        "Arkalyk"
    ],
    "name:fas_x_preferred":[
        "\u0622\u0631\u0642\u0627\u0644\u06cc\u0642"
    ],
    "name:fra_x_preferred":[
        "Arkalyk"
    ],
    "name:hsb_x_preferred":[
        "Arkalyk"
    ],
    "name:ita_x_preferred":[
        "Arkalyk"
    ],
    "name:jpn_x_preferred":[
        "\u30a2\u30eb\u30ab\u30eb\u30a4\u30af"
    ],
    "name:kat_x_preferred":[
        "\u10d0\u10e0\u10d9\u10d0\u10da\u10d8\u10d9\u10d8"
    ],
    "name:kaz_x_preferred":[
        "\u0410\u0440\u049b\u0430\u043b\u044b\u049b"
    ],
    "name:kir_x_preferred":[
        "\u0410\u0440\u043a\u0430\u043b\u044b\u043a"
    ],
    "name:kor_x_preferred":[
        "\uc544\ub974\uce7c\ub9ac\ud06c"
    ],
    "name:lit_x_preferred":[
        "Arkalykas"
    ],
    "name:nld_x_preferred":[
        "Arkalyk"
    ],
    "name:pol_x_preferred":[
        "Arka\u0142yk"
    ],
    "name:por_x_preferred":[
        "Arkalyk"
    ],
    "name:rus_x_preferred":[
        "\u0410\u0440\u043a\u0430\u043b\u044b\u043a"
    ],
    "name:slk_x_preferred":[
        "Arkalyk"
    ],
    "name:spa_x_preferred":[
        "Arkalyk"
    ],
    "name:swe_x_preferred":[
        "Arqalyq"
    ],
    "name:tat_x_preferred":[
        "\u0410\u0440\u043a\u0430\u043b\u044b\u043a"
    ],
    "name:ukr_x_preferred":[
        "\u0410\u0440\u043a\u0430\u043b\u0438\u043a"
    ],
    "name:urd_x_preferred":[
        "\u0622\u0631\u0642\u0627\u0644\u06cc\u0642"
    ],
    "name:uzb_x_preferred":[
        "Orqaliq"
    ],
    "name:vie_x_preferred":[
        "Arkalyk"
    ],
    "name:zho_x_preferred":[
        "\u963f\u5c14\u5361\u96f7\u514b"
    ],
    "wof:name":"Arkalyk",
    "wof:placetype":"locality"
},
  "geometry": {"coordinates":[72.72403,40.97484],"type":"Point"}
}