{
  "type": "Feature",
  "properties": {
    "gn:admin1_code":"03",
    "gn:asciiname":"Kypchak-Talaa",
    "gn:country_code":"KG",
    "gn:dem":702,
    "gn:feature_class":"P",
    "gn:feature_code":"PPL",
    "gn:name":"Kypchak-Talaa",
    "gn:population":0,
    "gn:timezone":"Asia/Bishkek",
    "iso:country":"KG",
    "name:kir_x_preferred":[
        "\u041a\u044b\u043f\u0447\u0430\u043a-\u0422\u0430\u043b\u0430\u0430"
    ],
    "name:rus_x_preferred":[
        "\u041a\u044b\u043f\u0447\u0430\u043a-\u0422\u0430\u043b\u0430\u0430"
    ],
    "name:und_x_variant":[
        "Sarybiya"
    ],
    "wof:name":"Kypchak-Talaa",
    "wof:placetype":"locality"
},
  "geometry": {"coordinates":[72.35455,41.09239],"type":"Point"}
}