{
  "type": "Feature",
  "properties": {
    "iso:country":"KG",
    "name:ara_x_preferred":[
        "\u0643\u064a\u0632\u064a\u0644-\u0633\u0648"
    ],
    "name:arz_x_preferred":[
        "\u0643\u064a\u0632\u064a\u0644 \u0633\u0648"
    ],
    "name:bel_x_preferred":[
        "\u041a\u044b\u0437\u044b\u043b-\u0421\u0443\u0443"
    ],
    "name:ceb_x_preferred":[
        "Kyzyl-Suu"
    ],
    "name:che_x_preferred":[
        "\u041a\u044b\u0437\u044b\u043b-\u0421\u0443\u0443"
    ],
    "name:ckb_x_preferred":[
        "\u0642\u0632\u0644\u0633\u0648\u060c \u0642\u0631\u063a\u06cc\u0632\u0633\u062a\u0627\u0646"
    ],
    "name:ckb_x_variant":[
        "\u0642\u0632\u0644\u0633\u0648"
    ],
    "name:deu_x_preferred":[
        "Kyzyl-Suu"
    ],
    "name:eng_x_preferred":[
        "Kyzyl-Suu"
    ],
    "name:est_x_preferred":[
        "K\u00f5z\u00f5lsuu"
    ],
    "name:fas_x_preferred":[
        "\u0642\u06cc\u0632\u06cc\u0644\u0633\u0648\u060c \u0642\u0631\u0642\u06cc\u0632\u0633\u062a\u0627\u0646"
    ],
    "name:fas_x_variant":[
        "\u0642\u06cc\u0632\u06cc\u0644\u0633\u0648"
    ],
    "name:fra_x_preferred":[
        "Kyzyl-Suu"
    ],
    "name:ita_x_preferred":[
        "Kyzyl-Suu"
    ],
    "name:kir_x_preferred":[
        "\u041a\u044b\u0437\u044b\u043b-\u0421\u0443\u0443"
    ],
    "name:nld_x_preferred":[
        "Kyzyl-Suu"
    ],
    "name:rup_x_preferred":[
        "Kyzyl-Suu"
    ],
    "name:rus_x_preferred":[
        "\u041f\u043e\u043a\u0440\u043e\u0432\u043a\u0430"
    ],
    "name:rus_x_variant":[
        "\u041a\u044b\u0437\u044b\u043b-\u0421\u0443\u0443"
    ],
    "name:swe_x_preferred":[
        "Pokrovka"
    ],
    "name:tur_x_preferred":[
        "K\u0131z\u0131l-Su"
    ],
    "name:und_x_variant":[
        "Nov Pokrovka"
    ],
    "name:zho_x_preferred":[
        "\u514b\u5b5c\u52d2\u2027\u8607"
    ],
    "qs:gn_country":"KG",
    "qs:gn_fcode":"PPLA2",
    "qs:gn_pop":16927,
    "qs:name":"Pokrovka",
    "qs:name_adm0":"Kyrgyzstan",
    "qs:name_adm1":"Ysyk-Kol",
    "qs:photos":0,
    "qs:photos_1k":0,
    "qs:photos_9k":1,
    "qs:photos_9r":1,
    "qs:photos_all":5,
    "qs:photos_sr":0,
    "qs:placetype":"Town",
    "qs:pop_sr":"6",
    "qs:woe_adm0":23424864,
    "wof:name":"Pokrovka",
    "wof:placetype":"locality",
    "wof:population":16927
},
  "geometry": {"coordinates":[78.00644,42.34211],"type":"Point"}
}