{
  "type": "Feature",
  "properties": {
    "gn:admin1_code":"09",
    "gn:asciiname":"Kalacha",
    "gn:country_code":"KG",
    "gn:dem":921,
    "gn:feature_class":"P",
    "gn:feature_code":"PPL",
    "gn:name":"Kalacha",
    "gn:population":0,
    "gn:timezone":"Asia/Bishkek",
    "iso:country":"KG",
    "name:rus_x_preferred":[
        "\u041a\u0430\u043b\u0430\u0447\u0430"
    ],
    "name:uzb_x_preferred":[
        "Qal-Acha"
    ],
    "wof:name":"Kalacha",
    "wof:placetype":"locality"
},
  "geometry": {"coordinates":[72.05318,40.25774000000001],"type":"Point"}
}