{
  "type": "Feature",
  "properties": {
    "gn:admin1_code":"00",
    "gn:asciiname":"Kichik-Alay",
    "gn:country_code":"KG",
    "gn:dem":1847,
    "gn:feature_class":"P",
    "gn:feature_code":"PPL",
    "gn:name":"Kichik-Alay",
    "gn:population":0,
    "gn:timezone":"Asia/Bishkek",
    "iso:country":"KG",
    "name:kir_x_preferred":[
        "\u041a\u0438\u0447\u0438\u043a-\u0410\u043b\u0430\u0439"
    ],
    "name:kir_x_variant":[
        "\u041a\u0438\u0447\u0438-\u0410\u043b\u0430\u0439"
    ],
    "name:uzb_x_preferred":[
        "Kichik-Oloy"
    ],
    "wof:name":"Kichik-Alay",
    "wof:placetype":"locality"
},
  "geometry": {"coordinates":[72.92161999999998,40.02492],"type":"Point"}
}