{
  "type": "Feature",
  "properties": {
    "gn:admin1_code":"00",
    "gn:asciiname":"Chilandy",
    "gn:country_code":"KG",
    "gn:dem":1799,
    "gn:feature_class":"P",
    "gn:feature_code":"PPL",
    "gn:name":"Chilandy",
    "gn:population":0,
    "gn:timezone":"Asia/Bishkek",
    "iso:country":"KG",
    "wof:name":"Chilandy",
    "wof:placetype":"locality"
},
  "geometry": {"coordinates":[72.18333,39.91667],"type":"Point"}
}