{
  "type": "Feature",
  "properties": {
    "gn:asciiname":"Archa-Beshkik",
    "gn:country_code":"KG",
    "gn:dem":841,
    "gn:feature_class":"P",
    "gn:feature_code":"PPL",
    "gn:name":"Archa-Beshkik",
    "gn:population":0,
    "gn:timezone":"Asia/Bishkek",
    "iso:country":"KG",
    "wof:name":"Archa-Beshkik",
    "wof:placetype":"locality"
},
  "geometry": {"coordinates":[74.55194,42.82944000000001],"type":"Point"}
}