{
  "type": "Feature",
  "properties": {
    "gn:admin1_code":"03",
    "gn:asciiname":"Zhdanovo",
    "gn:country_code":"KG",
    "gn:dem":1194,
    "gn:feature_class":"P",
    "gn:feature_code":"PPL",
    "gn:name":"Zhdanovo",
    "gn:population":0,
    "gn:timezone":"Asia/Bishkek",
    "iso:country":"KG",
    "name:eng_x_preferred":[
        "Dostuk"
    ],
    "name:kir_x_preferred":[
        "\u0414\u043e\u0441\u0442\u0443\u043a"
    ],
    "name:rus_x_preferred":[
        "\u0416\u0434\u0430\u043d\u043e\u0432\u043e"
    ],
    "wof:name":"Zhdanovo",
    "wof:placetype":"locality"
},
  "geometry": {"coordinates":[71.46108000000002,41.39688],"type":"Point"}
}