{
  "type": "Feature",
  "properties": {
    "gn:admin1_code":"09",
    "gn:asciiname":"Irilesh",
    "gn:country_code":"KG",
    "gn:dem":826,
    "gn:feature_class":"P",
    "gn:feature_code":"PPL",
    "gn:name":"Irilesh",
    "gn:population":0,
    "gn:timezone":"Asia/Bishkek",
    "iso:country":"KG",
    "name:kir_x_preferred":[
        "\u0418\u0440\u0438\u043b\u0435\u0448"
    ],
    "name:rus_x_preferred":[
        "\u0418\u0440\u0438\u043b\u0435\u0448"
    ],
    "wof:name":"Irilesh",
    "wof:placetype":"locality"
},
  "geometry": {"coordinates":[71.65475000000001,40.19392],"type":"Point"}
}