{
  "type": "Feature",
  "properties": {
    "gn:admin1_code":"03",
    "gn:asciiname":"Ajek",
    "gn:country_code":"KG",
    "gn:dem":977,
    "gn:feature_class":"P",
    "gn:feature_code":"PPL",
    "gn:name":"Ajek",
    "gn:population":0,
    "gn:timezone":"Asia/Bishkek",
    "iso:country":"KG",
    "name:kir_x_preferred":[
        "\u0410\u0436\u0435\u043a"
    ],
    "name:rus_x_historical":[
        "Uchastok Nomer Shest\u2019 Sovkhoz Komsomol",
        "\u0423\u0447\u0430\u0441\u0442\u043e\u043a \u041d\u043e\u043c\u0435\u0440 \u0428\u0435\u0441\u0442\u044c \u0421\u043e\u0432\u0445\u043e\u0437 \u041a\u043e\u043c\u0441\u043e\u043c\u043e\u043b"
    ],
    "name:rus_x_preferred":[
        "Uchastok Nomer Shest\u2019 Sovkhoz Komsomol"
    ],
    "name:rus_x_variant":[
        "\u0423\u0447\u0430\u0441\u0442\u043e\u043a \u041d\u043e\u043c\u0435\u0440 \u0428\u0435\u0441\u0442\u044c \u0421\u043e\u0432\u0445\u043e\u0437 \u041a\u043e\u043c\u0441\u043e\u043c\u043e\u043b"
    ],
    "wof:name":"Ajek",
    "wof:placetype":"locality"
},
  "geometry": {"coordinates":[71.38315,41.17685],"type":"Point"}
}