{
  "type": "Feature",
  "properties": {
    "gn:admin1_code":"08",
    "gn:asciiname":"Dzhakshylyk",
    "gn:country_code":"KG",
    "gn:dem":695,
    "gn:feature_class":"P",
    "gn:feature_code":"PPL",
    "gn:name":"Dzhakshylyk",
    "gn:population":0,
    "gn:timezone":"Asia/Bishkek",
    "iso:country":"KG",
    "name:kir_x_preferred":[
        "\u0416\u0430\u043a\u0448\u044b\u043b\u044b\u043a"
    ],
    "name:rus_x_preferred":[
        "\u0414\u0436\u0430\u043a\u0448\u044b\u043b\u044b\u043a"
    ],
    "name:uzb_x_preferred":[
        "Jaqshilik"
    ],
    "wof:name":"Dzhakshylyk",
    "wof:placetype":"locality"
},
  "geometry": {"coordinates":[72.44371,40.52276],"type":"Point"}
}