{
  "type": "Feature",
  "properties": {
    "gn:admin1_code":"00",
    "gn:asciiname":"Emir-Kul'",
    "gn:country_code":"KG",
    "gn:dem":1367,
    "gn:feature_class":"P",
    "gn:feature_code":"PPL",
    "gn:name":"Emir-Kul\u2019",
    "gn:population":0,
    "gn:timezone":"Asia/Bishkek",
    "iso:country":"KG",
    "wof:name":"Emir-Kul'",
    "wof:placetype":"locality"
},
  "geometry": {"coordinates":[73.7008,40.8813],"type":"Point"}
}