{
  "type": "Feature",
  "properties": {
    "gn:admin1_code":"03",
    "gn:asciiname":"Chukurchak",
    "gn:country_code":"KG",
    "gn:dem":1745,
    "gn:feature_class":"P",
    "gn:feature_code":"PPL",
    "gn:name":"Chukurchak",
    "gn:population":0,
    "gn:timezone":"Asia/Bishkek",
    "iso:country":"KG",
    "name:kir_x_preferred":[
        "\u0427\u0443\u043a\u0443\u0440\u0447\u0430\u043a"
    ],
    "name:rus_x_preferred":[
        "\u0427\u0443\u043a\u0443\u0440\u0447\u0430\u043a"
    ],
    "wof:name":"Chukurchak",
    "wof:placetype":"locality"
},
  "geometry": {"coordinates":[71.12253,41.78262],"type":"Point"}
}