{
  "type": "Feature",
  "properties": {
    "gn:admin1_code":"08",
    "gn:asciiname":"Kyrgyz-Ata",
    "gn:country_code":"KG",
    "gn:dem":1600,
    "gn:feature_class":"P",
    "gn:feature_code":"PPL",
    "gn:name":"Kyrgyz-Ata",
    "gn:population":0,
    "gn:timezone":"Asia/Bishkek",
    "iso:country":"KG",
    "name:rus_x_preferred":[
        "\u041a\u044b\u0440\u0433\u044b\u0437-\u0410\u0442\u0430"
    ],
    "wof:name":"Kyrgyz-Ata",
    "wof:placetype":"locality"
},
  "geometry": {"coordinates":[72.682,40.20393],"type":"Point"}
}