{
  "type": "Feature",
  "properties": {
    "gn:admin1_code":"09",
    "gn:asciiname":"Dzhany-Korgon",
    "gn:country_code":"KG",
    "gn:dem":1919,
    "gn:feature_class":"P",
    "gn:feature_code":"PPL",
    "gn:name":"Dzhany-Korgon",
    "gn:population":0,
    "gn:timezone":"Asia/Bishkek",
    "iso:country":"KG",
    "name:kir_x_preferred":[
        "\u0416\u0430\u04a3\u044b-\u041a\u043e\u0440\u0433\u043e\u043d"
    ],
    "name:kir_x_variant":[
        "Djany-Korgon"
    ],
    "name:rus_x_preferred":[
        "\u0414\u0436\u0430\u043d\u044b-\u041a\u043e\u0440\u0433\u043e\u043d"
    ],
    "name:uzb_x_preferred":[
        "Jani-Qo\u2018rg\u2018on"
    ],
    "wof:name":"Dzhany-Korgon",
    "wof:placetype":"locality"
},
  "geometry": {"coordinates":[71.30704,39.92286],"type":"Point"}
}