{
  "type": "Feature",
  "properties": {
    "gn:admin1_code":"09",
    "gn:asciiname":"Bedzhey",
    "gn:country_code":"KG",
    "gn:dem":1527,
    "gn:feature_class":"P",
    "gn:feature_code":"PPL",
    "gn:name":"B\u00ebdzh\u00eby",
    "gn:population":0,
    "gn:timezone":"Asia/Bishkek",
    "iso:country":"KG",
    "name:kir_x_preferred":[
        "\u0411\u04e9\u0436\u04e9\u0439"
    ],
    "name:kir_x_variant":[
        "\u0411\u0451\u0434\u0436\u0451\u0439",
        "Bedjei"
    ],
    "name:rus_x_preferred":[
        "B\u00ebdzh\u00eby"
    ],
    "name:rus_x_variant":[
        "\u0411\u0451\u0434\u0436\u0451\u0439"
    ],
    "name:und_x_variant":[
        "Noygut",
        "Bodzhoy"
    ],
    "name:uzb_x_preferred":[
        "Bo\u2018jo\u2018y"
    ],
    "wof:name":"Bedzhey",
    "wof:placetype":"locality"
},
  "geometry": {"coordinates":[71.21519000000001,40.01199],"type":"Point"}
}