{
  "type": "Feature",
  "properties": {
    "gn:admin1_code":"02",
    "gn:asciiname":"Zavodskoye",
    "gn:country_code":"KG",
    "gn:dem":784,
    "gn:feature_class":"P",
    "gn:feature_code":"PPL",
    "gn:name":"Zavodskoye",
    "gn:population":0,
    "gn:timezone":"Asia/Bishkek",
    "iso:country":"KG",
    "name:rus_x_preferred":[
        "\u0417\u0430\u0432\u043e\u0434\u0441\u043a\u043e\u0435"
    ],
    "wof:name":"Zavodskoye",
    "wof:placetype":"locality"
},
  "geometry": {"coordinates":[74.01371999999998,42.82239000000001],"type":"Point"}
}