{
  "type": "Feature",
  "properties": {
    "gn:admin1_code":"03",
    "gn:asciiname":"Dzhany-Aryk",
    "gn:country_code":"KG",
    "gn:dem":668,
    "gn:feature_class":"P",
    "gn:feature_code":"PPL",
    "gn:name":"Dzhany-Aryk",
    "gn:population":0,
    "gn:timezone":"Asia/Bishkek",
    "iso:country":"KG",
    "name:kir_x_preferred":[
        "\u0414\u0436\u0430\u043d\u044b-\u0410\u0440\u044b\u043a"
    ],
    "name:rus_x_preferred":[
        "\u0414\u0436\u0430\u043d\u044b-\u0410\u0440\u044b\u043a"
    ],
    "name:uzb_x_preferred":[
        "Jani-Ariq"
    ],
    "wof:name":"Dzhany-Aryk",
    "wof:placetype":"locality"
},
  "geometry": {"coordinates":[72.32609000000002,41.0514],"type":"Point"}
}