{
  "type": "Feature",
  "properties": {
    "gn:admin1_code":"02",
    "gn:asciiname":"Kashka-Suu",
    "gn:country_code":"KG",
    "gn:dem":1346,
    "gn:feature_class":"P",
    "gn:feature_code":"PPL",
    "gn:name":"Kashka-Suu",
    "gn:population":0,
    "gn:timezone":"Asia/Bishkek",
    "iso:country":"KG",
    "name:kir_x_preferred":[
        "\u041a\u0430\u0448\u043a\u0430-\u0421\u0443\u0443"
    ],
    "name:rus_x_historical":[
        "\u041c\u0430\u043b\u0438\u043d\u043e\u0432\u043a\u0430"
    ],
    "name:rus_x_preferred":[
        "\u041a\u0430\u0448\u043a\u0430-\u0421\u0443\u0443"
    ],
    "name:rus_x_variant":[
        "\u041c\u0430\u043b\u0438\u043d\u043e\u0432\u043a\u0430"
    ],
    "name:und_x_variant":[
        "Malinovka"
    ],
    "wof:name":"Kashka-Suu",
    "wof:placetype":"locality"
},
  "geometry": {"coordinates":[74.53201999999997,42.6948],"type":"Point"}
}