{
  "type": "Feature",
  "properties": {
    "gn:admin1_code":"08",
    "gn:asciiname":"Kup-Tash",
    "gn:country_code":"KG",
    "gn:dem":2238,
    "gn:feature_class":"P",
    "gn:feature_code":"PPL",
    "gn:name":"Kup-Tash",
    "gn:population":0,
    "gn:timezone":"Asia/Bishkek",
    "iso:country":"KG",
    "name:kir_x_preferred":[
        "\u041a\u0443\u043b-\u0422\u0430\u0448"
    ],
    "name:rus_x_preferred":[
        "\u041a\u0443\u043b-\u0422\u0430\u0448"
    ],
    "wof:name":"Kup-Tash",
    "wof:placetype":"locality"
},
  "geometry": {"coordinates":[74.26271,40.33708],"type":"Point"}
}