{
  "type": "Feature",
  "properties": {
    "gn:admin1_code":"03",
    "gn:asciiname":"Shina",
    "gn:country_code":"KG",
    "gn:dem":815,
    "gn:feature_class":"P",
    "gn:feature_code":"PPL",
    "gn:name":"Shina",
    "gn:population":0,
    "gn:timezone":"Asia/Bishkek",
    "iso:country":"KG",
    "name:kir_x_preferred":[
        "\u0428\u0438\u043d\u0430"
    ],
    "name:rus_x_preferred":[
        "\u0428\u0438\u043d\u0430"
    ],
    "name:und_x_variant":[
        "Chomkamysh"
    ],
    "wof:name":"Shina",
    "wof:placetype":"locality"
},
  "geometry": {"coordinates":[72.16479,41.55619],"type":"Point"}
}