{
  "type": "Feature",
  "properties": {
    "gn:admin1_code":"09",
    "gn:asciiname":"Kara-Suu",
    "gn:country_code":"KG",
    "gn:dem":1388,
    "gn:feature_class":"P",
    "gn:feature_code":"PPL",
    "gn:name":"Kara-Suu",
    "gn:population":0,
    "gn:timezone":"Asia/Bishkek",
    "iso:country":"KG",
    "name:ckb_x_preferred":[
        "\u0642\u0627\u0631\u0627-\u0633\u0648"
    ],
    "name:deu_x_preferred":[
        "Karasuu"
    ],
    "name:est_x_preferred":[
        "Kara-Suu"
    ],
    "name:fas_x_preferred":[
        "\u0642\u0627\u0631\u0627\u0633\u0648"
    ],
    "name:fra_x_preferred":[
        "Kara-Suu"
    ],
    "name:hsb_x_preferred":[
        "Kara-Suu"
    ],
    "name:ita_x_preferred":[
        "Kara-Suu"
    ],
    "name:kir_x_preferred":[
        "\u041a\u0430\u0440\u0430-\u0421\u0443\u0443"
    ],
    "name:kir_x_variant":[
        "\u041a\u0430\u0440\u0430-\u0421\u0443\u0443 \u0448\u0430\u0430\u0440\u044b"
    ],
    "name:lit_x_preferred":[
        "Kara Su"
    ],
    "name:pol_x_preferred":[
        "Karasuu"
    ],
    "name:rus_x_preferred":[
        "\u041a\u0430\u0440\u0430-\u0421\u0443\u0443"
    ],
    "name:sco_x_preferred":[
        "Kara-Suu"
    ],
    "name:spa_x_preferred":[
        "Kara-Suu"
    ],
    "name:tat_x_preferred":[
        "\u041a\u0430\u0440\u0430\u0441\u0443"
    ],
    "name:tur_x_preferred":[
        "Kara-Su"
    ],
    "name:uzb_x_preferred":[
        "Qorasuv"
    ],
    "name:zho_x_preferred":[
        "\u5361\u62c9\u8607"
    ],
    "wof:name":"Kara-Suu",
    "wof:placetype":"locality"
},
  "geometry": {"coordinates":[70.02401999999999,39.87583],"type":"Point"}
}