{
  "type": "Feature",
  "properties": {
    "gn:admin1_code":"09",
    "gn:asciiname":"Kara-Suu",
    "gn:country_code":"KG",
    "gn:dem":1388,
    "gn:feature_class":"P",
    "gn:feature_code":"PPL",
    "gn:name":"Kara-Suu",
    "gn:population":0,
    "gn:timezone":"Asia/Bishkek",
    "iso:country":"KG",
    "name:kir_x_preferred":[
        "\u041a\u0430\u0440\u0430-\u0421\u0443\u0443"
    ],
    "name:rus_x_preferred":[
        "\u041a\u0430\u0440\u0430-\u0421\u0443\u0443"
    ],
    "wof:name":"Kara-Suu",
    "wof:placetype":"locality"
},
  "geometry": {"coordinates":[70.02401999999999,39.87583],"type":"Point"}
}