{
  "type": "Feature",
  "properties": {
    "gn:admin1_code":"02",
    "gn:asciiname":"Kernivoz",
    "gn:country_code":"KG",
    "gn:dem":651,
    "gn:feature_class":"P",
    "gn:feature_code":"PPL",
    "gn:name":"Kernivoz",
    "gn:population":0,
    "gn:timezone":"Asia/Bishkek",
    "iso:country":"KG",
    "name:kir_x_preferred":[
        "\u041a\u0435\u0440\u043d\u0438\u0432\u043e\u0437"
    ],
    "name:rus_x_preferred":[
        "\u041a\u0435\u0440\u043d\u0438\u0432\u043e\u0437"
    ],
    "wof:name":"Kernivoz",
    "wof:placetype":"locality"
},
  "geometry": {"coordinates":[74.52221999999998,43.01877],"type":"Point"}
}