{
  "type": "Feature",
  "properties": {
    "gn:country":"KG",
    "gn:fcode":"PPL",
    "gn:population":5885,
    "iso:country":"KG",
    "name:ceb_x_preferred":[
        "Sosnovka"
    ],
    "name:che_x_preferred":[
        "\u0421\u043e\u0441\u043d\u043e\u0432\u043a\u0430"
    ],
    "name:eng_x_preferred":[
        "Sosnovka"
    ],
    "name:fas_x_preferred":[
        "\u0633\u0648\u0633\u0646\u0648\u0641\u06a9\u0627"
    ],
    "name:kir_x_preferred":[
        "\u0421\u043e\u0441\u043d\u043e\u0432\u043a\u0430"
    ],
    "name:nld_x_preferred":[
        "Sosnovka"
    ],
    "name:rus_x_preferred":[
        "\u0421\u043e\u0441\u043d\u043e\u0432\u043a\u0430"
    ],
    "name:swe_x_preferred":[
        "Sosnovka"
    ],
    "name:uzb_x_preferred":[
        "Sosnovka"
    ],
    "name:zho_x_preferred":[
        "\u7d22\u65af\u8bfa\u592b\u5361"
    ],
    "qs:name":"Sosnovka",
    "qs:photos_9r":0,
    "qs:photos_sr":0,
    "qs:pop_sr":"5",
    "wd:wordcount":4069,
    "wof:name":"Sosnovka",
    "wof:placetype":"locality",
    "wof:population":5885
},
  "geometry": {"coordinates":[73.90572,42.63699],"type":"Point"}
}