{
  "type": "Feature",
  "properties": {
    "gn:admin1_code":"03",
    "gn:asciiname":"Dzharadar",
    "gn:country_code":"KG",
    "gn:dem":1330,
    "gn:feature_class":"P",
    "gn:feature_code":"PPL",
    "gn:name":"Dzharadar",
    "gn:population":0,
    "gn:timezone":"Asia/Bishkek",
    "iso:country":"KG",
    "name:kir_x_preferred":[
        "\u0416\u0430\u0440\u0430\u0434\u0430\u0440"
    ],
    "name:rus_x_preferred":[
        "\u0414\u0436\u0430\u0440\u0430\u0434\u0430\u0440"
    ],
    "wof:name":"Dzharadar",
    "wof:placetype":"locality"
},
  "geometry": {"coordinates":[72.97201,41.32311],"type":"Point"}
}