{
  "type": "Feature",
  "properties": {
    "gn:admin1_code":"04",
    "gn:asciiname":"Kokdzhar",
    "gn:country_code":"KG",
    "gn:dem":1863,
    "gn:feature_class":"P",
    "gn:feature_code":"PPL",
    "gn:name":"Kokdzhar",
    "gn:population":0,
    "gn:timezone":"Asia/Bishkek",
    "iso:country":"KG",
    "name:kir_x_preferred":[
        "\u041a\u04e9\u043a-\u0416\u0430\u0440"
    ],
    "name:rus_x_preferred":[
        "\u041a\u043e\u043a\u0434\u0436\u0430\u0440"
    ],
    "name:und_x_variant":[
        "K\u00ebkdzhar"
    ],
    "wof:name":"Kokdzhar",
    "wof:placetype":"locality"
},
  "geometry": {"coordinates":[75.6516,42.18398],"type":"Point"}
}