{
  "type": "Feature",
  "properties": {
    "gn:admin1_code":"02",
    "gn:asciiname":"Druzhba",
    "gn:country_code":"KG",
    "gn:dem":752,
    "gn:feature_class":"P",
    "gn:feature_code":"PPL",
    "gn:name":"Druzhba",
    "gn:population":0,
    "gn:timezone":"Asia/Almaty",
    "iso:country":"KG",
    "name:kir_x_preferred":[
        "\u0414\u0440\u0443\u0436\u0431\u0430"
    ],
    "name:rus_x_preferred":[
        "\u0414\u0440\u0443\u0436\u0431\u0430"
    ],
    "wof:name":"Druzhba",
    "wof:placetype":"locality"
},
  "geometry": {"coordinates":[75.14936,42.87732000000001],"type":"Point"}
}