{
  "type": "Feature",
  "properties": {
    "gn:admin1_code":"03",
    "gn:asciiname":"Kaynar",
    "gn:country_code":"KG",
    "gn:dem":882,
    "gn:feature_class":"P",
    "gn:feature_code":"PPL",
    "gn:name":"Kaynar",
    "gn:population":0,
    "gn:timezone":"Asia/Bishkek",
    "iso:country":"KG",
    "name:kat_x_preferred":[
        "\u10d9\u10d0\u10d8\u10dc\u10d0\u10e0\u10d8"
    ],
    "name:kir_x_preferred":[
        "\u041a\u0430\u0439\u043d\u0430\u0440"
    ],
    "name:rus_x_preferred":[
        "\u041a\u0430\u0439\u043d\u0430\u0440"
    ],
    "name:tat_x_preferred":[
        "\u041a\u0430\u0439\u043d\u0430\u0440"
    ],
    "name:uzb_x_preferred":[
        "Qaynar"
    ],
    "wof:name":"Kaynar",
    "wof:placetype":"locality"
},
  "geometry": {"coordinates":[73.09044,40.90828],"type":"Point"}
}