{
  "type": "Feature",
  "properties": {
    "gn:admin1_code":"09",
    "gn:asciiname":"Pakhalya",
    "gn:country_code":"KG",
    "gn:dem":1674,
    "gn:feature_class":"P",
    "gn:feature_code":"PPL",
    "gn:name":"Pakhalya",
    "gn:population":0,
    "gn:timezone":"Asia/Bishkek",
    "iso:country":"KG",
    "name:kir_x_preferred":[
        "\u041f\u0430\u0445\u0430\u043b\u044f"
    ],
    "name:rus_x_preferred":[
        "\u041f\u0430\u0445\u0430\u043b\u044f"
    ],
    "name:uzb_x_preferred":[
        "Paxala"
    ],
    "wof:name":"Pakhalya",
    "wof:placetype":"locality"
},
  "geometry": {"coordinates":[71.85615,40.0859],"type":"Point"}
}