{
  "type": "Feature",
  "properties": {
    "gn:admin1_code":"02",
    "gn:asciiname":"Sotsialchi",
    "gn:country_code":"KG",
    "gn:dem":759,
    "gn:feature_class":"P",
    "gn:feature_code":"PPL",
    "gn:name":"Sotsialchi",
    "gn:population":0,
    "gn:timezone":"Asia/Bishkek",
    "iso:country":"KG",
    "name:kir_x_preferred":[
        "\u0421\u043e\u0446\u0438\u0430\u043b\u0447\u0438"
    ],
    "name:rus_x_preferred":[
        "\u0421\u043e\u0446\u0438\u0430\u043b\u0447\u0438"
    ],
    "wof:name":"Sotsialchi",
    "wof:placetype":"locality"
},
  "geometry": {"coordinates":[74.90763000000003,42.86605],"type":"Point"}
}