{
  "type": "Feature",
  "properties": {
    "gn:admin1_code":"02",
    "gn:asciiname":"Dzhel'-Aryk",
    "gn:country_code":"KG",
    "gn:dem":1382,
    "gn:feature_class":"P",
    "gn:feature_code":"PPL",
    "gn:name":"Dzhel\u2019-Aryk",
    "gn:population":0,
    "gn:timezone":"Asia/Bishkek",
    "iso:country":"KG",
    "name:kir_x_preferred":[
        "\u0416\u044d\u043b-\u0410\u0440\u044b\u043a"
    ],
    "name:rus_x_preferred":[
        "Dzhel\u2019-Aryk"
    ],
    "name:rus_x_variant":[
        "\u0414\u0436\u0435\u043b\u044c-\u0410\u0440\u044b\u043a"
    ],
    "wof:name":"Dzhel'-Aryk",
    "wof:placetype":"locality"
},
  "geometry": {"coordinates":[75.89449999999999,42.67658],"type":"Point"}
}