{
  "type": "Feature",
  "properties": {
    "gn:admin1_code":"09",
    "gn:asciiname":"Kek-Talaa",
    "gn:country_code":"KG",
    "gn:dem":756,
    "gn:feature_class":"P",
    "gn:feature_code":"PPL",
    "gn:name":"K\u00ebk-Talaa",
    "gn:population":0,
    "gn:timezone":"Asia/Bishkek",
    "iso:country":"KG",
    "name:kir_x_preferred":[
        "\u041a\u04e9\u043a-\u0422\u0430\u043b\u0430\u0430"
    ],
    "name:kir_x_variant":[
        "Kok-Talaa"
    ],
    "name:rus_x_preferred":[
        "K\u00ebk-Talaa"
    ],
    "name:rus_x_variant":[
        "\u041a\u0451\u043a-\u0422\u0430\u043b\u0430\u0430"
    ],
    "name:uzb_x_preferred":[
        "Keq-Talaa"
    ],
    "wof:name":"Kek-Talaa",
    "wof:placetype":"locality"
},
  "geometry": {"coordinates":[71.85786,40.23941],"type":"Point"}
}