{
  "type": "Feature",
  "properties": {
    "gn:admin1_code":"02",
    "gn:asciiname":"Sveklopunkt",
    "gn:country_code":"KG",
    "gn:dem":1195,
    "gn:feature_class":"P",
    "gn:feature_code":"PPL",
    "gn:name":"Sveklopunkt",
    "gn:population":0,
    "gn:timezone":"Asia/Bishkek",
    "iso:country":"KG",
    "name:kir_x_preferred":[
        "\u0421\u0435\u0441\u044b\u043a-\u0411\u0443\u043b\u0430\u043a"
    ],
    "name:rus_x_preferred":[
        "\u0421\u0432\u0435\u043a\u043b\u043e\u043f\u0443\u043d\u043a\u0442"
    ],
    "wof:name":"Sveklopunkt",
    "wof:placetype":"locality"
},
  "geometry": {"coordinates":[75.7647,42.76335],"type":"Point"}
}