{
  "type": "Feature",
  "properties": {
    "gn:admin1_code":"02",
    "gn:asciiname":"Imeni Gagarina",
    "gn:country_code":"KG",
    "gn:dem":776,
    "gn:feature_class":"P",
    "gn:feature_code":"PPL",
    "gn:name":"Imeni Gagarina",
    "gn:population":0,
    "gn:timezone":"Asia/Bishkek",
    "iso:country":"KG",
    "name:kir_x_preferred":[
        "\u0418\u043c\u0435\u043d\u0438 \u0413\u0430\u0433\u0430\u0440\u0438\u043d\u0430"
    ],
    "name:rus_x_preferred":[
        "\u0418\u043c\u0435\u043d\u0438 \u0413\u0430\u0433\u0430\u0440\u0438\u043d\u0430"
    ],
    "wof:name":"Imeni Gagarina",
    "wof:placetype":"locality"
},
  "geometry": {"coordinates":[74.90089999999999,42.84588],"type":"Point"}
}