{
  "type": "Feature",
  "properties": {
    "gn:admin1_code":"09",
    "gn:asciiname":"Kara-Tangi",
    "gn:country_code":"KG",
    "gn:dem":1581,
    "gn:feature_class":"P",
    "gn:feature_code":"PPL",
    "gn:name":"Kara-Tangi",
    "gn:population":0,
    "gn:timezone":"Asia/Bishkek",
    "iso:country":"KG",
    "name:kir_x_preferred":[
        "\u041a\u0430\u0440\u0430-\u0422\u0430\u043d\u0433\u0438"
    ],
    "name:rus_x_preferred":[
        "\u041a\u0430\u0440\u0430-\u0422\u0430\u043d\u0433\u0438"
    ],
    "name:uzb_x_preferred":[
        "Qora-Tangi"
    ],
    "wof:name":"Kara-Tangi",
    "wof:placetype":"locality"
},
  "geometry": {"coordinates":[71.38633,40.10364000000001],"type":"Point"}
}