{
  "type": "Feature",
  "properties": {
    "gn:admin1_code":"07",
    "gn:asciiname":"Koshtebe",
    "gn:country_code":"KG",
    "gn:dem":1681,
    "gn:feature_class":"P",
    "gn:feature_code":"PPL",
    "gn:name":"Kosht\u00ebb\u00eb",
    "gn:population":0,
    "gn:timezone":"Asia/Bishkek",
    "iso:country":"KG",
    "name:kir_x_preferred":[
        "\u041a\u043e\u0448-\u0414\u04e9\u0431\u04e9"
    ],
    "name:rus_x_preferred":[
        "Kosht\u00ebb\u00eb"
    ],
    "name:rus_x_variant":[
        "\u041a\u043e\u0448\u0442\u0451\u0431\u0451"
    ],
    "wof:name":"Koshtebe",
    "wof:placetype":"locality"
},
  "geometry": {"coordinates":[78.51586,42.703],"type":"Point"}
}